Workbook

Sheet Data Entry
A2: Yom | B2: Art no. | C2: Item | D2: Quality | E2: Supplier | F2: Description | G2: Cost | H2: Increase | I2: Expenses | J2: Total Cost | K2: Net Price Credit | L2: Wsp | M2: Mrp | N2: Net Cash | O2: South | P2: Amazon | Q2: With Box | S2: Value | T2: Box Price for pc. | W2: Box price | X2: Box price | AD2: Item | AH2: Price
A3: 2026 | B3: 203 | C3: shawl | D3: Kashmiri | F3: shahtoosh | G3: 205 | I3: 85 | J3: =IF(SUMIF(G3:I3,"<>")=0,"",SUM(G3:I3)) -> 290 | K3: =IF(ISNUMBER(L3), IF(CEILING(ROUND(L3*0.95,2),5)=420, 425, CEILING(ROUND(L3*0.95,2),5) ), "" ) -> 380 | L3: =IF(ISNUMBER(J3), IF(CEILING(ROUND(J3*1.35,2),5)=420, 425, CEILING(ROUND(J3*1.35,2),5) ), "" ) -> 395 | M3: =IF(AND(ISNUMBER(J3),ISNUMBER(G3)), IF( CEILING( ROUND((J3*1.5) * IF(J3*1.5 <= 2500, 1.05, 1.18), 2), IF(ROUND((J3*1.5) * IF(J3*1.5 <= 2500, 1.05, 1.18), 2) < 2500, 25, 50) )=420, 425, CEILING( ROUND((J3*1.5) * IF(J3*1.5 <= 2500, 1.05, 1.18), 2), IF(ROUND((J3*1.5) * IF(J3*1.5 <= 2500, 1.05, 1.18), 2) < 2500, 25, 50) ) ), "" ) -> 475 | N3: =IF(ISNUMBER(G3), CEILING(ROUND(L3*0.92,2),5), "") -> 365 | O3: =IF(ISNUMBER(L3), IF(CEILING(ROUND(L3*1.07,2),5)=420, 425, CEILING(ROUND(L3*1.07,2),5) ), "" ) -> 425 | P3: =IF((((G3*1.5)+50)/0.835)<2500, MROUND(((((G3*1.5)+50)/0.835)*1.05)*2,10), MROUND(((((G3*1.5)+50)/0.835)*1.18)*2,10)) -> 900 | Q3: =IF($S$3="","", MROUND( IF($S$3="m", IF($T$3=1, Price35[[#This Row],[Mrp]]+$W$4, Price35[[#This Row],[Mrp]]+$X$4), IF($S$3="nc", IF($T$3=1, Price35[[#This Row],[Net Cash]]+$W$5, Price35[[#This Row],[Net Cash]]+$X$5), IF($S$3="npc", IF($T$3=1, Price35[[#This Row],[Net Price Credit]]+$W$6, Price35[[#This Row],[Net Price Credit]]+$X$6), IF($S$3="w", IF($T$3=1, Price35[[#This Row],[Wsp]]+$W$6, Price35[[#This Row],[Wsp]]+$X$6), "")))), 10)) -> 550 | S3: m | T3: 1 | W3: 1 | X3: 2 | AD3: cashmilon cloth | AH3: 440/- kg
A4: 2026 | B4: 208 | C4: shawl | D4: Kashmiri | F4: variety | G4: 205 | I4: 160 | J4: =IF(SUMIF(G4:I4,"<>")=0,"",SUM(G4:I4)) -> 365 | K4: =IF(ISNUMBER(L4), IF(CEILING(ROUND(L4*0.95,2),5)=420, 425, CEILING(ROUND(L4*0.95,2),5) ), "" ) -> 475 | L4: =IF(ISNUMBER(J4), IF(CEILING(ROUND(J4*1.35,2),5)=420, 425, CEILING(ROUND(J4*1.35,2),5) ), "" ) -> 495 | M4: =IF(AND(ISNUMBER(J4),ISNUMBER(G4)), IF( CEILING( ROUND((J4*1.5) * IF(J4*1.5 <= 2500, 1.05, 1.18), 2), IF(ROUND((J4*1.5) * IF(J4*1.5 <= 2500, 1.05, 1.18), 2) < 2500, 25, 50) )=420, 425, CEILING( ROUND((J4*1.5) * IF(J4*1.5 <= 2500, 1.05, 1.18), 2), IF(ROUND((J4*1.5) * IF(J4*1.5 <= 2500, 1.05, 1.18), 2) < 2500, 25, 50) ) ), "" ) -> 575 | N4: =IF(ISNUMBER(G4), CEILING(ROUND(L4*0.92,2),5), "") -> 460 | O4: =IF(ISNUMBER(L4), IF(CEILING(ROUND(L4*1.07,2),5)=420, 425, CEILING(ROUND(L4*1.07,2),5) ), "" ) -> 530 | P4: =IF((((G4*1.5)+50)/0.835)<2500, MROUND(((((G4*1.5)+50)/0.835)*1.05)*2,10), MROUND(((((G4*1.5)+50)/0.835)*1.18)*2,10)) -> 900 | Q4: =IF($S$3="","", MROUND( IF($S$3="m", IF($T$3=1, Price35[[#This Row],[Mrp]]+$W$4, Price35[[#This Row],[Mrp]]+$X$4), IF($S$3="nc", IF($T$3=1, Price35[[#This Row],[Net Cash]]+$W$5, Price35[[#This Row],[Net Cash]]+$X$5), IF($S$3="npc", IF($T$3=1, Price35[[#This Row],[Net Price Credit]]+$W$6, Price35[[#This Row],[Net Price Credit]]+$X$6), IF($S$3="w", IF($T$3=1, Price35[[#This Row],[Wsp]]+$W$6, Price35[[#This Row],[Wsp]]+$X$6), "")))), 10)) -> 650 | W4: 70 | X4: 35 | Y4: m=mrp | AD4: s/s pure dyed | AH4: 2500/-
A5: 2026 | B5: 215 | C5: shawl | D5: Kashmiri | F5: multihead neem dour 350 gm | G5: 205 | I5: 265 | J5: =IF(SUMIF(G5:I5,"<>")=0,"",SUM(G5:I5)) -> 470 | K5: =IF(ISNUMBER(L5), IF(CEILING(ROUND(L5*0.95,2),5)=420, 425, CEILING(ROUND(L5*0.95,2),5) ), "" ) -> 605 | L5: =IF(ISNUMBER(J5), IF(CEILING(ROUND(J5*1.35,2),5)=420, 425, CEILING(ROUND(J5*1.35,2),5) ), "" ) -> 635 | M5: =IF(AND(ISNUMBER(J5),ISNUMBER(G5)), IF( CEILING( ROUND((J5*1.5) * IF(J5*1.5 <= 2500, 1.05, 1.18), 2), IF(ROUND((J5*1.5) * IF(J5*1.5 <= 2500, 1.05, 1.18), 2) < 2500, 25, 50) )=420, 425, CEILING( ROUND((J5*1.5) * IF(J5*1.5 <= 2500, 1.05, 1.18), 2), IF(ROUND((J5*1.5) * IF(J5*1.5 <= 2500, 1.05, 1.18), 2) < 2500, 25, 50) ) ), "" ) -> 750 | N5: =IF(ISNUMBER(G5), CEILING(ROUND(L5*0.92,2),5), "") -> 585 | O5: =IF(ISNUMBER(L5), IF(CEILING(ROUND(L5*1.07,2),5)=420, 425, CEILING(ROUND(L5*1.07,2),5) ), "" ) -> 680 | P5: =IF((((G5*1.5)+50)/0.835)<2500, MROUND(((((G5*1.5)+50)/0.835)*1.05)*2,10), MROUND(((((G5*1.5)+50)/0.835)*1.18)*2,10)) -> 900 | Q5: =IF($S$3="","", MROUND( IF($S$3="m", IF($T$3=1, Price35[[#This Row],[Mrp]]+$W$4, Price35[[#This Row],[Mrp]]+$X$4), IF($S$3="nc", IF($T$3=1, Price35[[#This Row],[Net Cash]]+$W$5, Price35[[#This Row],[Net Cash]]+$X$5), IF($S$3="npc", IF($T$3=1, Price35[[#This Row],[Net Price Credit]]+$W$6, Price35[[#This Row],[Net Price Credit]]+$X$6), IF($S$3="w", IF($T$3=1, Price35[[#This Row],[Wsp]]+$W$6, Price35[[#This Row],[Wsp]]+$X$6), "")))), 10)) -> 820 | W5: 56 | X5: 28 | Y5: nc=net cash | AD5: s/s pure white | AH5: 2300/-
A6: 2026 | B6: 216 | C6: shawl | D6: Kashmiri | F6: multihead variety new | G6: 205 | I6: 223 | J6: =IF(SUMIF(G6:I6,"<>")=0,"",SUM(G6:I6)) -> 428 | K6: =IF(ISNUMBER(L6), IF(CEILING(ROUND(L6*0.95,2),5)=420, 425, CEILING(ROUND(L6*0.95,2),5) ), "" ) -> 555 | L6: =IF(ISNUMBER(J6), IF(CEILING(ROUND(J6*1.35,2),5)=420, 425, CEILING(ROUND(J6*1.35,2),5) ), "" ) -> 580 | M6: =IF(AND(ISNUMBER(J6),ISNUMBER(G6)), IF( CEILING( ROUND((J6*1.5) * IF(J6*1.5 <= 2500, 1.05, 1.18), 2), IF(ROUND((J6*1.5) * IF(J6*1.5 <= 2500, 1.05, 1.18), 2) < 2500, 25, 50) )=420, 425, CEILING( ROUND((J6*1.5) * IF(J6*1.5 <= 2500, 1.05, 1.18), 2), IF(ROUND((J6*1.5) * IF(J6*1.5 <= 2500, 1.05, 1.18), 2) < 2500, 25, 50) ) ), "" ) -> 675 | N6: =IF(ISNUMBER(G6), CEILING(ROUND(L6*0.92,2),5), "") -> 535 | O6: =IF(ISNUMBER(L6), IF(CEILING(ROUND(L6*1.07,2),5)=420, 425, CEILING(ROUND(L6*1.07,2),5) ), "" ) -> 625 | P6: =IF((((G6*1.5)+50)/0.835)<2500, MROUND(((((G6*1.5)+50)/0.835)*1.05)*2,10), MROUND(((((G6*1.5)+50)/0.835)*1.18)*2,10)) -> 900 | Q6: =IF($S$3="","", MROUND( IF($S$3="m", IF($T$3=1, Price35[[#This Row],[Mrp]]+$W$4, Price35[[#This Row],[Mrp]]+$X$4), IF($S$3="nc", IF($T$3=1, Price35[[#This Row],[Net Cash]]+$W$5, Price35[[#This Row],[Net Cash]]+$X$5), IF($S$3="npc", IF($T$3=1, Price35[[#This Row],[Net Price Credit]]+$W$6, Price35[[#This Row],[Net Price Credit]]+$X$6), IF($S$3="w", IF($T$3=1, Price35[[#This Row],[Wsp]]+$W$6, Price35[[#This Row],[Wsp]]+$X$6), "")))), 10)) -> 750 | W6: 58 | X6: 29 | Y6: npc= net credit | AD6: fine wool dyed | AH6: 3600/-
A7: 2026 | B7: 291 | C7: shawl | D7: Kashmiri | F7: shahtoosh 50 *100 | G7: 285 | I7: 375 | J7: =IF(SUMIF(G7:I7,"<>")=0,"",SUM(G7:I7)) -> 660 | K7: =IF(ISNUMBER(L7), IF(CEILING(ROUND(L7*0.95,2),5)=420, 425, CEILING(ROUND(L7*0.95,2),5) ), "" ) -> 855 | L7: =IF(ISNUMBER(J7), IF(CEILING(ROUND(J7*1.35,2),5)=420, 425, CEILING(ROUND(J7*1.35,2),5) ), "" ) -> 895 | M7: =IF(AND(ISNUMBER(J7),ISNUMBER(G7)), IF( CEILING( ROUND((J7*1.5) * IF(J7*1.5 <= 2500, 1.05, 1.18), 2), IF(ROUND((J7*1.5) * IF(J7*1.5 <= 2500, 1.05, 1.18), 2) < 2500, 25, 50) )=420, 425, CEILING( ROUND((J7*1.5) * IF(J7*1.5 <= 2500, 1.05, 1.18), 2), IF(ROUND((J7*1.5) * IF(J7*1.5 <= 2500, 1.05, 1.18), 2) < 2500, 25, 50) ) ), "" ) -> 1050 | N7: =IF(ISNUMBER(G7), CEILING(ROUND(L7*0.92,2),5), "") -> 825 | O7: =IF(ISNUMBER(L7), IF(CEILING(ROUND(L7*1.07,2),5)=420, 425, CEILING(ROUND(L7*1.07,2),5) ), "" ) -> 960 | P7: =IF((((G7*1.5)+50)/0.835)<2500, MROUND(((((G7*1.5)+50)/0.835)*1.05)*2,10), MROUND(((((G7*1.5)+50)/0.835)*1.18)*2,10)) -> 1200 | Q7: =IF($S$3="","", MROUND( IF($S$3="m", IF($T$3=1, Price35[[#This Row],[Mrp]]+$W$4, Price35[[#This Row],[Mrp]]+$X$4), IF($S$3="nc", IF($T$3=1, Price35[[#This Row],[Net Cash]]+$W$5, Price35[[#This Row],[Net Cash]]+$X$5), IF($S$3="npc", IF($T$3=1, Price35[[#This Row],[Net Price Credit]]+$W$6, Price35[[#This Row],[Net Price Credit]]+$X$6), IF($S$3="w", IF($T$3=1, Price35[[#This Row],[Wsp]]+$W$6, Price35[[#This Row],[Wsp]]+$X$6), "")))), 10)) -> 1120 | W7: 60 | X7: 30 | Y7: W = WSP | AD7: fine wool white | AH7: 3400/-
A8: 2026 | B8: 292 | C8: shawl | D8: Kashmiri | F8: c.n.d 50 * 100 cashmilon | G8: 285 | I8: 375 | J8: =IF(SUMIF(G8:I8,"<>")=0,"",SUM(G8:I8)) -> 660 | K8: =IF(ISNUMBER(L8), IF(CEILING(ROUND(L8*0.95,2),5)=420, 425, CEILING(ROUND(L8*0.95,2),5) ), "" ) -> 855 | L8: =IF(ISNUMBER(J8), IF(CEILING(ROUND(J8*1.35,2),5)=420, 425, CEILING(ROUND(J8*1.35,2),5) ), "" ) -> 895 | M8: =IF(AND(ISNUMBER(J8),ISNUMBER(G8)), IF( CEILING( ROUND((J8*1.5) * IF(J8*1.5 <= 2500, 1.05, 1.18), 2), IF(ROUND((J8*1.5) * IF(J8*1.5 <= 2500, 1.05, 1.18), 2) < 2500, 25, 50) )=420, 425, CEILING( ROUND((J8*1.5) * IF(J8*1.5 <= 2500, 1.05, 1.18), 2), IF(ROUND((J8*1.5) * IF(J8*1.5 <= 2500, 1.05, 1.18), 2) < 2500, 25, 50) ) ), "" ) -> 1050 | N8: =IF(ISNUMBER(G8), CEILING(ROUND(L8*0.92,2),5), "") -> 825 | O8: =IF(ISNUMBER(L8), IF(CEILING(ROUND(L8*1.07,2),5)=420, 425, CEILING(ROUND(L8*1.07,2),5) ), "" ) -> 960 | P8: =IF((((G8*1.5)+50)/0.835)<2500, MROUND(((((G8*1.5)+50)/0.835)*1.05)*2,10), MROUND(((((G8*1.5)+50)/0.835)*1.18)*2,10)) -> 1200 | Q8: =IF($S$3="","", MROUND( IF($S$3="m", IF($T$3=1, Price35[[#This Row],[Mrp]]+$W$4, Price35[[#This Row],[Mrp]]+$X$4), IF($S$3="nc", IF($T$3=1, Price35[[#This Row],[Net Cash]]+$W$5, Price35[[#This Row],[Net Cash]]+$X$5), IF($S$3="npc", IF($T$3=1, Price35[[#This Row],[Net Price Credit]]+$W$6, Price35[[#This Row],[Net Price Credit]]+$X$6), IF($S$3="w", IF($T$3=1, Price35[[#This Row],[Wsp]]+$W$6, Price35[[#This Row],[Wsp]]+$X$6), "")))), 10)) -> 1120 | AD8: 2/72 white | AH8: 1075/-
B9: 101 | C9: shawl | D9: Wool | F9: plain 40 x 80 | G9: 380 | I9: 20 | J9: =IF(SUMIF(G9:I9,"<>")=0,"",SUM(G9:I9)) -> 400 | K9: =IF(ISNUMBER(L9), IF(CEILING(ROUND(L9*0.95,2),5)=420, 425, CEILING(ROUND(L9*0.95,2),5) ), "" ) -> 515 | L9: =IF(ISNUMBER(J9), IF(CEILING(ROUND(J9*1.35,2),5)=420, 425, CEILING(ROUND(J9*1.35,2),5) ), "" ) -> 540 | M9: =IF(AND(ISNUMBER(J9),ISNUMBER(G9)), IF( CEILING( ROUND((J9*1.5) * IF(J9*1.5 <= 2500, 1.05, 1.18), 2), IF(ROUND((J9*1.5) * IF(J9*1.5 <= 2500, 1.05, 1.18), 2) < 2500, 25, 50) )=420, 425, CEILING( ROUND((J9*1.5) * IF(J9*1.5 <= 2500, 1.05, 1.18), 2), IF(ROUND((J9*1.5) * IF(J9*1.5 <= 2500, 1.05, 1.18), 2) < 2500, 25, 50) ) ), "" ) -> 650 | N9: =IF(ISNUMBER(G9), CEILING(ROUND(L9*0.92,2),5), "") -> 500 | O9: =IF(ISNUMBER(L9), IF(CEILING(ROUND(L9*1.07,2),5)=420, 425, CEILING(ROUND(L9*1.07,2),5) ), "" ) -> 580 | P9: =IF((((G9*1.5)+50)/0.835)<2500, MROUND(((((G9*1.5)+50)/0.835)*1.05)*2,10), MROUND(((((G9*1.5)+50)/0.835)*1.18)*2,10)) -> 1560 | Q9: =IF($S$3="","", MROUND( IF($S$3="m", IF($T$3=1, Price35[[#This Row],[Mrp]]+$W$4, Price35[[#This Row],[Mrp]]+$X$4), IF($S$3="nc", IF($T$3=1, Price35[[#This Row],[Net Cash]]+$W$5, Price35[[#This Row],[Net Cash]]+$X$5), IF($S$3="npc", IF($T$3=1, Price35[[#This Row],[Net Price Credit]]+$W$6, Price35[[#This Row],[Net Price Credit]]+$X$6), IF($S$3="w", IF($T$3=1, Price35[[#This Row],[Wsp]]+$W$6, Price35[[#This Row],[Wsp]]+$X$6), "")))), 10)) -> 720 | AD9: 2/72 dyed | AH9: 1125/-
B10: 102 | C10: shawl | D10: wool | E10: Usha | F10: s.s tape 40 | G10: 380 | I10: 15 | J10: =IF(SUMIF(G10:I10,"<>")=0,"",SUM(G10:I10)) -> 395 | K10: =IF(ISNUMBER(L10), IF(CEILING(ROUND(L10*0.95,2),5)=420, 425, CEILING(ROUND(L10*0.95,2),5) ), "" ) -> 510 | L10: =IF(ISNUMBER(J10), IF(CEILING(ROUND(J10*1.35,2),5)=420, 425, CEILING(ROUND(J10*1.35,2),5) ), "" ) -> 535 | M10: =IF(AND(ISNUMBER(J10),ISNUMBER(G10)), IF( CEILING( ROUND((J10*1.5) * IF(J10*1.5 <= 2500, 1.05, 1.18), 2), IF(ROUND((J10*1.5) * IF(J10*1.5 <= 2500, 1.05, 1.18), 2) < 2500, 25, 50) )=420, 425, CEILING( ROUND((J10*1.5) * IF(J10*1.5 <= 2500, 1.05, 1.18), 2), IF(ROUND((J10*1.5) * IF(J10*1.5 <= 2500, 1.05, 1.18), 2) < 2500, 25, 50) ) ), "" ) -> 625 | N10: =IF(ISNUMBER(G10), CEILING(ROUND(L10*0.92,2),5), "") -> 495 | O10: =IF(ISNUMBER(L10), IF(CEILING(ROUND(L10*1.07,2),5)=420, 425, CEILING(ROUND(L10*1.07,2),5) ), "" ) -> 575 | P10: =IF((((G10*1.5)+50)/0.835)<2500, MROUND(((((G10*1.5)+50)/0.835)*1.05)*2,10), MROUND(((((G10*1.5)+50)/0.835)*1.18)*2,10)) -> 1560 | Q10: =IF($S$3="","", MROUND( IF($S$3="m", IF($T$3=1, Price35[[#This Row],[Mrp]]+$W$4, Price35[[#This Row],[Mrp]]+$X$4), IF($S$3="nc", IF($T$3=1, Price35[[#This Row],[Net Cash]]+$W$5, Price35[[#This Row],[Net Cash]]+$X$5), IF($S$3="npc", IF($T$3=1, Price35[[#This Row],[Net Price Credit]]+$W$6, Price35[[#This Row],[Net Price Credit]]+$X$6), IF($S$3="w", IF($T$3=1, Price35[[#This Row],[Wsp]]+$W$6, Price35[[#This Row],[Wsp]]+$X$6), "")))), 10)) -> 700
A11: 2026 | B11: 150 | C11: Lohi | D11: Fine Wool | E11: ankur | F11: fine wool 270 gm | G11: 970 | H11: 300 | I11: 60 | J11: =IF(SUMIF(G11:I11,"<>")=0,"",SUM(G11:I11)) -> 1330 | K11: =IF(ISNUMBER(L11), IF(CEILING(ROUND(L11*0.95,2),5)=420, 425, CEILING(ROUND(L11*0.95,2),5) ), "" ) -> 1710 | L11: =IF(ISNUMBER(J11), IF(CEILING(ROUND(J11*1.35,2),5)=420, 425, CEILING(ROUND(J11*1.35,2),5) ), "" ) -> 1800 | M11: =IF(AND(ISNUMBER(J11),ISNUMBER(G11)), IF( CEILING( ROUND((J11*1.5) * IF(J11*1.5 <= 2500, 1.05, 1.18), 2), IF(ROUND((J11*1.5) * IF(J11*1.5 <= 2500, 1.05, 1.18), 2) < 2500, 25, 50) )=420, 425, CEILING( ROUND((J11*1.5) * IF(J11*1.5 <= 2500, 1.05, 1.18), 2), IF(ROUND((J11*1.5) * IF(J11*1.5 <= 2500, 1.05, 1.18), 2) < 2500, 25, 50) ) ), "" ) -> 2100 | N11: =IF(ISNUMBER(G11), CEILING(ROUND(L11*0.92,2),5), "") -> 1660 | O11: =IF(ISNUMBER(L11), IF(CEILING(ROUND(L11*1.07,2),5)=420, 425, CEILING(ROUND(L11*1.07,2),5) ), "" ) -> 1930 | P11: =IF((((G11*1.5)+50)/0.835)<2500, MROUND(((((G11*1.5)+50)/0.835)*1.05)*2,10), MROUND(((((G11*1.5)+50)/0.835)*1.18)*2,10)) -> 3790 | Q11: =IF($S$3="","", MROUND( IF($S$3="m", IF($T$3=1, Price35[[#This Row],[Mrp]]+$W$4, Price35[[#This Row],[Mrp]]+$X$4), IF($S$3="nc", IF($T$3=1, Price35[[#This Row],[Net Cash]]+$W$5, Price35[[#This Row],[Net Cash]]+$X$5), IF($S$3="npc", IF($T$3=1, Price35[[#This Row],[Net Price Credit]]+$W$6, Price35[[#This Row],[Net Price Credit]]+$X$6), IF($S$3="w", IF($T$3=1, Price35[[#This Row],[Wsp]]+$W$6, Price35[[#This Row],[Wsp]]+$X$6), "")))), 10)) -> 2170
A12: 2026 | B12: 160 | C12: shawl | D12: Fine Wool | F12: solo Plain 40*80 shawl weight 225 gm | G12: 630 | I12: 60 | J12: =IF(SUMIF(G12:I12,"<>")=0,"",SUM(G12:I12)) -> 690 | K12: =IF(ISNUMBER(L12), IF(CEILING(ROUND(L12*0.95,2),5)=420, 425, CEILING(ROUND(L12*0.95,2),5) ), "" ) -> 890 | L12: =IF(ISNUMBER(J12), IF(CEILING(ROUND(J12*1.35,2),5)=420, 425, CEILING(ROUND(J12*1.35,2),5) ), "" ) -> 935 | M12: =IF(AND(ISNUMBER(J12),ISNUMBER(G12)), IF( CEILING( ROUND((J12*1.5) * IF(J12*1.5 <= 2500, 1.05, 1.18), 2), IF(ROUND((J12*1.5) * IF(J12*1.5 <= 2500, 1.05, 1.18), 2) < 2500, 25, 50) )=420, 425, CEILING( ROUND((J12*1.5) * IF(J12*1.5 <= 2500, 1.05, 1.18), 2), IF(ROUND((J12*1.5) * IF(J12*1.5 <= 2500, 1.05, 1.18), 2) < 2500, 25, 50) ) ), "" ) -> 1100 | N12: =IF(ISNUMBER(G12), CEILING(ROUND(L12*0.92,2),5), "") -> 865 | O12: =IF(ISNUMBER(L12), IF(CEILING(ROUND(L12*1.07,2),5)=420, 425, CEILING(ROUND(L12*1.07,2),5) ), "" ) -> 1005 | P12: =IF((((G12*1.5)+50)/0.835)<2500, MROUND(((((G12*1.5)+50)/0.835)*1.05)*2,10), MROUND(((((G12*1.5)+50)/0.835)*1.18)*2,10)) -> 2500 | Q12: =IF($S$3="","", MROUND( IF($S$3="m", IF($T$3=1, Price35[[#This Row],[Mrp]]+$W$4, Price35[[#This Row],[Mrp]]+$X$4), IF($S$3="nc", IF($T$3=1, Price35[[#This Row],[Net Cash]]+$W$5, Price35[[#This Row],[Net Cash]]+$X$5), IF($S$3="npc", IF($T$3=1, Price35[[#This Row],[Net Price Credit]]+$W$6, Price35[[#This Row],[Net Price Credit]]+$X$6), IF($S$3="w", IF($T$3=1, Price35[[#This Row],[Wsp]]+$W$6, Price35[[#This Row],[Wsp]]+$X$6), "")))), 10)) -> 1170
A13: 2026 | B13: 161 | C13: shawl | D13: Fine Wool | E13: ankur | F13: 2/90 fine wool weight 180 gm | G13: 650 | I13: 60 | J13: =IF(SUMIF(G13:I13,"<>")=0,"",SUM(G13:I13)) -> 710 | K13: =IF(ISNUMBER(L13), IF(CEILING(ROUND(L13*0.95,2),5)=420, 425, CEILING(ROUND(L13*0.95,2),5) ), "" ) -> 915 | L13: =IF(ISNUMBER(J13), IF(CEILING(ROUND(J13*1.35,2),5)=420, 425, CEILING(ROUND(J13*1.35,2),5) ), "" ) -> 960 | M13: =IF(AND(ISNUMBER(J13),ISNUMBER(G13)), IF( CEILING( ROUND((J13*1.5) * IF(J13*1.5 <= 2500, 1.05, 1.18), 2), IF(ROUND((J13*1.5) * IF(J13*1.5 <= 2500, 1.05, 1.18), 2) < 2500, 25, 50) )=420, 425, CEILING( ROUND((J13*1.5) * IF(J13*1.5 <= 2500, 1.05, 1.18), 2), IF(ROUND((J13*1.5) * IF(J13*1.5 <= 2500, 1.05, 1.18), 2) < 2500, 25, 50) ) ), "" ) -> 1125 | N13: =IF(ISNUMBER(G13), CEILING(ROUND(L13*0.92,2),5), "") -> 885 | O13: =IF(ISNUMBER(L13), IF(CEILING(ROUND(L13*1.07,2),5)=420, 425, CEILING(ROUND(L13*1.07,2),5) ), "" ) -> 1030 | P13: =IF((((G13*1.5)+50)/0.835)<2500, MROUND(((((G13*1.5)+50)/0.835)*1.05)*2,10), MROUND(((((G13*1.5)+50)/0.835)*1.18)*2,10)) -> 2580 | Q13: =IF($S$3="","", MROUND( IF($S$3="m", IF($T$3=1, Price35[[#This Row],[Mrp]]+$W$4, Price35[[#This Row],[Mrp]]+$X$4), IF($S$3="nc", IF($T$3=1, Price35[[#This Row],[Net Cash]]+$W$5, Price35[[#This Row],[Net Cash]]+$X$5), IF($S$3="npc", IF($T$3=1, Price35[[#This Row],[Net Price Credit]]+$W$6, Price35[[#This Row],[Net Price Credit]]+$X$6), IF($S$3="w", IF($T$3=1, Price35[[#This Row],[Wsp]]+$W$6, Price35[[#This Row],[Wsp]]+$X$6), "")))), 10)) -> 1200
A14: 2026 | B14: 170 | C14: Lohi | D14: Fine Wool | F14: toosha gents plain 350 gm | G14: 980 | H14: 170 | I14: 60 | J14: =IF(SUMIF(G14:I14,"<>")=0,"",SUM(G14:I14)) -> 1210 | K14: =IF(ISNUMBER(L14), IF(CEILING(ROUND(L14*0.95,2),5)=420, 425, CEILING(ROUND(L14*0.95,2),5) ), "" ) -> 1555 | L14: =IF(ISNUMBER(J14), IF(CEILING(ROUND(J14*1.35,2),5)=420, 425, CEILING(ROUND(J14*1.35,2),5) ), "" ) -> 1635 | M14: =IF(AND(ISNUMBER(J14),ISNUMBER(G14)), IF( CEILING( ROUND((J14*1.5) * IF(J14*1.5 <= 2500, 1.05, 1.18), 2), IF(ROUND((J14*1.5) * IF(J14*1.5 <= 2500, 1.05, 1.18), 2) < 2500, 25, 50) )=420, 425, CEILING( ROUND((J14*1.5) * IF(J14*1.5 <= 2500, 1.05, 1.18), 2), IF(ROUND((J14*1.5) * IF(J14*1.5 <= 2500, 1.05, 1.18), 2) < 2500, 25, 50) ) ), "" ) -> 1925 | N14: =IF(ISNUMBER(G14), CEILING(ROUND(L14*0.92,2),5), "") -> 1505 | O14: =IF(ISNUMBER(L14), IF(CEILING(ROUND(L14*1.07,2),5)=420, 425, CEILING(ROUND(L14*1.07,2),5) ), "" ) -> 1750 | P14: =IF((((G14*1.5)+50)/0.835)<2500, MROUND(((((G14*1.5)+50)/0.835)*1.05)*2,10), MROUND(((((G14*1.5)+50)/0.835)*1.18)*2,10)) -> 3820 | Q14: =IF($S$3="","", MROUND( IF($S$3="m", IF($T$3=1, Price35[[#This Row],[Mrp]]+$W$4, Price35[[#This Row],[Mrp]]+$X$4), IF($S$3="nc", IF($T$3=1, Price35[[#This Row],[Net Cash]]+$W$5, Price35[[#This Row],[Net Cash]]+$X$5), IF($S$3="npc", IF($T$3=1, Price35[[#This Row],[Net Price Credit]]+$W$6, Price35[[#This Row],[Net Price Credit]]+$X$6), IF($S$3="w", IF($T$3=1, Price35[[#This Row],[Wsp]]+$W$6, Price35[[#This Row],[Wsp]]+$X$6), "")))), 10)) -> 2000
B15: 193 | C15: Lohi | D15: Fine Wool | E15: gaurav | F15: 120 count fine wool lohi | G15: 2500 | I15: 25 | J15: =IF(SUMIF(G15:I15,"<>")=0,"",SUM(G15:I15)) -> 2525 | K15: =IF(ISNUMBER(L15), IF(CEILING(ROUND(L15*0.95,2),5)=420, 425, CEILING(ROUND(L15*0.95,2),5) ), "" ) -> 3240 | L15: =IF(ISNUMBER(J15), IF(CEILING(ROUND(J15*1.35,2),5)=420, 425, CEILING(ROUND(J15*1.35,2),5) ), "" ) -> 3410 | M15: =IF(AND(ISNUMBER(J15),ISNUMBER(G15)), IF( CEILING( ROUND((J15*1.5) * IF(J15*1.5 <= 2500, 1.05, 1.18), 2), IF(ROUND((J15*1.5) * IF(J15*1.5 <= 2500, 1.05, 1.18), 2) < 2500, 25, 50) )=420, 425, CEILING( ROUND((J15*1.5) * IF(J15*1.5 <= 2500, 1.05, 1.18), 2), IF(ROUND((J15*1.5) * IF(J15*1.5 <= 2500, 1.05, 1.18), 2) < 2500, 25, 50) ) ), "" ) -> 4500 | N15: =IF(ISNUMBER(G15), CEILING(ROUND(L15*0.92,2),5), "") -> 3140 | O15: =IF(ISNUMBER(L15), IF(CEILING(ROUND(L15*1.07,2),5)=420, 425, CEILING(ROUND(L15*1.07,2),5) ), "" ) -> 3650 | P15: =IF((((G15*1.5)+50)/0.835)<2500, MROUND(((((G15*1.5)+50)/0.835)*1.05)*2,10), MROUND(((((G15*1.5)+50)/0.835)*1.18)*2,10)) -> 10740 | Q15: =IF($S$3="","", MROUND( IF($S$3="m", IF($T$3=1, Price35[[#This Row],[Mrp]]+$W$4, Price35[[#This Row],[Mrp]]+$X$4), IF($S$3="nc", IF($T$3=1, Price35[[#This Row],[Net Cash]]+$W$5, Price35[[#This Row],[Net Cash]]+$X$5), IF($S$3="npc", IF($T$3=1, Price35[[#This Row],[Net Price Credit]]+$W$6, Price35[[#This Row],[Net Price Credit]]+$X$6), IF($S$3="w", IF($T$3=1, Price35[[#This Row],[Wsp]]+$W$6, Price35[[#This Row],[Wsp]]+$X$6), "")))), 10)) -> 4570
B16: 710 | C16: Lohi | D16: wool | F16: 45*90 gents | G16: 340 | I16: 50 | J16: =IF(SUMIF(G16:I16,"<>")=0,"",SUM(G16:I16)) -> 390 | K16: =IF(ISNUMBER(L16), IF(CEILING(ROUND(L16*0.95,2),5)=420, 425, CEILING(ROUND(L16*0.95,2),5) ), "" ) -> 505 | L16: =IF(ISNUMBER(J16), IF(CEILING(ROUND(J16*1.35,2),5)=420, 425, CEILING(ROUND(J16*1.35,2),5) ), "" ) -> 530 | M16: =IF(AND(ISNUMBER(J16),ISNUMBER(G16)), IF( CEILING( ROUND((J16*1.5) * IF(J16*1.5 <= 2500, 1.05, 1.18), 2), IF(ROUND((J16*1.5) * IF(J16*1.5 <= 2500, 1.05, 1.18), 2) < 2500, 25, 50) )=420, 425, CEILING( ROUND((J16*1.5) * IF(J16*1.5 <= 2500, 1.05, 1.18), 2), IF(ROUND((J16*1.5) * IF(J16*1.5 <= 2500, 1.05, 1.18), 2) < 2500, 25, 50) ) ), "" ) -> 625 | N16: =IF(ISNUMBER(G16), CEILING(ROUND(L16*0.92,2),5), "") -> 490 | O16: =IF(ISNUMBER(L16), IF(CEILING(ROUND(L16*1.07,2),5)=420, 425, CEILING(ROUND(L16*1.07,2),5) ), "" ) -> 570 | P16: =IF((((G16*1.5)+50)/0.835)<2500, MROUND(((((G16*1.5)+50)/0.835)*1.05)*2,10), MROUND(((((G16*1.5)+50)/0.835)*1.18)*2,10)) -> 1410 | Q16: =IF($S$3="","", MROUND( IF($S$3="m", IF($T$3=1, Price35[[#This Row],[Mrp]]+$W$4, Price35[[#This Row],[Mrp]]+$X$4), IF($S$3="nc", IF($T$3=1, Price35[[#This Row],[Net Cash]]+$W$5, Price35[[#This Row],[Net Cash]]+$X$5), IF($S$3="npc", IF($T$3=1, Price35[[#This Row],[Net Price Credit]]+$W$6, Price35[[#This Row],[Net Price Credit]]+$X$6), IF($S$3="w", IF($T$3=1, Price35[[#This Row],[Wsp]]+$W$6, Price35[[#This Row],[Wsp]]+$X$6), "")))), 10)) -> 700
A17: 2026 | B17: 910 | C17: Lohi | D17: wool | F17: malida | G17: 500 | I17: 100 | J17: =IF(SUMIF(G17:I17,"<>")=0,"",SUM(G17:I17)) -> 600 | K17: =IF(ISNUMBER(L17), IF(CEILING(ROUND(L17*0.95,2),5)=420, 425, CEILING(ROUND(L17*0.95,2),5) ), "" ) -> 770 | L17: =IF(ISNUMBER(J17), IF(CEILING(ROUND(J17*1.35,2),5)=420, 425, CEILING(ROUND(J17*1.35,2),5) ), "" ) -> 810 | M17: =IF(AND(ISNUMBER(J17),ISNUMBER(G17)), IF( CEILING( ROUND((J17*1.5) * IF(J17*1.5 <= 2500, 1.05, 1.18), 2), IF(ROUND((J17*1.5) * IF(J17*1.5 <= 2500, 1.05, 1.18), 2) < 2500, 25, 50) )=420, 425, CEILING( ROUND((J17*1.5) * IF(J17*1.5 <= 2500, 1.05, 1.18), 2), IF(ROUND((J17*1.5) * IF(J17*1.5 <= 2500, 1.05, 1.18), 2) < 2500, 25, 50) ) ), "" ) -> 950 | N17: =IF(ISNUMBER(G17), CEILING(ROUND(L17*0.92,2),5), "") -> 750 | O17: =IF(ISNUMBER(L17), IF(CEILING(ROUND(L17*1.07,2),5)=420, 425, CEILING(ROUND(L17*1.07,2),5) ), "" ) -> 870 | P17: =IF((((G17*1.5)+50)/0.835)<2500, MROUND(((((G17*1.5)+50)/0.835)*1.05)*2,10), MROUND(((((G17*1.5)+50)/0.835)*1.18)*2,10)) -> 2010 | Q17: =IF($S$3="","", MROUND( IF($S$3="m", IF($T$3=1, Price35[[#This Row],[Mrp]]+$W$4, Price35[[#This Row],[Mrp]]+$X$4), IF($S$3="nc", IF($T$3=1, Price35[[#This Row],[Net Cash]]+$W$5, Price35[[#This Row],[Net Cash]]+$X$5), IF($S$3="npc", IF($T$3=1, Price35[[#This Row],[Net Price Credit]]+$W$6, Price35[[#This Row],[Net Price Credit]]+$X$6), IF($S$3="w", IF($T$3=1, Price35[[#This Row],[Wsp]]+$W$6, Price35[[#This Row],[Wsp]]+$X$6), "")))), 10)) -> 1020
A18: 2026 | B18: 1000 | C18: Lohi | D18: wool | F18: ramayan lohi jay dee 80 x 20 | G18: 693 | I18: 15 | J18: =IF(SUMIF(G18:I18,"<>")=0,"",SUM(G18:I18)) -> 708 | K18: =IF(ISNUMBER(L18), IF(CEILING(ROUND(L18*0.95,2),5)=420, 425, CEILING(ROUND(L18*0.95,2),5) ), "" ) -> 915 | L18: =IF(ISNUMBER(J18), IF(CEILING(ROUND(J18*1.35,2),5)=420, 425, CEILING(ROUND(J18*1.35,2),5) ), "" ) -> 960 | M18: =IF(AND(ISNUMBER(J18),ISNUMBER(G18)), IF( CEILING( ROUND((J18*1.5) * IF(J18*1.5 <= 2500, 1.05, 1.18), 2), IF(ROUND((J18*1.5) * IF(J18*1.5 <= 2500, 1.05, 1.18), 2) < 2500, 25, 50) )=420, 425, CEILING( ROUND((J18*1.5) * IF(J18*1.5 <= 2500, 1.05, 1.18), 2), IF(ROUND((J18*1.5) * IF(J18*1.5 <= 2500, 1.05, 1.18), 2) < 2500, 25, 50) ) ), "" ) -> 1125 | N18: =IF(ISNUMBER(G18), CEILING(ROUND(L18*0.92,2),5), "") -> 885 | O18: =IF(ISNUMBER(L18), IF(CEILING(ROUND(L18*1.07,2),5)=420, 425, CEILING(ROUND(L18*1.07,2),5) ), "" ) -> 1030 | P18: =IF((((G18*1.5)+50)/0.835)<2500, MROUND(((((G18*1.5)+50)/0.835)*1.05)*2,10), MROUND(((((G18*1.5)+50)/0.835)*1.18)*2,10)) -> 2740 | Q18: =IF($S$3="","", MROUND( IF($S$3="m", IF($T$3=1, Price35[[#This Row],[Mrp]]+$W$4, Price35[[#This Row],[Mrp]]+$X$4), IF($S$3="nc", IF($T$3=1, Price35[[#This Row],[Net Cash]]+$W$5, Price35[[#This Row],[Net Cash]]+$X$5), IF($S$3="npc", IF($T$3=1, Price35[[#This Row],[Net Price Credit]]+$W$6, Price35[[#This Row],[Net Price Credit]]+$X$6), IF($S$3="w", IF($T$3=1, Price35[[#This Row],[Wsp]]+$W$6, Price35[[#This Row],[Wsp]]+$X$6), "")))), 10)) -> 1200
B19: 1010 | C19: Lohi | D19: wool | F19: malida 10 no. | G19: 480 | I19: 80 | J19: =IF(SUMIF(G19:I19,"<>")=0,"",SUM(G19:I19)) -> 560 | K19: =IF(ISNUMBER(L19), IF(CEILING(ROUND(L19*0.95,2),5)=420, 425, CEILING(ROUND(L19*0.95,2),5) ), "" ) -> 725 | L19: =IF(ISNUMBER(J19), IF(CEILING(ROUND(J19*1.35,2),5)=420, 425, CEILING(ROUND(J19*1.35,2),5) ), "" ) -> 760 | M19: =IF(AND(ISNUMBER(J19),ISNUMBER(G19)), IF( CEILING( ROUND((J19*1.5) * IF(J19*1.5 <= 2500, 1.05, 1.18), 2), IF(ROUND((J19*1.5) * IF(J19*1.5 <= 2500, 1.05, 1.18), 2) < 2500, 25, 50) )=420, 425, CEILING( ROUND((J19*1.5) * IF(J19*1.5 <= 2500, 1.05, 1.18), 2), IF(ROUND((J19*1.5) * IF(J19*1.5 <= 2500, 1.05, 1.18), 2) < 2500, 25, 50) ) ), "" ) -> 900 | N19: =IF(ISNUMBER(G19), CEILING(ROUND(L19*0.92,2),5), "") -> 700 | O19: =IF(ISNUMBER(L19), IF(CEILING(ROUND(L19*1.07,2),5)=420, 425, CEILING(ROUND(L19*1.07,2),5) ), "" ) -> 815 | P19: =IF((((G19*1.5)+50)/0.835)<2500, MROUND(((((G19*1.5)+50)/0.835)*1.05)*2,10), MROUND(((((G19*1.5)+50)/0.835)*1.18)*2,10)) -> 1940 | Q19: =IF($S$3="","", MROUND( IF($S$3="m", IF($T$3=1, Price35[[#This Row],[Mrp]]+$W$4, Price35[[#This Row],[Mrp]]+$X$4), IF($S$3="nc", IF($T$3=1, Price35[[#This Row],[Net Cash]]+$W$5, Price35[[#This Row],[Net Cash]]+$X$5), IF($S$3="npc", IF($T$3=1, Price35[[#This Row],[Net Price Credit]]+$W$6, Price35[[#This Row],[Net Price Credit]]+$X$6), IF($S$3="w", IF($T$3=1, Price35[[#This Row],[Wsp]]+$W$6, Price35[[#This Row],[Wsp]]+$X$6), "")))), 10)) -> 970
A20: 2026 | B20: 1651 | C20: Lohi | D20: wool | E20: international | F20: malida 1651 no.pure wool 450 gm | G20: 881 | I20: 25 | J20: =IF(SUMIF(G20:I20,"<>")=0,"",SUM(G20:I20)) -> 906 | K20: =IF(ISNUMBER(L20), IF(CEILING(ROUND(L20*0.95,2),5)=420, 425, CEILING(ROUND(L20*0.95,2),5) ), "" ) -> 1165 | L20: =IF(ISNUMBER(J20), IF(CEILING(ROUND(J20*1.35,2),5)=420, 425, CEILING(ROUND(J20*1.35,2),5) ), "" ) -> 1225 | M20: =IF(AND(ISNUMBER(J20),ISNUMBER(G20)), IF( CEILING( ROUND((J20*1.5) * IF(J20*1.5 <= 2500, 1.05, 1.18), 2), IF(ROUND((J20*1.5) * IF(J20*1.5 <= 2500, 1.05, 1.18), 2) < 2500, 25, 50) )=420, 425, CEILING( ROUND((J20*1.5) * IF(J20*1.5 <= 2500, 1.05, 1.18), 2), IF(ROUND((J20*1.5) * IF(J20*1.5 <= 2500, 1.05, 1.18), 2) < 2500, 25, 50) ) ), "" ) -> 1450 | N20: =IF(ISNUMBER(G20), CEILING(ROUND(L20*0.92,2),5), "") -> 1130 | O20: =IF(ISNUMBER(L20), IF(CEILING(ROUND(L20*1.07,2),5)=420, 425, CEILING(ROUND(L20*1.07,2),5) ), "" ) -> 1315 | P20: =IF((((G20*1.5)+50)/0.835)<2500, MROUND(((((G20*1.5)+50)/0.835)*1.05)*2,10), MROUND(((((G20*1.5)+50)/0.835)*1.18)*2,10)) -> 3450 | Q20: =IF($S$3="","", MROUND( IF($S$3="m", IF($T$3=1, Price35[[#This Row],[Mrp]]+$W$4, Price35[[#This Row],[Mrp]]+$X$4), IF($S$3="nc", IF($T$3=1, Price35[[#This Row],[Net Cash]]+$W$5, Price35[[#This Row],[Net Cash]]+$X$5), IF($S$3="npc", IF($T$3=1, Price35[[#This Row],[Net Price Credit]]+$W$6, Price35[[#This Row],[Net Price Credit]]+$X$6), IF($S$3="w", IF($T$3=1, Price35[[#This Row],[Wsp]]+$W$6, Price35[[#This Row],[Wsp]]+$X$6), "")))), 10)) -> 1520
A21: 2026 | B21: 2400 | C21: Lohi | D21: wool | F21: lohi govinda 80 x 20 jay dee | G21: 936 | I21: 15 | J21: =IF(SUMIF(G21:I21,"<>")=0,"",SUM(G21:I21)) -> 951 | K21: =IF(ISNUMBER(L21), IF(CEILING(ROUND(L21*0.95,2),5)=420, 425, CEILING(ROUND(L21*0.95,2),5) ), "" ) -> 1225 | L21: =IF(ISNUMBER(J21), IF(CEILING(ROUND(J21*1.35,2),5)=420, 425, CEILING(ROUND(J21*1.35,2),5) ), "" ) -> 1285 | M21: =IF(AND(ISNUMBER(J21),ISNUMBER(G21)), IF( CEILING( ROUND((J21*1.5) * IF(J21*1.5 <= 2500, 1.05, 1.18), 2), IF(ROUND((J21*1.5) * IF(J21*1.5 <= 2500, 1.05, 1.18), 2) < 2500, 25, 50) )=420, 425, CEILING( ROUND((J21*1.5) * IF(J21*1.5 <= 2500, 1.05, 1.18), 2), IF(ROUND((J21*1.5) * IF(J21*1.5 <= 2500, 1.05, 1.18), 2) < 2500, 25, 50) ) ), "" ) -> 1500 | N21: =IF(ISNUMBER(G21), CEILING(ROUND(L21*0.92,2),5), "") -> 1185 | O21: =IF(ISNUMBER(L21), IF(CEILING(ROUND(L21*1.07,2),5)=420, 425, CEILING(ROUND(L21*1.07,2),5) ), "" ) -> 1375 | P21: =IF((((G21*1.5)+50)/0.835)<2500, MROUND(((((G21*1.5)+50)/0.835)*1.05)*2,10), MROUND(((((G21*1.5)+50)/0.835)*1.18)*2,10)) -> 3660 | Q21: =IF($S$3="","", MROUND( IF($S$3="m", IF($T$3=1, Price35[[#This Row],[Mrp]]+$W$4, Price35[[#This Row],[Mrp]]+$X$4), IF($S$3="nc", IF($T$3=1, Price35[[#This Row],[Net Cash]]+$W$5, Price35[[#This Row],[Net Cash]]+$X$5), IF($S$3="npc", IF($T$3=1, Price35[[#This Row],[Net Price Credit]]+$W$6, Price35[[#This Row],[Net Price Credit]]+$X$6), IF($S$3="w", IF($T$3=1, Price35[[#This Row],[Wsp]]+$W$6, Price35[[#This Row],[Wsp]]+$X$6), "")))), 10)) -> 1570
A22: 2026 | B22: 2451 | C22: Lohi | D22: wool | E22: international | F22: malida 2451 no. pure wool 650gm | G22: 1303 | I22: 25 | J22: =IF(SUMIF(G22:I22,"<>")=0,"",SUM(G22:I22)) -> 1328 | K22: =IF(ISNUMBER(L22), IF(CEILING(ROUND(L22*0.95,2),5)=420, 425, CEILING(ROUND(L22*0.95,2),5) ), "" ) -> 1710 | L22: =IF(ISNUMBER(J22), IF(CEILING(ROUND(J22*1.35,2),5)=420, 425, CEILING(ROUND(J22*1.35,2),5) ), "" ) -> 1795 | M22: =IF(AND(ISNUMBER(J22),ISNUMBER(G22)), IF( CEILING( ROUND((J22*1.5) * IF(J22*1.5 <= 2500, 1.05, 1.18), 2), IF(ROUND((J22*1.5) * IF(J22*1.5 <= 2500, 1.05, 1.18), 2) < 2500, 25, 50) )=420, 425, CEILING( ROUND((J22*1.5) * IF(J22*1.5 <= 2500, 1.05, 1.18), 2), IF(ROUND((J22*1.5) * IF(J22*1.5 <= 2500, 1.05, 1.18), 2) < 2500, 25, 50) ) ), "" ) -> 2100 | N22: =IF(ISNUMBER(G22), CEILING(ROUND(L22*0.92,2),5), "") -> 1655 | O22: =IF(ISNUMBER(L22), IF(CEILING(ROUND(L22*1.07,2),5)=420, 425, CEILING(ROUND(L22*1.07,2),5) ), "" ) -> 1925 | P22: =IF((((G22*1.5)+50)/0.835)<2500, MROUND(((((G22*1.5)+50)/0.835)*1.05)*2,10), MROUND(((((G22*1.5)+50)/0.835)*1.18)*2,10)) -> 5040 | Q22: =IF($S$3="","", MROUND( IF($S$3="m", IF($T$3=1, Price35[[#This Row],[Mrp]]+$W$4, Price35[[#This Row],[Mrp]]+$X$4), IF($S$3="nc", IF($T$3=1, Price35[[#This Row],[Net Cash]]+$W$5, Price35[[#This Row],[Net Cash]]+$X$5), IF($S$3="npc", IF($T$3=1, Price35[[#This Row],[Net Price Credit]]+$W$6, Price35[[#This Row],[Net Price Credit]]+$X$6), IF($S$3="w", IF($T$3=1, Price35[[#This Row],[Wsp]]+$W$6, Price35[[#This Row],[Wsp]]+$X$6), "")))), 10)) -> 2170
A23: 2026 | B23: 142 | C23: shawl | D23: Polywool | E23: MM enterprises | F23: shahtoosh 2/72 polywool | G23: 370 | I23: 265 | J23: =IF(SUMIF(G23:I23,"<>")=0,"",SUM(G23:I23)) -> 635 | K23: =IF(ISNUMBER(L23), IF(CEILING(ROUND(L23*0.95,2),5)=420, 425, CEILING(ROUND(L23*0.95,2),5) ), "" ) -> 820 | L23: =IF(ISNUMBER(J23), IF(CEILING(ROUND(J23*1.35,2),5)=420, 425, CEILING(ROUND(J23*1.35,2),5) ), "" ) -> 860 | M23: =IF(AND(ISNUMBER(J23),ISNUMBER(G23)), IF( CEILING( ROUND((J23*1.5) * IF(J23*1.5 <= 2500, 1.05, 1.18), 2), IF(ROUND((J23*1.5) * IF(J23*1.5 <= 2500, 1.05, 1.18), 2) < 2500, 25, 50) )=420, 425, CEILING( ROUND((J23*1.5) * IF(J23*1.5 <= 2500, 1.05, 1.18), 2), IF(ROUND((J23*1.5) * IF(J23*1.5 <= 2500, 1.05, 1.18), 2) < 2500, 25, 50) ) ), "" ) -> 1025 | N23: =IF(ISNUMBER(G23), CEILING(ROUND(L23*0.92,2),5), "") -> 795 | O23: =IF(ISNUMBER(L23), IF(CEILING(ROUND(L23*1.07,2),5)=420, 425, CEILING(ROUND(L23*1.07,2),5) ), "" ) -> 925 | P23: =IF((((G23*1.5)+50)/0.835)<2500, MROUND(((((G23*1.5)+50)/0.835)*1.05)*2,10), MROUND(((((G23*1.5)+50)/0.835)*1.18)*2,10)) -> 1520 | Q23: =IF($S$3="","", MROUND( IF($S$3="m", IF($T$3=1, Price35[[#This Row],[Mrp]]+$W$4, Price35[[#This Row],[Mrp]]+$X$4), IF($S$3="nc", IF($T$3=1, Price35[[#This Row],[Net Cash]]+$W$5, Price35[[#This Row],[Net Cash]]+$X$5), IF($S$3="npc", IF($T$3=1, Price35[[#This Row],[Net Price Credit]]+$W$6, Price35[[#This Row],[Net Price Credit]]+$X$6), IF($S$3="w", IF($T$3=1, Price35[[#This Row],[Wsp]]+$W$6, Price35[[#This Row],[Wsp]]+$X$6), "")))), 10)) -> 1100
A24: 2026 | B24: 143 | C24: shawl | D24: Polywool | E24: MM enterprises | F24: shahtoosh 2/72 polywool 50*100 | G24: 500 | I24: 325 | J24: =IF(SUMIF(G24:I24,"<>")=0,"",SUM(G24:I24)) -> 825 | K24: =IF(ISNUMBER(L24), IF(CEILING(ROUND(L24*0.95,2),5)=420, 425, CEILING(ROUND(L24*0.95,2),5) ), "" ) -> 1060 | L24: =IF(ISNUMBER(J24), IF(CEILING(ROUND(J24*1.35,2),5)=420, 425, CEILING(ROUND(J24*1.35,2),5) ), "" ) -> 1115 | M24: =IF(AND(ISNUMBER(J24),ISNUMBER(G24)), IF( CEILING( ROUND((J24*1.5) * IF(J24*1.5 <= 2500, 1.05, 1.18), 2), IF(ROUND((J24*1.5) * IF(J24*1.5 <= 2500, 1.05, 1.18), 2) < 2500, 25, 50) )=420, 425, CEILING( ROUND((J24*1.5) * IF(J24*1.5 <= 2500, 1.05, 1.18), 2), IF(ROUND((J24*1.5) * IF(J24*1.5 <= 2500, 1.05, 1.18), 2) < 2500, 25, 50) ) ), "" ) -> 1300 | N24: =IF(ISNUMBER(G24), CEILING(ROUND(L24*0.92,2),5), "") -> 1030 | O24: =IF(ISNUMBER(L24), IF(CEILING(ROUND(L24*1.07,2),5)=420, 425, CEILING(ROUND(L24*1.07,2),5) ), "" ) -> 1195 | P24: =IF((((G24*1.5)+50)/0.835)<2500, MROUND(((((G24*1.5)+50)/0.835)*1.05)*2,10), MROUND(((((G24*1.5)+50)/0.835)*1.18)*2,10)) -> 2010 | Q24: =IF($S$3="","", MROUND( IF($S$3="m", IF($T$3=1, Price35[[#This Row],[Mrp]]+$W$4, Price35[[#This Row],[Mrp]]+$X$4), IF($S$3="nc", IF($T$3=1, Price35[[#This Row],[Net Cash]]+$W$5, Price35[[#This Row],[Net Cash]]+$X$5), IF($S$3="npc", IF($T$3=1, Price35[[#This Row],[Net Price Credit]]+$W$6, Price35[[#This Row],[Net Price Credit]]+$X$6), IF($S$3="w", IF($T$3=1, Price35[[#This Row],[Wsp]]+$W$6, Price35[[#This Row],[Wsp]]+$X$6), "")))), 10)) -> 1370
B25: 948 | C25: shawl | D25: Kashmiri | F25: hashia | G25: 390 | I25: 215 | J25: =IF(SUMIF(G25:I25,"<>")=0,"",SUM(G25:I25)) -> 605 | K25: =IF(ISNUMBER(L25), IF(CEILING(ROUND(L25*0.95,2),5)=420, 425, CEILING(ROUND(L25*0.95,2),5) ), "" ) -> 780 | L25: =IF(ISNUMBER(J25), IF(CEILING(ROUND(J25*1.35,2),5)=420, 425, CEILING(ROUND(J25*1.35,2),5) ), "" ) -> 820 | M25: =IF(AND(ISNUMBER(J25),ISNUMBER(G25)), IF( CEILING( ROUND((J25*1.5) * IF(J25*1.5 <= 2500, 1.05, 1.18), 2), IF(ROUND((J25*1.5) * IF(J25*1.5 <= 2500, 1.05, 1.18), 2) < 2500, 25, 50) )=420, 425, CEILING( ROUND((J25*1.5) * IF(J25*1.5 <= 2500, 1.05, 1.18), 2), IF(ROUND((J25*1.5) * IF(J25*1.5 <= 2500, 1.05, 1.18), 2) < 2500, 25, 50) ) ), "" ) -> 975 | N25: =IF(ISNUMBER(G25), CEILING(ROUND(L25*0.92,2),5), "") -> 755 | O25: =IF(ISNUMBER(L25), IF(CEILING(ROUND(L25*1.07,2),5)=420, 425, CEILING(ROUND(L25*1.07,2),5) ), "" ) -> 880 | P25: =IF((((G25*1.5)+50)/0.835)<2500, MROUND(((((G25*1.5)+50)/0.835)*1.05)*2,10), MROUND(((((G25*1.5)+50)/0.835)*1.18)*2,10)) -> 1600 | Q25: =IF($S$3="","", MROUND( IF($S$3="m", IF($T$3=1, Price35[[#This Row],[Mrp]]+$W$4, Price35[[#This Row],[Mrp]]+$X$4), IF($S$3="nc", IF($T$3=1, Price35[[#This Row],[Net Cash]]+$W$5, Price35[[#This Row],[Net Cash]]+$X$5), IF($S$3="npc", IF($T$3=1, Price35[[#This Row],[Net Price Credit]]+$W$6, Price35[[#This Row],[Net Price Credit]]+$X$6), IF($S$3="w", IF($T$3=1, Price35[[#This Row],[Wsp]]+$W$6, Price35[[#This Row],[Wsp]]+$X$6), "")))), 10)) -> 1050
B26: 949 | C26: shawl | D26: Kashmiri | F26: hashia 14 no. | G26: 460 | I26: 215 | J26: =IF(SUMIF(G26:I26,"<>")=0,"",SUM(G26:I26)) -> 675 | K26: =IF(ISNUMBER(L26), IF(CEILING(ROUND(L26*0.95,2),5)=420, 425, CEILING(ROUND(L26*0.95,2),5) ), "" ) -> 870 | L26: =IF(ISNUMBER(J26), IF(CEILING(ROUND(J26*1.35,2),5)=420, 425, CEILING(ROUND(J26*1.35,2),5) ), "" ) -> 915 | M26: =IF(AND(ISNUMBER(J26),ISNUMBER(G26)), IF( CEILING( ROUND((J26*1.5) * IF(J26*1.5 <= 2500, 1.05, 1.18), 2), IF(ROUND((J26*1.5) * IF(J26*1.5 <= 2500, 1.05, 1.18), 2) < 2500, 25, 50) )=420, 425, CEILING( ROUND((J26*1.5) * IF(J26*1.5 <= 2500, 1.05, 1.18), 2), IF(ROUND((J26*1.5) * IF(J26*1.5 <= 2500, 1.05, 1.18), 2) < 2500, 25, 50) ) ), "" ) -> 1075 | N26: =IF(ISNUMBER(G26), CEILING(ROUND(L26*0.92,2),5), "") -> 845 | O26: =IF(ISNUMBER(L26), IF(CEILING(ROUND(L26*1.07,2),5)=420, 425, CEILING(ROUND(L26*1.07,2),5) ), "" ) -> 980 | P26: =IF((((G26*1.5)+50)/0.835)<2500, MROUND(((((G26*1.5)+50)/0.835)*1.05)*2,10), MROUND(((((G26*1.5)+50)/0.835)*1.18)*2,10)) -> 1860 | Q26: =IF($S$3="","", MROUND( IF($S$3="m", IF($T$3=1, Price35[[#This Row],[Mrp]]+$W$4, Price35[[#This Row],[Mrp]]+$X$4), IF($S$3="nc", IF($T$3=1, Price35[[#This Row],[Net Cash]]+$W$5, Price35[[#This Row],[Net Cash]]+$X$5), IF($S$3="npc", IF($T$3=1, Price35[[#This Row],[Net Price Credit]]+$W$6, Price35[[#This Row],[Net Price Credit]]+$X$6), IF($S$3="w", IF($T$3=1, Price35[[#This Row],[Wsp]]+$W$6, Price35[[#This Row],[Wsp]]+$X$6), "")))), 10)) -> 1150
B27: 951 | C27: shawl | D27: Kashmiri | F27: mini neem dour multihead 13 no. | G27: 390 | I27: 300 | J27: =IF(SUMIF(G27:I27,"<>")=0,"",SUM(G27:I27)) -> 690 | K27: =IF(ISNUMBER(L27), IF(CEILING(ROUND(L27*0.95,2),5)=420, 425, CEILING(ROUND(L27*0.95,2),5) ), "" ) -> 890 | L27: =IF(ISNUMBER(J27), IF(CEILING(ROUND(J27*1.35,2),5)=420, 425, CEILING(ROUND(J27*1.35,2),5) ), "" ) -> 935 | M27: =IF(AND(ISNUMBER(J27),ISNUMBER(G27)), IF( CEILING( ROUND((J27*1.5) * IF(J27*1.5 <= 2500, 1.05, 1.18), 2), IF(ROUND((J27*1.5) * IF(J27*1.5 <= 2500, 1.05, 1.18), 2) < 2500, 25, 50) )=420, 425, CEILING( ROUND((J27*1.5) * IF(J27*1.5 <= 2500, 1.05, 1.18), 2), IF(ROUND((J27*1.5) * IF(J27*1.5 <= 2500, 1.05, 1.18), 2) < 2500, 25, 50) ) ), "" ) -> 1100 | N27: =IF(ISNUMBER(G27), CEILING(ROUND(L27*0.92,2),5), "") -> 865 | O27: =IF(ISNUMBER(L27), IF(CEILING(ROUND(L27*1.07,2),5)=420, 425, CEILING(ROUND(L27*1.07,2),5) ), "" ) -> 1005 | P27: =IF((((G27*1.5)+50)/0.835)<2500, MROUND(((((G27*1.5)+50)/0.835)*1.05)*2,10), MROUND(((((G27*1.5)+50)/0.835)*1.18)*2,10)) -> 1600 | Q27: =IF($S$3="","", MROUND( IF($S$3="m", IF($T$3=1, Price35[[#This Row],[Mrp]]+$W$4, Price35[[#This Row],[Mrp]]+$X$4), IF($S$3="nc", IF($T$3=1, Price35[[#This Row],[Net Cash]]+$W$5, Price35[[#This Row],[Net Cash]]+$X$5), IF($S$3="npc", IF($T$3=1, Price35[[#This Row],[Net Price Credit]]+$W$6, Price35[[#This Row],[Net Price Credit]]+$X$6), IF($S$3="w", IF($T$3=1, Price35[[#This Row],[Wsp]]+$W$6, Price35[[#This Row],[Wsp]]+$X$6), "")))), 10)) -> 1170
A28: 2026 | B28: 959 | C28: shawl | D28: Kashmiri | E28: sharma | F28: c.n.d multihead new | G28: 390 | I28: 265 | J28: =IF(SUMIF(G28:I28,"<>")=0,"",SUM(G28:I28)) -> 655 | K28: =IF(ISNUMBER(L28), IF(CEILING(ROUND(L28*0.95,2),5)=420, 425, CEILING(ROUND(L28*0.95,2),5) ), "" ) -> 845 | L28: =IF(ISNUMBER(J28), IF(CEILING(ROUND(J28*1.35,2),5)=420, 425, CEILING(ROUND(J28*1.35,2),5) ), "" ) -> 885 | M28: =IF(AND(ISNUMBER(J28),ISNUMBER(G28)), IF( CEILING( ROUND((J28*1.5) * IF(J28*1.5 <= 2500, 1.05, 1.18), 2), IF(ROUND((J28*1.5) * IF(J28*1.5 <= 2500, 1.05, 1.18), 2) < 2500, 25, 50) )=420, 425, CEILING( ROUND((J28*1.5) * IF(J28*1.5 <= 2500, 1.05, 1.18), 2), IF(ROUND((J28*1.5) * IF(J28*1.5 <= 2500, 1.05, 1.18), 2) < 2500, 25, 50) ) ), "" ) -> 1050 | N28: =IF(ISNUMBER(G28), CEILING(ROUND(L28*0.92,2),5), "") -> 815 | O28: =IF(ISNUMBER(L28), IF(CEILING(ROUND(L28*1.07,2),5)=420, 425, CEILING(ROUND(L28*1.07,2),5) ), "" ) -> 950 | P28: =IF((((G28*1.5)+50)/0.835)<2500, MROUND(((((G28*1.5)+50)/0.835)*1.05)*2,10), MROUND(((((G28*1.5)+50)/0.835)*1.18)*2,10)) -> 1600 | Q28: =IF($S$3="","", MROUND( IF($S$3="m", IF($T$3=1, Price35[[#This Row],[Mrp]]+$W$4, Price35[[#This Row],[Mrp]]+$X$4), IF($S$3="nc", IF($T$3=1, Price35[[#This Row],[Net Cash]]+$W$5, Price35[[#This Row],[Net Cash]]+$X$5), IF($S$3="npc", IF($T$3=1, Price35[[#This Row],[Net Price Credit]]+$W$6, Price35[[#This Row],[Net Price Credit]]+$X$6), IF($S$3="w", IF($T$3=1, Price35[[#This Row],[Wsp]]+$W$6, Price35[[#This Row],[Wsp]]+$X$6), "")))), 10)) -> 1120
B29: 960 | C29: shawl | D29: Kashmiri | F29: hashia multihead 14 no. | G29: 460 | I29: 325 | J29: =IF(SUMIF(G29:I29,"<>")=0,"",SUM(G29:I29)) -> 785 | K29: =IF(ISNUMBER(L29), IF(CEILING(ROUND(L29*0.95,2),5)=420, 425, CEILING(ROUND(L29*0.95,2),5) ), "" ) -> 1010 | L29: =IF(ISNUMBER(J29), IF(CEILING(ROUND(J29*1.35,2),5)=420, 425, CEILING(ROUND(J29*1.35,2),5) ), "" ) -> 1060 | M29: =IF(AND(ISNUMBER(J29),ISNUMBER(G29)), IF( CEILING( ROUND((J29*1.5) * IF(J29*1.5 <= 2500, 1.05, 1.18), 2), IF(ROUND((J29*1.5) * IF(J29*1.5 <= 2500, 1.05, 1.18), 2) < 2500, 25, 50) )=420, 425, CEILING( ROUND((J29*1.5) * IF(J29*1.5 <= 2500, 1.05, 1.18), 2), IF(ROUND((J29*1.5) * IF(J29*1.5 <= 2500, 1.05, 1.18), 2) < 2500, 25, 50) ) ), "" ) -> 1250 | N29: =IF(ISNUMBER(G29), CEILING(ROUND(L29*0.92,2),5), "") -> 980 | O29: =IF(ISNUMBER(L29), IF(CEILING(ROUND(L29*1.07,2),5)=420, 425, CEILING(ROUND(L29*1.07,2),5) ), "" ) -> 1135 | P29: =IF((((G29*1.5)+50)/0.835)<2500, MROUND(((((G29*1.5)+50)/0.835)*1.05)*2,10), MROUND(((((G29*1.5)+50)/0.835)*1.18)*2,10)) -> 1860 | Q29: =IF($S$3="","", MROUND( IF($S$3="m", IF($T$3=1, Price35[[#This Row],[Mrp]]+$W$4, Price35[[#This Row],[Mrp]]+$X$4), IF($S$3="nc", IF($T$3=1, Price35[[#This Row],[Net Cash]]+$W$5, Price35[[#This Row],[Net Cash]]+$X$5), IF($S$3="npc", IF($T$3=1, Price35[[#This Row],[Net Price Credit]]+$W$6, Price35[[#This Row],[Net Price Credit]]+$X$6), IF($S$3="w", IF($T$3=1, Price35[[#This Row],[Wsp]]+$W$6, Price35[[#This Row],[Wsp]]+$X$6), "")))), 10)) -> 1320
B30: 962 | C30: shawl | D30: Kashmiri | F30: variety 14 no. | G30: 460 | I30: 310 | J30: =IF(SUMIF(G30:I30,"<>")=0,"",SUM(G30:I30)) -> 770 | K30: =IF(ISNUMBER(L30), IF(CEILING(ROUND(L30*0.95,2),5)=420, 425, CEILING(ROUND(L30*0.95,2),5) ), "" ) -> 990 | L30: =IF(ISNUMBER(J30), IF(CEILING(ROUND(J30*1.35,2),5)=420, 425, CEILING(ROUND(J30*1.35,2),5) ), "" ) -> 1040 | M30: =IF(AND(ISNUMBER(J30),ISNUMBER(G30)), IF( CEILING( ROUND((J30*1.5) * IF(J30*1.5 <= 2500, 1.05, 1.18), 2), IF(ROUND((J30*1.5) * IF(J30*1.5 <= 2500, 1.05, 1.18), 2) < 2500, 25, 50) )=420, 425, CEILING( ROUND((J30*1.5) * IF(J30*1.5 <= 2500, 1.05, 1.18), 2), IF(ROUND((J30*1.5) * IF(J30*1.5 <= 2500, 1.05, 1.18), 2) < 2500, 25, 50) ) ), "" ) -> 1225 | N30: =IF(ISNUMBER(G30), CEILING(ROUND(L30*0.92,2),5), "") -> 960 | O30: =IF(ISNUMBER(L30), IF(CEILING(ROUND(L30*1.07,2),5)=420, 425, CEILING(ROUND(L30*1.07,2),5) ), "" ) -> 1115 | P30: =IF((((G30*1.5)+50)/0.835)<2500, MROUND(((((G30*1.5)+50)/0.835)*1.05)*2,10), MROUND(((((G30*1.5)+50)/0.835)*1.18)*2,10)) -> 1860 | Q30: =IF($S$3="","", MROUND( IF($S$3="m", IF($T$3=1, Price35[[#This Row],[Mrp]]+$W$4, Price35[[#This Row],[Mrp]]+$X$4), IF($S$3="nc", IF($T$3=1, Price35[[#This Row],[Net Cash]]+$W$5, Price35[[#This Row],[Net Cash]]+$X$5), IF($S$3="npc", IF($T$3=1, Price35[[#This Row],[Net Price Credit]]+$W$6, Price35[[#This Row],[Net Price Credit]]+$X$6), IF($S$3="w", IF($T$3=1, Price35[[#This Row],[Wsp]]+$W$6, Price35[[#This Row],[Wsp]]+$X$6), "")))), 10)) -> 1300
B31: 965 | C31: shawl | D31: Kashmiri | F31: shahtoosh | G31: 390 | I31: 165 | J31: =IF(SUMIF(G31:I31,"<>")=0,"",SUM(G31:I31)) -> 555 | K31: =IF(ISNUMBER(L31), IF(CEILING(ROUND(L31*0.95,2),5)=420, 425, CEILING(ROUND(L31*0.95,2),5) ), "" ) -> 715 | L31: =IF(ISNUMBER(J31), IF(CEILING(ROUND(J31*1.35,2),5)=420, 425, CEILING(ROUND(J31*1.35,2),5) ), "" ) -> 750 | M31: =IF(AND(ISNUMBER(J31),ISNUMBER(G31)), IF( CEILING( ROUND((J31*1.5) * IF(J31*1.5 <= 2500, 1.05, 1.18), 2), IF(ROUND((J31*1.5) * IF(J31*1.5 <= 2500, 1.05, 1.18), 2) < 2500, 25, 50) )=420, 425, CEILING( ROUND((J31*1.5) * IF(J31*1.5 <= 2500, 1.05, 1.18), 2), IF(ROUND((J31*1.5) * IF(J31*1.5 <= 2500, 1.05, 1.18), 2) < 2500, 25, 50) ) ), "" ) -> 875 | N31: =IF(ISNUMBER(G31), CEILING(ROUND(L31*0.92,2),5), "") -> 690 | O31: =IF(ISNUMBER(L31), IF(CEILING(ROUND(L31*1.07,2),5)=420, 425, CEILING(ROUND(L31*1.07,2),5) ), "" ) -> 805 | P31: =IF((((G31*1.5)+50)/0.835)<2500, MROUND(((((G31*1.5)+50)/0.835)*1.05)*2,10), MROUND(((((G31*1.5)+50)/0.835)*1.18)*2,10)) -> 1600 | Q31: =IF($S$3="","", MROUND( IF($S$3="m", IF($T$3=1, Price35[[#This Row],[Mrp]]+$W$4, Price35[[#This Row],[Mrp]]+$X$4), IF($S$3="nc", IF($T$3=1, Price35[[#This Row],[Net Cash]]+$W$5, Price35[[#This Row],[Net Cash]]+$X$5), IF($S$3="npc", IF($T$3=1, Price35[[#This Row],[Net Price Credit]]+$W$6, Price35[[#This Row],[Net Price Credit]]+$X$6), IF($S$3="w", IF($T$3=1, Price35[[#This Row],[Wsp]]+$W$6, Price35[[#This Row],[Wsp]]+$X$6), "")))), 10)) -> 950
B32: 968 | C32: shawl | D32: Kashmiri | F32: variety 14 no. | G32: 460 | I32: 310 | J32: =IF(SUMIF(G32:I32,"<>")=0,"",SUM(G32:I32)) -> 770 | K32: =IF(ISNUMBER(L32), IF(CEILING(ROUND(L32*0.95,2),5)=420, 425, CEILING(ROUND(L32*0.95,2),5) ), "" ) -> 990 | L32: =IF(ISNUMBER(J32), IF(CEILING(ROUND(J32*1.35,2),5)=420, 425, CEILING(ROUND(J32*1.35,2),5) ), "" ) -> 1040 | M32: =IF(AND(ISNUMBER(J32),ISNUMBER(G32)), IF( CEILING( ROUND((J32*1.5) * IF(J32*1.5 <= 2500, 1.05, 1.18), 2), IF(ROUND((J32*1.5) * IF(J32*1.5 <= 2500, 1.05, 1.18), 2) < 2500, 25, 50) )=420, 425, CEILING( ROUND((J32*1.5) * IF(J32*1.5 <= 2500, 1.05, 1.18), 2), IF(ROUND((J32*1.5) * IF(J32*1.5 <= 2500, 1.05, 1.18), 2) < 2500, 25, 50) ) ), "" ) -> 1225 | N32: =IF(ISNUMBER(G32), CEILING(ROUND(L32*0.92,2),5), "") -> 960 | O32: =IF(ISNUMBER(L32), IF(CEILING(ROUND(L32*1.07,2),5)=420, 425, CEILING(ROUND(L32*1.07,2),5) ), "" ) -> 1115 | P32: =IF((((G32*1.5)+50)/0.835)<2500, MROUND(((((G32*1.5)+50)/0.835)*1.05)*2,10), MROUND(((((G32*1.5)+50)/0.835)*1.18)*2,10)) -> 1860 | Q32: =IF($S$3="","", MROUND( IF($S$3="m", IF($T$3=1, Price35[[#This Row],[Mrp]]+$W$4, Price35[[#This Row],[Mrp]]+$X$4), IF($S$3="nc", IF($T$3=1, Price35[[#This Row],[Net Cash]]+$W$5, Price35[[#This Row],[Net Cash]]+$X$5), IF($S$3="npc", IF($T$3=1, Price35[[#This Row],[Net Price Credit]]+$W$6, Price35[[#This Row],[Net Price Credit]]+$X$6), IF($S$3="w", IF($T$3=1, Price35[[#This Row],[Wsp]]+$W$6, Price35[[#This Row],[Wsp]]+$X$6), "")))), 10)) -> 1300
B33: 969 | C33: shawl | D33: Kashmiri | F33: pipping variety | G33: 390 | I33: 210 | J33: =IF(SUMIF(G33:I33,"<>")=0,"",SUM(G33:I33)) -> 600 | K33: =IF(ISNUMBER(L33), IF(CEILING(ROUND(L33*0.95,2),5)=420, 425, CEILING(ROUND(L33*0.95,2),5) ), "" ) -> 770 | L33: =IF(ISNUMBER(J33), IF(CEILING(ROUND(J33*1.35,2),5)=420, 425, CEILING(ROUND(J33*1.35,2),5) ), "" ) -> 810 | M33: =IF(AND(ISNUMBER(J33),ISNUMBER(G33)), IF( CEILING( ROUND((J33*1.5) * IF(J33*1.5 <= 2500, 1.05, 1.18), 2), IF(ROUND((J33*1.5) * IF(J33*1.5 <= 2500, 1.05, 1.18), 2) < 2500, 25, 50) )=420, 425, CEILING( ROUND((J33*1.5) * IF(J33*1.5 <= 2500, 1.05, 1.18), 2), IF(ROUND((J33*1.5) * IF(J33*1.5 <= 2500, 1.05, 1.18), 2) < 2500, 25, 50) ) ), "" ) -> 950 | N33: =IF(ISNUMBER(G33), CEILING(ROUND(L33*0.92,2),5), "") -> 750 | O33: =IF(ISNUMBER(L33), IF(CEILING(ROUND(L33*1.07,2),5)=420, 425, CEILING(ROUND(L33*1.07,2),5) ), "" ) -> 870 | P33: =IF((((G33*1.5)+50)/0.835)<2500, MROUND(((((G33*1.5)+50)/0.835)*1.05)*2,10), MROUND(((((G33*1.5)+50)/0.835)*1.18)*2,10)) -> 1600 | Q33: =IF($S$3="","", MROUND( IF($S$3="m", IF($T$3=1, Price35[[#This Row],[Mrp]]+$W$4, Price35[[#This Row],[Mrp]]+$X$4), IF($S$3="nc", IF($T$3=1, Price35[[#This Row],[Net Cash]]+$W$5, Price35[[#This Row],[Net Cash]]+$X$5), IF($S$3="npc", IF($T$3=1, Price35[[#This Row],[Net Price Credit]]+$W$6, Price35[[#This Row],[Net Price Credit]]+$X$6), IF($S$3="w", IF($T$3=1, Price35[[#This Row],[Wsp]]+$W$6, Price35[[#This Row],[Wsp]]+$X$6), "")))), 10)) -> 1020
B34: 970 | C34: shawl | D34: Kashmiri | F34: jal | G34: 460 | I34: 375 | J34: =IF(SUMIF(G34:I34,"<>")=0,"",SUM(G34:I34)) -> 835 | K34: =IF(ISNUMBER(L34), IF(CEILING(ROUND(L34*0.95,2),5)=420, 425, CEILING(ROUND(L34*0.95,2),5) ), "" ) -> 1075 | L34: =IF(ISNUMBER(J34), IF(CEILING(ROUND(J34*1.35,2),5)=420, 425, CEILING(ROUND(J34*1.35,2),5) ), "" ) -> 1130 | M34: =IF(AND(ISNUMBER(J34),ISNUMBER(G34)), IF( CEILING( ROUND((J34*1.5) * IF(J34*1.5 <= 2500, 1.05, 1.18), 2), IF(ROUND((J34*1.5) * IF(J34*1.5 <= 2500, 1.05, 1.18), 2) < 2500, 25, 50) )=420, 425, CEILING( ROUND((J34*1.5) * IF(J34*1.5 <= 2500, 1.05, 1.18), 2), IF(ROUND((J34*1.5) * IF(J34*1.5 <= 2500, 1.05, 1.18), 2) < 2500, 25, 50) ) ), "" ) -> 1325 | N34: =IF(ISNUMBER(G34), CEILING(ROUND(L34*0.92,2),5), "") -> 1040 | O34: =IF(ISNUMBER(L34), IF(CEILING(ROUND(L34*1.07,2),5)=420, 425, CEILING(ROUND(L34*1.07,2),5) ), "" ) -> 1210 | P34: =IF((((G34*1.5)+50)/0.835)<2500, MROUND(((((G34*1.5)+50)/0.835)*1.05)*2,10), MROUND(((((G34*1.5)+50)/0.835)*1.18)*2,10)) -> 1860 | Q34: =IF($S$3="","", MROUND( IF($S$3="m", IF($T$3=1, Price35[[#This Row],[Mrp]]+$W$4, Price35[[#This Row],[Mrp]]+$X$4), IF($S$3="nc", IF($T$3=1, Price35[[#This Row],[Net Cash]]+$W$5, Price35[[#This Row],[Net Cash]]+$X$5), IF($S$3="npc", IF($T$3=1, Price35[[#This Row],[Net Price Credit]]+$W$6, Price35[[#This Row],[Net Price Credit]]+$X$6), IF($S$3="w", IF($T$3=1, Price35[[#This Row],[Wsp]]+$W$6, Price35[[#This Row],[Wsp]]+$X$6), "")))), 10)) -> 1400
B35: 971 | C35: shawl | D35: Kashmiri | F35: variety 13 no. | G35: 425 | I35: 210 | J35: =IF(SUMIF(G35:I35,"<>")=0,"",SUM(G35:I35)) -> 635 | K35: =IF(ISNUMBER(L35), IF(CEILING(ROUND(L35*0.95,2),5)=420, 425, CEILING(ROUND(L35*0.95,2),5) ), "" ) -> 820 | L35: =IF(ISNUMBER(J35), IF(CEILING(ROUND(J35*1.35,2),5)=420, 425, CEILING(ROUND(J35*1.35,2),5) ), "" ) -> 860 | M35: =IF(AND(ISNUMBER(J35),ISNUMBER(G35)), IF( CEILING( ROUND((J35*1.5) * IF(J35*1.5 <= 2500, 1.05, 1.18), 2), IF(ROUND((J35*1.5) * IF(J35*1.5 <= 2500, 1.05, 1.18), 2) < 2500, 25, 50) )=420, 425, CEILING( ROUND((J35*1.5) * IF(J35*1.5 <= 2500, 1.05, 1.18), 2), IF(ROUND((J35*1.5) * IF(J35*1.5 <= 2500, 1.05, 1.18), 2) < 2500, 25, 50) ) ), "" ) -> 1025 | N35: =IF(ISNUMBER(G35), CEILING(ROUND(L35*0.92,2),5), "") -> 795 | O35: =IF(ISNUMBER(L35), IF(CEILING(ROUND(L35*1.07,2),5)=420, 425, CEILING(ROUND(L35*1.07,2),5) ), "" ) -> 925 | P35: =IF((((G35*1.5)+50)/0.835)<2500, MROUND(((((G35*1.5)+50)/0.835)*1.05)*2,10), MROUND(((((G35*1.5)+50)/0.835)*1.18)*2,10)) -> 1730 | Q35: =IF($S$3="","", MROUND( IF($S$3="m", IF($T$3=1, Price35[[#This Row],[Mrp]]+$W$4, Price35[[#This Row],[Mrp]]+$X$4), IF($S$3="nc", IF($T$3=1, Price35[[#This Row],[Net Cash]]+$W$5, Price35[[#This Row],[Net Cash]]+$X$5), IF($S$3="npc", IF($T$3=1, Price35[[#This Row],[Net Price Credit]]+$W$6, Price35[[#This Row],[Net Price Credit]]+$X$6), IF($S$3="w", IF($T$3=1, Price35[[#This Row],[Wsp]]+$W$6, Price35[[#This Row],[Wsp]]+$X$6), "")))), 10)) -> 1100
B36: 973 | C36: shawl | D36: Kashmiri | F36: hashia variety | G36: 460 | I36: 340 | J36: =IF(SUMIF(G36:I36,"<>")=0,"",SUM(G36:I36)) -> 800 | K36: =IF(ISNUMBER(L36), IF(CEILING(ROUND(L36*0.95,2),5)=420, 425, CEILING(ROUND(L36*0.95,2),5) ), "" ) -> 1030 | L36: =IF(ISNUMBER(J36), IF(CEILING(ROUND(J36*1.35,2),5)=420, 425, CEILING(ROUND(J36*1.35,2),5) ), "" ) -> 1080 | M36: =IF(AND(ISNUMBER(J36),ISNUMBER(G36)), IF( CEILING( ROUND((J36*1.5) * IF(J36*1.5 <= 2500, 1.05, 1.18), 2), IF(ROUND((J36*1.5) * IF(J36*1.5 <= 2500, 1.05, 1.18), 2) < 2500, 25, 50) )=420, 425, CEILING( ROUND((J36*1.5) * IF(J36*1.5 <= 2500, 1.05, 1.18), 2), IF(ROUND((J36*1.5) * IF(J36*1.5 <= 2500, 1.05, 1.18), 2) < 2500, 25, 50) ) ), "" ) -> 1275 | N36: =IF(ISNUMBER(G36), CEILING(ROUND(L36*0.92,2),5), "") -> 995 | O36: =IF(ISNUMBER(L36), IF(CEILING(ROUND(L36*1.07,2),5)=420, 425, CEILING(ROUND(L36*1.07,2),5) ), "" ) -> 1160 | P36: =IF((((G36*1.5)+50)/0.835)<2500, MROUND(((((G36*1.5)+50)/0.835)*1.05)*2,10), MROUND(((((G36*1.5)+50)/0.835)*1.18)*2,10)) -> 1860 | Q36: =IF($S$3="","", MROUND( IF($S$3="m", IF($T$3=1, Price35[[#This Row],[Mrp]]+$W$4, Price35[[#This Row],[Mrp]]+$X$4), IF($S$3="nc", IF($T$3=1, Price35[[#This Row],[Net Cash]]+$W$5, Price35[[#This Row],[Net Cash]]+$X$5), IF($S$3="npc", IF($T$3=1, Price35[[#This Row],[Net Price Credit]]+$W$6, Price35[[#This Row],[Net Price Credit]]+$X$6), IF($S$3="w", IF($T$3=1, Price35[[#This Row],[Wsp]]+$W$6, Price35[[#This Row],[Wsp]]+$X$6), "")))), 10)) -> 1350
B37: 1004 | C37: shawl | D37: Kashmiri | F37: 2-4 b.r kingri | G37: 560 | I37: 145 | J37: =IF(SUMIF(G37:I37,"<>")=0,"",SUM(G37:I37)) -> 705 | K37: =IF(ISNUMBER(L37), IF(CEILING(ROUND(L37*0.95,2),5)=420, 425, CEILING(ROUND(L37*0.95,2),5) ), "" ) -> 910 | L37: =IF(ISNUMBER(J37), IF(CEILING(ROUND(J37*1.35,2),5)=420, 425, CEILING(ROUND(J37*1.35,2),5) ), "" ) -> 955 | M37: =IF(AND(ISNUMBER(J37),ISNUMBER(G37)), IF( CEILING( ROUND((J37*1.5) * IF(J37*1.5 <= 2500, 1.05, 1.18), 2), IF(ROUND((J37*1.5) * IF(J37*1.5 <= 2500, 1.05, 1.18), 2) < 2500, 25, 50) )=420, 425, CEILING( ROUND((J37*1.5) * IF(J37*1.5 <= 2500, 1.05, 1.18), 2), IF(ROUND((J37*1.5) * IF(J37*1.5 <= 2500, 1.05, 1.18), 2) < 2500, 25, 50) ) ), "" ) -> 1125 | N37: =IF(ISNUMBER(G37), CEILING(ROUND(L37*0.92,2),5), "") -> 880 | O37: =IF(ISNUMBER(L37), IF(CEILING(ROUND(L37*1.07,2),5)=420, 425, CEILING(ROUND(L37*1.07,2),5) ), "" ) -> 1025 | P37: =IF((((G37*1.5)+50)/0.835)<2500, MROUND(((((G37*1.5)+50)/0.835)*1.05)*2,10), MROUND(((((G37*1.5)+50)/0.835)*1.18)*2,10)) -> 2240 | Q37: =IF($S$3="","", MROUND( IF($S$3="m", IF($T$3=1, Price35[[#This Row],[Mrp]]+$W$4, Price35[[#This Row],[Mrp]]+$X$4), IF($S$3="nc", IF($T$3=1, Price35[[#This Row],[Net Cash]]+$W$5, Price35[[#This Row],[Net Cash]]+$X$5), IF($S$3="npc", IF($T$3=1, Price35[[#This Row],[Net Price Credit]]+$W$6, Price35[[#This Row],[Net Price Credit]]+$X$6), IF($S$3="w", IF($T$3=1, Price35[[#This Row],[Wsp]]+$W$6, Price35[[#This Row],[Wsp]]+$X$6), "")))), 10)) -> 1200
A38: 2026 | B38: 1005 | C38: shawl | D38: Kashmiri | E38: sharma | F38: shahtoosh multihead 45*90 | G38: 460 | I38: 300 | J38: =IF(SUMIF(G38:I38,"<>")=0,"",SUM(G38:I38)) -> 760 | K38: =IF(ISNUMBER(L38), IF(CEILING(ROUND(L38*0.95,2),5)=420, 425, CEILING(ROUND(L38*0.95,2),5) ), "" ) -> 980 | L38: =IF(ISNUMBER(J38), IF(CEILING(ROUND(J38*1.35,2),5)=420, 425, CEILING(ROUND(J38*1.35,2),5) ), "" ) -> 1030 | M38: =IF(AND(ISNUMBER(J38),ISNUMBER(G38)), IF( CEILING( ROUND((J38*1.5) * IF(J38*1.5 <= 2500, 1.05, 1.18), 2), IF(ROUND((J38*1.5) * IF(J38*1.5 <= 2500, 1.05, 1.18), 2) < 2500, 25, 50) )=420, 425, CEILING( ROUND((J38*1.5) * IF(J38*1.5 <= 2500, 1.05, 1.18), 2), IF(ROUND((J38*1.5) * IF(J38*1.5 <= 2500, 1.05, 1.18), 2) < 2500, 25, 50) ) ), "" ) -> 1200 | N38: =IF(ISNUMBER(G38), CEILING(ROUND(L38*0.92,2),5), "") -> 950 | O38: =IF(ISNUMBER(L38), IF(CEILING(ROUND(L38*1.07,2),5)=420, 425, CEILING(ROUND(L38*1.07,2),5) ), "" ) -> 1105 | P38: =IF((((G38*1.5)+50)/0.835)<2500, MROUND(((((G38*1.5)+50)/0.835)*1.05)*2,10), MROUND(((((G38*1.5)+50)/0.835)*1.18)*2,10)) -> 1860 | Q38: =IF($S$3="","", MROUND( IF($S$3="m", IF($T$3=1, Price35[[#This Row],[Mrp]]+$W$4, Price35[[#This Row],[Mrp]]+$X$4), IF($S$3="nc", IF($T$3=1, Price35[[#This Row],[Net Cash]]+$W$5, Price35[[#This Row],[Net Cash]]+$X$5), IF($S$3="npc", IF($T$3=1, Price35[[#This Row],[Net Price Credit]]+$W$6, Price35[[#This Row],[Net Price Credit]]+$X$6), IF($S$3="w", IF($T$3=1, Price35[[#This Row],[Wsp]]+$W$6, Price35[[#This Row],[Wsp]]+$X$6), "")))), 10)) -> 1270
A39: 2026 | B39: 1006 | C39: shawl | D39: Kashmiri | F39: 2-4 hashia multihead new | G39: 550 | I39: 400 | J39: =IF(SUMIF(G39:I39,"<>")=0,"",SUM(G39:I39)) -> 950 | K39: =IF(ISNUMBER(L39), IF(CEILING(ROUND(L39*0.95,2),5)=420, 425, CEILING(ROUND(L39*0.95,2),5) ), "" ) -> 1225 | L39: =IF(ISNUMBER(J39), IF(CEILING(ROUND(J39*1.35,2),5)=420, 425, CEILING(ROUND(J39*1.35,2),5) ), "" ) -> 1285 | M39: =IF(AND(ISNUMBER(J39),ISNUMBER(G39)), IF( CEILING( ROUND((J39*1.5) * IF(J39*1.5 <= 2500, 1.05, 1.18), 2), IF(ROUND((J39*1.5) * IF(J39*1.5 <= 2500, 1.05, 1.18), 2) < 2500, 25, 50) )=420, 425, CEILING( ROUND((J39*1.5) * IF(J39*1.5 <= 2500, 1.05, 1.18), 2), IF(ROUND((J39*1.5) * IF(J39*1.5 <= 2500, 1.05, 1.18), 2) < 2500, 25, 50) ) ), "" ) -> 1500 | N39: =IF(ISNUMBER(G39), CEILING(ROUND(L39*0.92,2),5), "") -> 1185 | O39: =IF(ISNUMBER(L39), IF(CEILING(ROUND(L39*1.07,2),5)=420, 425, CEILING(ROUND(L39*1.07,2),5) ), "" ) -> 1375 | P39: =IF((((G39*1.5)+50)/0.835)<2500, MROUND(((((G39*1.5)+50)/0.835)*1.05)*2,10), MROUND(((((G39*1.5)+50)/0.835)*1.18)*2,10)) -> 2200 | Q39: =IF($S$3="","", MROUND( IF($S$3="m", IF($T$3=1, Price35[[#This Row],[Mrp]]+$W$4, Price35[[#This Row],[Mrp]]+$X$4), IF($S$3="nc", IF($T$3=1, Price35[[#This Row],[Net Cash]]+$W$5, Price35[[#This Row],[Net Cash]]+$X$5), IF($S$3="npc", IF($T$3=1, Price35[[#This Row],[Net Price Credit]]+$W$6, Price35[[#This Row],[Net Price Credit]]+$X$6), IF($S$3="w", IF($T$3=1, Price35[[#This Row],[Wsp]]+$W$6, Price35[[#This Row],[Wsp]]+$X$6), "")))), 10)) -> 1570
B40: 1007 | C40: shawl | D40: Kashmiri | F40: 2-4 hashia | G40: 560 | I40: 210 | J40: =IF(SUMIF(G40:I40,"<>")=0,"",SUM(G40:I40)) -> 770 | K40: =IF(ISNUMBER(L40), IF(CEILING(ROUND(L40*0.95,2),5)=420, 425, CEILING(ROUND(L40*0.95,2),5) ), "" ) -> 990 | L40: =IF(ISNUMBER(J40), IF(CEILING(ROUND(J40*1.35,2),5)=420, 425, CEILING(ROUND(J40*1.35,2),5) ), "" ) -> 1040 | M40: =IF(AND(ISNUMBER(J40),ISNUMBER(G40)), IF( CEILING( ROUND((J40*1.5) * IF(J40*1.5 <= 2500, 1.05, 1.18), 2), IF(ROUND((J40*1.5) * IF(J40*1.5 <= 2500, 1.05, 1.18), 2) < 2500, 25, 50) )=420, 425, CEILING( ROUND((J40*1.5) * IF(J40*1.5 <= 2500, 1.05, 1.18), 2), IF(ROUND((J40*1.5) * IF(J40*1.5 <= 2500, 1.05, 1.18), 2) < 2500, 25, 50) ) ), "" ) -> 1225 | N40: =IF(ISNUMBER(G40), CEILING(ROUND(L40*0.92,2),5), "") -> 960 | O40: =IF(ISNUMBER(L40), IF(CEILING(ROUND(L40*1.07,2),5)=420, 425, CEILING(ROUND(L40*1.07,2),5) ), "" ) -> 1115 | P40: =IF((((G40*1.5)+50)/0.835)<2500, MROUND(((((G40*1.5)+50)/0.835)*1.05)*2,10), MROUND(((((G40*1.5)+50)/0.835)*1.18)*2,10)) -> 2240 | Q40: =IF($S$3="","", MROUND( IF($S$3="m", IF($T$3=1, Price35[[#This Row],[Mrp]]+$W$4, Price35[[#This Row],[Mrp]]+$X$4), IF($S$3="nc", IF($T$3=1, Price35[[#This Row],[Net Cash]]+$W$5, Price35[[#This Row],[Net Cash]]+$X$5), IF($S$3="npc", IF($T$3=1, Price35[[#This Row],[Net Price Credit]]+$W$6, Price35[[#This Row],[Net Price Credit]]+$X$6), IF($S$3="w", IF($T$3=1, Price35[[#This Row],[Wsp]]+$W$6, Price35[[#This Row],[Wsp]]+$X$6), "")))), 10)) -> 1300
B41: 1008 | C41: shawl | D41: Kashmiri | F41: hashia multihead 45 | G41: 460 | I41: 400 | J41: =IF(SUMIF(G41:I41,"<>")=0,"",SUM(G41:I41)) -> 860 | K41: =IF(ISNUMBER(L41), IF(CEILING(ROUND(L41*0.95,2),5)=420, 425, CEILING(ROUND(L41*0.95,2),5) ), "" ) -> 1110 | L41: =IF(ISNUMBER(J41), IF(CEILING(ROUND(J41*1.35,2),5)=420, 425, CEILING(ROUND(J41*1.35,2),5) ), "" ) -> 1165 | M41: =IF(AND(ISNUMBER(J41),ISNUMBER(G41)), IF( CEILING( ROUND((J41*1.5) * IF(J41*1.5 <= 2500, 1.05, 1.18), 2), IF(ROUND((J41*1.5) * IF(J41*1.5 <= 2500, 1.05, 1.18), 2) < 2500, 25, 50) )=420, 425, CEILING( ROUND((J41*1.5) * IF(J41*1.5 <= 2500, 1.05, 1.18), 2), IF(ROUND((J41*1.5) * IF(J41*1.5 <= 2500, 1.05, 1.18), 2) < 2500, 25, 50) ) ), "" ) -> 1375 | N41: =IF(ISNUMBER(G41), CEILING(ROUND(L41*0.92,2),5), "") -> 1075 | O41: =IF(ISNUMBER(L41), IF(CEILING(ROUND(L41*1.07,2),5)=420, 425, CEILING(ROUND(L41*1.07,2),5) ), "" ) -> 1250 | P41: =IF((((G41*1.5)+50)/0.835)<2500, MROUND(((((G41*1.5)+50)/0.835)*1.05)*2,10), MROUND(((((G41*1.5)+50)/0.835)*1.18)*2,10)) -> 1860 | Q41: =IF($S$3="","", MROUND( IF($S$3="m", IF($T$3=1, Price35[[#This Row],[Mrp]]+$W$4, Price35[[#This Row],[Mrp]]+$X$4), IF($S$3="nc", IF($T$3=1, Price35[[#This Row],[Net Cash]]+$W$5, Price35[[#This Row],[Net Cash]]+$X$5), IF($S$3="npc", IF($T$3=1, Price35[[#This Row],[Net Price Credit]]+$W$6, Price35[[#This Row],[Net Price Credit]]+$X$6), IF($S$3="w", IF($T$3=1, Price35[[#This Row],[Wsp]]+$W$6, Price35[[#This Row],[Wsp]]+$X$6), "")))), 10)) -> 1450
B42: 1009 | C42: shawl | D42: Kashmiri | F42: 90*45 c.n.d | G42: 470 | I42: 165 | J42: =IF(SUMIF(G42:I42,"<>")=0,"",SUM(G42:I42)) -> 635 | K42: =IF(ISNUMBER(L42), IF(CEILING(ROUND(L42*0.95,2),5)=420, 425, CEILING(ROUND(L42*0.95,2),5) ), "" ) -> 820 | L42: =IF(ISNUMBER(J42), IF(CEILING(ROUND(J42*1.35,2),5)=420, 425, CEILING(ROUND(J42*1.35,2),5) ), "" ) -> 860 | M42: =IF(AND(ISNUMBER(J42),ISNUMBER(G42)), IF( CEILING( ROUND((J42*1.5) * IF(J42*1.5 <= 2500, 1.05, 1.18), 2), IF(ROUND((J42*1.5) * IF(J42*1.5 <= 2500, 1.05, 1.18), 2) < 2500, 25, 50) )=420, 425, CEILING( ROUND((J42*1.5) * IF(J42*1.5 <= 2500, 1.05, 1.18), 2), IF(ROUND((J42*1.5) * IF(J42*1.5 <= 2500, 1.05, 1.18), 2) < 2500, 25, 50) ) ), "" ) -> 1025 | N42: =IF(ISNUMBER(G42), CEILING(ROUND(L42*0.92,2),5), "") -> 795 | O42: =IF(ISNUMBER(L42), IF(CEILING(ROUND(L42*1.07,2),5)=420, 425, CEILING(ROUND(L42*1.07,2),5) ), "" ) -> 925 | P42: =IF((((G42*1.5)+50)/0.835)<2500, MROUND(((((G42*1.5)+50)/0.835)*1.05)*2,10), MROUND(((((G42*1.5)+50)/0.835)*1.18)*2,10)) -> 1900 | Q42: =IF($S$3="","", MROUND( IF($S$3="m", IF($T$3=1, Price35[[#This Row],[Mrp]]+$W$4, Price35[[#This Row],[Mrp]]+$X$4), IF($S$3="nc", IF($T$3=1, Price35[[#This Row],[Net Cash]]+$W$5, Price35[[#This Row],[Net Cash]]+$X$5), IF($S$3="npc", IF($T$3=1, Price35[[#This Row],[Net Price Credit]]+$W$6, Price35[[#This Row],[Net Price Credit]]+$X$6), IF($S$3="w", IF($T$3=1, Price35[[#This Row],[Wsp]]+$W$6, Price35[[#This Row],[Wsp]]+$X$6), "")))), 10)) -> 1100
B43: 1011 | C43: shawl | D43: Kashmiri | F43: 2-8 shahtoosh | G43: 630 | I43: 130 | J43: =IF(SUMIF(G43:I43,"<>")=0,"",SUM(G43:I43)) -> 760 | K43: =IF(ISNUMBER(L43), IF(CEILING(ROUND(L43*0.95,2),5)=420, 425, CEILING(ROUND(L43*0.95,2),5) ), "" ) -> 980 | L43: =IF(ISNUMBER(J43), IF(CEILING(ROUND(J43*1.35,2),5)=420, 425, CEILING(ROUND(J43*1.35,2),5) ), "" ) -> 1030 | M43: =IF(AND(ISNUMBER(J43),ISNUMBER(G43)), IF( CEILING( ROUND((J43*1.5) * IF(J43*1.5 <= 2500, 1.05, 1.18), 2), IF(ROUND((J43*1.5) * IF(J43*1.5 <= 2500, 1.05, 1.18), 2) < 2500, 25, 50) )=420, 425, CEILING( ROUND((J43*1.5) * IF(J43*1.5 <= 2500, 1.05, 1.18), 2), IF(ROUND((J43*1.5) * IF(J43*1.5 <= 2500, 1.05, 1.18), 2) < 2500, 25, 50) ) ), "" ) -> 1200 | N43: =IF(ISNUMBER(G43), CEILING(ROUND(L43*0.92,2),5), "") -> 950 | O43: =IF(ISNUMBER(L43), IF(CEILING(ROUND(L43*1.07,2),5)=420, 425, CEILING(ROUND(L43*1.07,2),5) ), "" ) -> 1105 | P43: =IF((((G43*1.5)+50)/0.835)<2500, MROUND(((((G43*1.5)+50)/0.835)*1.05)*2,10), MROUND(((((G43*1.5)+50)/0.835)*1.18)*2,10)) -> 2500 | Q43: =IF($S$3="","", MROUND( IF($S$3="m", IF($T$3=1, Price35[[#This Row],[Mrp]]+$W$4, Price35[[#This Row],[Mrp]]+$X$4), IF($S$3="nc", IF($T$3=1, Price35[[#This Row],[Net Cash]]+$W$5, Price35[[#This Row],[Net Cash]]+$X$5), IF($S$3="npc", IF($T$3=1, Price35[[#This Row],[Net Price Credit]]+$W$6, Price35[[#This Row],[Net Price Credit]]+$X$6), IF($S$3="w", IF($T$3=1, Price35[[#This Row],[Wsp]]+$W$6, Price35[[#This Row],[Wsp]]+$X$6), "")))), 10)) -> 1270
A44: 2026 | B44: 1012 | C44: shawl | D44: Kashmiri | E44: sharma | F44: 2-4 shahtoosh multihead | G44: 550 | I44: 300 | J44: =IF(SUMIF(G44:I44,"<>")=0,"",SUM(G44:I44)) -> 850 | K44: =IF(ISNUMBER(L44), IF(CEILING(ROUND(L44*0.95,2),5)=420, 425, CEILING(ROUND(L44*0.95,2),5) ), "" ) -> 1095 | L44: =IF(ISNUMBER(J44), IF(CEILING(ROUND(J44*1.35,2),5)=420, 425, CEILING(ROUND(J44*1.35,2),5) ), "" ) -> 1150 | M44: =IF(AND(ISNUMBER(J44),ISNUMBER(G44)), IF( CEILING( ROUND((J44*1.5) * IF(J44*1.5 <= 2500, 1.05, 1.18), 2), IF(ROUND((J44*1.5) * IF(J44*1.5 <= 2500, 1.05, 1.18), 2) < 2500, 25, 50) )=420, 425, CEILING( ROUND((J44*1.5) * IF(J44*1.5 <= 2500, 1.05, 1.18), 2), IF(ROUND((J44*1.5) * IF(J44*1.5 <= 2500, 1.05, 1.18), 2) < 2500, 25, 50) ) ), "" ) -> 1350 | N44: =IF(ISNUMBER(G44), CEILING(ROUND(L44*0.92,2),5), "") -> 1060 | O44: =IF(ISNUMBER(L44), IF(CEILING(ROUND(L44*1.07,2),5)=420, 425, CEILING(ROUND(L44*1.07,2),5) ), "" ) -> 1235 | P44: =IF((((G44*1.5)+50)/0.835)<2500, MROUND(((((G44*1.5)+50)/0.835)*1.05)*2,10), MROUND(((((G44*1.5)+50)/0.835)*1.18)*2,10)) -> 2200 | Q44: =IF($S$3="","", MROUND( IF($S$3="m", IF($T$3=1, Price35[[#This Row],[Mrp]]+$W$4, Price35[[#This Row],[Mrp]]+$X$4), IF($S$3="nc", IF($T$3=1, Price35[[#This Row],[Net Cash]]+$W$5, Price35[[#This Row],[Net Cash]]+$X$5), IF($S$3="npc", IF($T$3=1, Price35[[#This Row],[Net Price Credit]]+$W$6, Price35[[#This Row],[Net Price Credit]]+$X$6), IF($S$3="w", IF($T$3=1, Price35[[#This Row],[Wsp]]+$W$6, Price35[[#This Row],[Wsp]]+$X$6), "")))), 10)) -> 1420
A45: 2026 | B45: 1016 | C45: shawl | D45: Kashmiri | F45: 2-4 c.n.d multihead | G45: 550 | I45: 300 | J45: =IF(SUMIF(G45:I45,"<>")=0,"",SUM(G45:I45)) -> 850 | K45: =IF(ISNUMBER(L45), IF(CEILING(ROUND(L45*0.95,2),5)=420, 425, CEILING(ROUND(L45*0.95,2),5) ), "" ) -> 1095 | L45: =IF(ISNUMBER(J45), IF(CEILING(ROUND(J45*1.35,2),5)=420, 425, CEILING(ROUND(J45*1.35,2),5) ), "" ) -> 1150 | M45: =IF(AND(ISNUMBER(J45),ISNUMBER(G45)), IF( CEILING( ROUND((J45*1.5) * IF(J45*1.5 <= 2500, 1.05, 1.18), 2), IF(ROUND((J45*1.5) * IF(J45*1.5 <= 2500, 1.05, 1.18), 2) < 2500, 25, 50) )=420, 425, CEILING( ROUND((J45*1.5) * IF(J45*1.5 <= 2500, 1.05, 1.18), 2), IF(ROUND((J45*1.5) * IF(J45*1.5 <= 2500, 1.05, 1.18), 2) < 2500, 25, 50) ) ), "" ) -> 1350 | N45: =IF(ISNUMBER(G45), CEILING(ROUND(L45*0.92,2),5), "") -> 1060 | O45: =IF(ISNUMBER(L45), IF(CEILING(ROUND(L45*1.07,2),5)=420, 425, CEILING(ROUND(L45*1.07,2),5) ), "" ) -> 1235 | P45: =IF((((G45*1.5)+50)/0.835)<2500, MROUND(((((G45*1.5)+50)/0.835)*1.05)*2,10), MROUND(((((G45*1.5)+50)/0.835)*1.18)*2,10)) -> 2200 | Q45: =IF($S$3="","", MROUND( IF($S$3="m", IF($T$3=1, Price35[[#This Row],[Mrp]]+$W$4, Price35[[#This Row],[Mrp]]+$X$4), IF($S$3="nc", IF($T$3=1, Price35[[#This Row],[Net Cash]]+$W$5, Price35[[#This Row],[Net Cash]]+$X$5), IF($S$3="npc", IF($T$3=1, Price35[[#This Row],[Net Price Credit]]+$W$6, Price35[[#This Row],[Net Price Credit]]+$X$6), IF($S$3="w", IF($T$3=1, Price35[[#This Row],[Wsp]]+$W$6, Price35[[#This Row],[Wsp]]+$X$6), "")))), 10)) -> 1420
B46: 1017 | C46: shawl | D46: Kashmiri | F46: 90*45 char hashia | G46: 470 | I46: 175 | J46: =IF(SUMIF(G46:I46,"<>")=0,"",SUM(G46:I46)) -> 645 | K46: =IF(ISNUMBER(L46), IF(CEILING(ROUND(L46*0.95,2),5)=420, 425, CEILING(ROUND(L46*0.95,2),5) ), "" ) -> 835 | L46: =IF(ISNUMBER(J46), IF(CEILING(ROUND(J46*1.35,2),5)=420, 425, CEILING(ROUND(J46*1.35,2),5) ), "" ) -> 875 | M46: =IF(AND(ISNUMBER(J46),ISNUMBER(G46)), IF( CEILING( ROUND((J46*1.5) * IF(J46*1.5 <= 2500, 1.05, 1.18), 2), IF(ROUND((J46*1.5) * IF(J46*1.5 <= 2500, 1.05, 1.18), 2) < 2500, 25, 50) )=420, 425, CEILING( ROUND((J46*1.5) * IF(J46*1.5 <= 2500, 1.05, 1.18), 2), IF(ROUND((J46*1.5) * IF(J46*1.5 <= 2500, 1.05, 1.18), 2) < 2500, 25, 50) ) ), "" ) -> 1025 | N46: =IF(ISNUMBER(G46), CEILING(ROUND(L46*0.92,2),5), "") -> 805 | O46: =IF(ISNUMBER(L46), IF(CEILING(ROUND(L46*1.07,2),5)=420, 425, CEILING(ROUND(L46*1.07,2),5) ), "" ) -> 940 | P46: =IF((((G46*1.5)+50)/0.835)<2500, MROUND(((((G46*1.5)+50)/0.835)*1.05)*2,10), MROUND(((((G46*1.5)+50)/0.835)*1.18)*2,10)) -> 1900 | Q46: =IF($S$3="","", MROUND( IF($S$3="m", IF($T$3=1, Price35[[#This Row],[Mrp]]+$W$4, Price35[[#This Row],[Mrp]]+$X$4), IF($S$3="nc", IF($T$3=1, Price35[[#This Row],[Net Cash]]+$W$5, Price35[[#This Row],[Net Cash]]+$X$5), IF($S$3="npc", IF($T$3=1, Price35[[#This Row],[Net Price Credit]]+$W$6, Price35[[#This Row],[Net Price Credit]]+$X$6), IF($S$3="w", IF($T$3=1, Price35[[#This Row],[Wsp]]+$W$6, Price35[[#This Row],[Wsp]]+$X$6), "")))), 10)) -> 1100
B47: 1018 | C47: shawl | D47: Kashmiri | F47: 90*45 shahtoosh | G47: 470 | I47: 120 | J47: =IF(SUMIF(G47:I47,"<>")=0,"",SUM(G47:I47)) -> 590 | K47: =IF(ISNUMBER(L47), IF(CEILING(ROUND(L47*0.95,2),5)=420, 425, CEILING(ROUND(L47*0.95,2),5) ), "" ) -> 760 | L47: =IF(ISNUMBER(J47), IF(CEILING(ROUND(J47*1.35,2),5)=420, 425, CEILING(ROUND(J47*1.35,2),5) ), "" ) -> 800 | M47: =IF(AND(ISNUMBER(J47),ISNUMBER(G47)), IF( CEILING( ROUND((J47*1.5) * IF(J47*1.5 <= 2500, 1.05, 1.18), 2), IF(ROUND((J47*1.5) * IF(J47*1.5 <= 2500, 1.05, 1.18), 2) < 2500, 25, 50) )=420, 425, CEILING( ROUND((J47*1.5) * IF(J47*1.5 <= 2500, 1.05, 1.18), 2), IF(ROUND((J47*1.5) * IF(J47*1.5 <= 2500, 1.05, 1.18), 2) < 2500, 25, 50) ) ), "" ) -> 950 | N47: =IF(ISNUMBER(G47), CEILING(ROUND(L47*0.92,2),5), "") -> 740 | O47: =IF(ISNUMBER(L47), IF(CEILING(ROUND(L47*1.07,2),5)=420, 425, CEILING(ROUND(L47*1.07,2),5) ), "" ) -> 860 | P47: =IF((((G47*1.5)+50)/0.835)<2500, MROUND(((((G47*1.5)+50)/0.835)*1.05)*2,10), MROUND(((((G47*1.5)+50)/0.835)*1.18)*2,10)) -> 1900 | Q47: =IF($S$3="","", MROUND( IF($S$3="m", IF($T$3=1, Price35[[#This Row],[Mrp]]+$W$4, Price35[[#This Row],[Mrp]]+$X$4), IF($S$3="nc", IF($T$3=1, Price35[[#This Row],[Net Cash]]+$W$5, Price35[[#This Row],[Net Cash]]+$X$5), IF($S$3="npc", IF($T$3=1, Price35[[#This Row],[Net Price Credit]]+$W$6, Price35[[#This Row],[Net Price Credit]]+$X$6), IF($S$3="w", IF($T$3=1, Price35[[#This Row],[Wsp]]+$W$6, Price35[[#This Row],[Wsp]]+$X$6), "")))), 10)) -> 1020
B48: 1019 | C48: shawl | D48: Kashmiri | F48: s.s tape 50" | G48: 600 | I48: 15 | J48: =IF(SUMIF(G48:I48,"<>")=0,"",SUM(G48:I48)) -> 615 | K48: =IF(ISNUMBER(L48), IF(CEILING(ROUND(L48*0.95,2),5)=420, 425, CEILING(ROUND(L48*0.95,2),5) ), "" ) -> 795 | L48: =IF(ISNUMBER(J48), IF(CEILING(ROUND(J48*1.35,2),5)=420, 425, CEILING(ROUND(J48*1.35,2),5) ), "" ) -> 835 | M48: =IF(AND(ISNUMBER(J48),ISNUMBER(G48)), IF( CEILING( ROUND((J48*1.5) * IF(J48*1.5 <= 2500, 1.05, 1.18), 2), IF(ROUND((J48*1.5) * IF(J48*1.5 <= 2500, 1.05, 1.18), 2) < 2500, 25, 50) )=420, 425, CEILING( ROUND((J48*1.5) * IF(J48*1.5 <= 2500, 1.05, 1.18), 2), IF(ROUND((J48*1.5) * IF(J48*1.5 <= 2500, 1.05, 1.18), 2) < 2500, 25, 50) ) ), "" ) -> 975 | N48: =IF(ISNUMBER(G48), CEILING(ROUND(L48*0.92,2),5), "") -> 770 | O48: =IF(ISNUMBER(L48), IF(CEILING(ROUND(L48*1.07,2),5)=420, 425, CEILING(ROUND(L48*1.07,2),5) ), "" ) -> 895 | P48: =IF((((G48*1.5)+50)/0.835)<2500, MROUND(((((G48*1.5)+50)/0.835)*1.05)*2,10), MROUND(((((G48*1.5)+50)/0.835)*1.18)*2,10)) -> 2390 | Q48: =IF($S$3="","", MROUND( IF($S$3="m", IF($T$3=1, Price35[[#This Row],[Mrp]]+$W$4, Price35[[#This Row],[Mrp]]+$X$4), IF($S$3="nc", IF($T$3=1, Price35[[#This Row],[Net Cash]]+$W$5, Price35[[#This Row],[Net Cash]]+$X$5), IF($S$3="npc", IF($T$3=1, Price35[[#This Row],[Net Price Credit]]+$W$6, Price35[[#This Row],[Net Price Credit]]+$X$6), IF($S$3="w", IF($T$3=1, Price35[[#This Row],[Wsp]]+$W$6, Price35[[#This Row],[Wsp]]+$X$6), "")))), 10)) -> 1050
A49: 2026 | B49: 1020 | C49: shawl | D49: Kashmiri | E49: sharma | F49: c.n.d 45" multihead new | G49: 460 | I49: 300 | J49: =IF(SUMIF(G49:I49,"<>")=0,"",SUM(G49:I49)) -> 760 | K49: =IF(ISNUMBER(L49), IF(CEILING(ROUND(L49*0.95,2),5)=420, 425, CEILING(ROUND(L49*0.95,2),5) ), "" ) -> 980 | L49: =IF(ISNUMBER(J49), IF(CEILING(ROUND(J49*1.35,2),5)=420, 425, CEILING(ROUND(J49*1.35,2),5) ), "" ) -> 1030 | M49: =IF(AND(ISNUMBER(J49),ISNUMBER(G49)), IF( CEILING( ROUND((J49*1.5) * IF(J49*1.5 <= 2500, 1.05, 1.18), 2), IF(ROUND((J49*1.5) * IF(J49*1.5 <= 2500, 1.05, 1.18), 2) < 2500, 25, 50) )=420, 425, CEILING( ROUND((J49*1.5) * IF(J49*1.5 <= 2500, 1.05, 1.18), 2), IF(ROUND((J49*1.5) * IF(J49*1.5 <= 2500, 1.05, 1.18), 2) < 2500, 25, 50) ) ), "" ) -> 1200 | N49: =IF(ISNUMBER(G49), CEILING(ROUND(L49*0.92,2),5), "") -> 950 | O49: =IF(ISNUMBER(L49), IF(CEILING(ROUND(L49*1.07,2),5)=420, 425, CEILING(ROUND(L49*1.07,2),5) ), "" ) -> 1105 | P49: =IF((((G49*1.5)+50)/0.835)<2500, MROUND(((((G49*1.5)+50)/0.835)*1.05)*2,10), MROUND(((((G49*1.5)+50)/0.835)*1.18)*2,10)) -> 1860 | Q49: =IF($S$3="","", MROUND( IF($S$3="m", IF($T$3=1, Price35[[#This Row],[Mrp]]+$W$4, Price35[[#This Row],[Mrp]]+$X$4), IF($S$3="nc", IF($T$3=1, Price35[[#This Row],[Net Cash]]+$W$5, Price35[[#This Row],[Net Cash]]+$X$5), IF($S$3="npc", IF($T$3=1, Price35[[#This Row],[Net Price Credit]]+$W$6, Price35[[#This Row],[Net Price Credit]]+$X$6), IF($S$3="w", IF($T$3=1, Price35[[#This Row],[Wsp]]+$W$6, Price35[[#This Row],[Wsp]]+$X$6), "")))), 10)) -> 1270
B50: 1021 | C50: shawl | D50: Kashmiri | F50: 3-0 sch | G50: 720 | I50: 300 | J50: =IF(SUMIF(G50:I50,"<>")=0,"",SUM(G50:I50)) -> 1020 | K50: =IF(ISNUMBER(L50), IF(CEILING(ROUND(L50*0.95,2),5)=420, 425, CEILING(ROUND(L50*0.95,2),5) ), "" ) -> 1315 | L50: =IF(ISNUMBER(J50), IF(CEILING(ROUND(J50*1.35,2),5)=420, 425, CEILING(ROUND(J50*1.35,2),5) ), "" ) -> 1380 | M50: =IF(AND(ISNUMBER(J50),ISNUMBER(G50)), IF( CEILING( ROUND((J50*1.5) * IF(J50*1.5 <= 2500, 1.05, 1.18), 2), IF(ROUND((J50*1.5) * IF(J50*1.5 <= 2500, 1.05, 1.18), 2) < 2500, 25, 50) )=420, 425, CEILING( ROUND((J50*1.5) * IF(J50*1.5 <= 2500, 1.05, 1.18), 2), IF(ROUND((J50*1.5) * IF(J50*1.5 <= 2500, 1.05, 1.18), 2) < 2500, 25, 50) ) ), "" ) -> 1625 | N50: =IF(ISNUMBER(G50), CEILING(ROUND(L50*0.92,2),5), "") -> 1270 | O50: =IF(ISNUMBER(L50), IF(CEILING(ROUND(L50*1.07,2),5)=420, 425, CEILING(ROUND(L50*1.07,2),5) ), "" ) -> 1480 | P50: =IF((((G50*1.5)+50)/0.835)<2500, MROUND(((((G50*1.5)+50)/0.835)*1.05)*2,10), MROUND(((((G50*1.5)+50)/0.835)*1.18)*2,10)) -> 2840 | Q50: =IF($S$3="","", MROUND( IF($S$3="m", IF($T$3=1, Price35[[#This Row],[Mrp]]+$W$4, Price35[[#This Row],[Mrp]]+$X$4), IF($S$3="nc", IF($T$3=1, Price35[[#This Row],[Net Cash]]+$W$5, Price35[[#This Row],[Net Cash]]+$X$5), IF($S$3="npc", IF($T$3=1, Price35[[#This Row],[Net Price Credit]]+$W$6, Price35[[#This Row],[Net Price Credit]]+$X$6), IF($S$3="w", IF($T$3=1, Price35[[#This Row],[Wsp]]+$W$6, Price35[[#This Row],[Wsp]]+$X$6), "")))), 10)) -> 1700
B51: 1030 | C51: shawl | D51: Kashmiri | F51: 2-4 shahtoosh | G51: 560 | I51: 130 | J51: =IF(SUMIF(G51:I51,"<>")=0,"",SUM(G51:I51)) -> 690 | K51: =IF(ISNUMBER(L51), IF(CEILING(ROUND(L51*0.95,2),5)=420, 425, CEILING(ROUND(L51*0.95,2),5) ), "" ) -> 890 | L51: =IF(ISNUMBER(J51), IF(CEILING(ROUND(J51*1.35,2),5)=420, 425, CEILING(ROUND(J51*1.35,2),5) ), "" ) -> 935 | M51: =IF(AND(ISNUMBER(J51),ISNUMBER(G51)), IF( CEILING( ROUND((J51*1.5) * IF(J51*1.5 <= 2500, 1.05, 1.18), 2), IF(ROUND((J51*1.5) * IF(J51*1.5 <= 2500, 1.05, 1.18), 2) < 2500, 25, 50) )=420, 425, CEILING( ROUND((J51*1.5) * IF(J51*1.5 <= 2500, 1.05, 1.18), 2), IF(ROUND((J51*1.5) * IF(J51*1.5 <= 2500, 1.05, 1.18), 2) < 2500, 25, 50) ) ), "" ) -> 1100 | N51: =IF(ISNUMBER(G51), CEILING(ROUND(L51*0.92,2),5), "") -> 865 | O51: =IF(ISNUMBER(L51), IF(CEILING(ROUND(L51*1.07,2),5)=420, 425, CEILING(ROUND(L51*1.07,2),5) ), "" ) -> 1005 | P51: =IF((((G51*1.5)+50)/0.835)<2500, MROUND(((((G51*1.5)+50)/0.835)*1.05)*2,10), MROUND(((((G51*1.5)+50)/0.835)*1.18)*2,10)) -> 2240 | Q51: =IF($S$3="","", MROUND( IF($S$3="m", IF($T$3=1, Price35[[#This Row],[Mrp]]+$W$4, Price35[[#This Row],[Mrp]]+$X$4), IF($S$3="nc", IF($T$3=1, Price35[[#This Row],[Net Cash]]+$W$5, Price35[[#This Row],[Net Cash]]+$X$5), IF($S$3="npc", IF($T$3=1, Price35[[#This Row],[Net Price Credit]]+$W$6, Price35[[#This Row],[Net Price Credit]]+$X$6), IF($S$3="w", IF($T$3=1, Price35[[#This Row],[Wsp]]+$W$6, Price35[[#This Row],[Wsp]]+$X$6), "")))), 10)) -> 1170
A54: Yom | B54: Art no. | C54: Item | D54: Quality | E54: Supplier | F54: Description | G54: Cost | H54: Increase | I54: Expenses | J54: Total Cost | K54: Net Price Credit | L54: Wsp | M54: Mrp | N54: Net Cash | O54: South | P54: Amazon | Q54: With Box
A55: 2026 | B55: 105 | C55: shawl | D55: Fine Wool | E55: Rajesh | F55: kalamkari | G55: 12500 | I55: 50 | J55: =IF(SUMIF(G55:I55,"<>")=0,"",SUM(G55:I55)) -> 12550 | K55: =IF(ISNUMBER(L55), IF(CEILING(ROUND(L55*0.95,2),5)=420, 425, CEILING(ROUND(L55*0.95,2),5) ), "" ) -> 15500 | L55: =IF(AND(ISNUMBER(J55),ISNUMBER(G55)), IF(CEILING(ROUND(J55*1.3,2),5)=420, 425, CEILING(ROUND(J55*1.3,2),5) ), "" ) -> 16315 | M55: =IF(AND(ISNUMBER(J55),ISNUMBER(G55)), IF( CEILING( ROUND((J55*1.5) * IF(J55*1.5 <= 2500, 1.05, 1.18), 2), IF(ROUND((J55*1.5) * IF(J55*1.5 <= 2500, 1.05, 1.18), 2) < 2500, 25, 50) )=420, 425, CEILING( ROUND((J55*1.5) * IF(J55*1.5 <= 2500, 1.05, 1.18), 2), IF(ROUND((J55*1.5) * IF(J55*1.5 <= 2500, 1.05, 1.18), 2) < 2500, 25, 50) ) ), "" ) -> 22250 | N55: =IF(ISNUMBER(G55), IF(CEILING(ROUND(L55*0.92,2),5)=420, 425, CEILING(ROUND(L55*0.92,2),5) ), "" ) -> 15010 | O55: =IF(ISNUMBER(L55), IF(CEILING(ROUND(L55*1.07,2),5)=420, 425, CEILING(ROUND(L55*1.07,2),5) ), "" ) -> 17460 | P55: =IF((((Price30[Cost]*1.5)+50)/0.835)<2500, MROUND((((( Price30[Cost]*1.5)+50)/0.835)*1.05)*2,10), MROUND((((( Price30[Cost]*1.5)+50)/0.835)*1.18)*2,10)) -> 53140 | Q55: =IF($S$3="","", MROUND( IF($S$3="m", IF($T$3=1, Price30[[#This Row],[Mrp]]+$W$4, Price30[[#This Row],[Mrp]]+$X$4), IF($S$3="nc", IF($T$3=1, Price30[[#This Row],[Net Cash]]+$W$5, Price30[[#This Row],[Net Cash]]+$X$5), IF($S$3="npc", IF($T$3=1, Price30[[#This Row],[Net Price Credit]]+$W$6, Price30[[#This Row],[Net Price Credit]]+$X$6), IF($S$3="w", IF($T$3=1, Price30[[#This Row],[Wsp]]+$W$6, Price30[[#This Row],[Wsp]]+$X$6), "")))), 10)) -> 22320
A56: 2025 | B56: 106 | C56: shawl | D56: Fine Wool | E56: Rajesh | F56: kalamkari | G56: 8500 | H56: 15 | I56: 25 | J56: =IF(SUMIF(G56:I56,"<>")=0,"",SUM(G56:I56)) -> 8540 | K56: =IF(ISNUMBER(L56), IF(CEILING(ROUND(L56*0.95,2),5)=420, 425, CEILING(ROUND(L56*0.95,2),5) ), "" ) -> 10550 | L56: =IF(AND(ISNUMBER(J56),ISNUMBER(G56)), IF(CEILING(ROUND(J56*1.3,2),5)=420, 425, CEILING(ROUND(J56*1.3,2),5) ), "" ) -> 11105 | M56: =IF(AND(ISNUMBER(J56),ISNUMBER(G56)), IF( CEILING( ROUND((J56*1.5) * IF(J56*1.5 <= 2500, 1.05, 1.18), 2), IF(ROUND((J56*1.5) * IF(J56*1.5 <= 2500, 1.05, 1.18), 2) < 2500, 25, 50) )=420, 425, CEILING( ROUND((J56*1.5) * IF(J56*1.5 <= 2500, 1.05, 1.18), 2), IF(ROUND((J56*1.5) * IF(J56*1.5 <= 2500, 1.05, 1.18), 2) < 2500, 25, 50) ) ), "" ) -> 15150 | N56: =IF(ISNUMBER(G56), IF(CEILING(ROUND(L56*0.92,2),5)=420, 425, CEILING(ROUND(L56*0.92,2),5) ), "" ) -> 10220 | O56: =IF(ISNUMBER(L56), IF(CEILING(ROUND(L56*1.07,2),5)=420, 425, CEILING(ROUND(L56*1.07,2),5) ), "" ) -> 11885 | P56: =IF((((Price30[Cost]*1.5)+50)/0.835)<2500, MROUND((((( Price30[Cost]*1.5)+50)/0.835)*1.05)*2,10), MROUND((((( Price30[Cost]*1.5)+50)/0.835)*1.18)*2,10)) -> 36180 | Q56: =IF($S$3="","", MROUND( IF($S$3="m", IF($T$3=1, Price30[[#This Row],[Mrp]]+$W$4, Price30[[#This Row],[Mrp]]+$X$4), IF($S$3="nc", IF($T$3=1, Price30[[#This Row],[Net Cash]]+$W$5, Price30[[#This Row],[Net Cash]]+$X$5), IF($S$3="npc", IF($T$3=1, Price30[[#This Row],[Net Price Credit]]+$W$6, Price30[[#This Row],[Net Price Credit]]+$X$6), IF($S$3="w", IF($T$3=1, Price30[[#This Row],[Wsp]]+$W$6, Price30[[#This Row],[Wsp]]+$X$6), "")))), 10)) -> 15220
B57: 107 | C57: Shawl | D57: Fine Wool | E57: Subhash | F57: multihead sangeen dour subhash | G57: 2700 | I57: 15 | J57: =IF(SUMIF(G57:I57,"<>")=0,"",SUM(G57:I57)) -> 2715 | K57: =IF(ISNUMBER(L57), IF(CEILING(ROUND(L57*0.95,2),5)=420, 425, CEILING(ROUND(L57*0.95,2),5) ), "" ) -> 3355 | L57: =IF(AND(ISNUMBER(J57),ISNUMBER(G57)), IF(CEILING(ROUND(J57*1.3,2),5)=420, 425, CEILING(ROUND(J57*1.3,2),5) ), "" ) -> 3530 | M57: =IF(AND(ISNUMBER(J57),ISNUMBER(G57)), IF( CEILING( ROUND((J57*1.5) * IF(J57*1.5 <= 2500, 1.05, 1.18), 2), IF(ROUND((J57*1.5) * IF(J57*1.5 <= 2500, 1.05, 1.18), 2) < 2500, 25, 50) )=420, 425, CEILING( ROUND((J57*1.5) * IF(J57*1.5 <= 2500, 1.05, 1.18), 2), IF(ROUND((J57*1.5) * IF(J57*1.5 <= 2500, 1.05, 1.18), 2) < 2500, 25, 50) ) ), "" ) -> 4850 | N57: =IF(ISNUMBER(G57), IF(CEILING(ROUND(L57*0.92,2),5)=420, 425, CEILING(ROUND(L57*0.92,2),5) ), "" ) -> 3250 | O57: =IF(ISNUMBER(L57), IF(CEILING(ROUND(L57*1.07,2),5)=420, 425, CEILING(ROUND(L57*1.07,2),5) ), "" ) -> 3780 | P57: =IF((((Price30[Cost]*1.5)+50)/0.835)<2500, MROUND((((( Price30[Cost]*1.5)+50)/0.835)*1.05)*2,10), MROUND((((( Price30[Cost]*1.5)+50)/0.835)*1.18)*2,10)) -> 11590 | Q57: =IF($S$3="","", MROUND( IF($S$3="m", IF($T$3=1, Price30[[#This Row],[Mrp]]+$W$4, Price30[[#This Row],[Mrp]]+$X$4), IF($S$3="nc", IF($T$3=1, Price30[[#This Row],[Net Cash]]+$W$5, Price30[[#This Row],[Net Cash]]+$X$5), IF($S$3="npc", IF($T$3=1, Price30[[#This Row],[Net Price Credit]]+$W$6, Price30[[#This Row],[Net Price Credit]]+$X$6), IF($S$3="w", IF($T$3=1, Price30[[#This Row],[Wsp]]+$W$6, Price30[[#This Row],[Wsp]]+$X$6), "")))), 10)) -> 4920
A58: 2026 | B58: 108 | C58: Shawl | D58: Fine Wool | E58: Subhash | F58: gents hashia multihead subhash 2350 | G58: 3700 | I58: 25 | J58: =IF(SUMIF(G58:I58,"<>")=0,"",SUM(G58:I58)) -> 3725 | K58: =IF(ISNUMBER(L58), IF(CEILING(ROUND(L58*0.95,2),5)=420, 425, CEILING(ROUND(L58*0.95,2),5) ), "" ) -> 4605 | L58: =IF(AND(ISNUMBER(J58),ISNUMBER(G58)), IF(CEILING(ROUND(J58*1.3,2),5)=420, 425, CEILING(ROUND(J58*1.3,2),5) ), "" ) -> 4845 | M58: =IF(AND(ISNUMBER(J58),ISNUMBER(G58)), IF( CEILING( ROUND((J58*1.5) * IF(J58*1.5 <= 2500, 1.05, 1.18), 2), IF(ROUND((J58*1.5) * IF(J58*1.5 <= 2500, 1.05, 1.18), 2) < 2500, 25, 50) )=420, 425, CEILING( ROUND((J58*1.5) * IF(J58*1.5 <= 2500, 1.05, 1.18), 2), IF(ROUND((J58*1.5) * IF(J58*1.5 <= 2500, 1.05, 1.18), 2) < 2500, 25, 50) ) ), "" ) -> 6600 | N58: =IF(ISNUMBER(G58), IF(CEILING(ROUND(L58*0.92,2),5)=420, 425, CEILING(ROUND(L58*0.92,2),5) ), "" ) -> 4460 | O58: =IF(ISNUMBER(L58), IF(CEILING(ROUND(L58*1.07,2),5)=420, 425, CEILING(ROUND(L58*1.07,2),5) ), "" ) -> 5185 | P58: =IF((((Price30[Cost]*1.5)+50)/0.835)<2500, MROUND((((( Price30[Cost]*1.5)+50)/0.835)*1.05)*2,10), MROUND((((( Price30[Cost]*1.5)+50)/0.835)*1.18)*2,10)) -> 15830 | Q58: =IF($S$3="","", MROUND( IF($S$3="m", IF($T$3=1, Price30[[#This Row],[Mrp]]+$W$4, Price30[[#This Row],[Mrp]]+$X$4), IF($S$3="nc", IF($T$3=1, Price30[[#This Row],[Net Cash]]+$W$5, Price30[[#This Row],[Net Cash]]+$X$5), IF($S$3="npc", IF($T$3=1, Price30[[#This Row],[Net Price Credit]]+$W$6, Price30[[#This Row],[Net Price Credit]]+$X$6), IF($S$3="w", IF($T$3=1, Price30[[#This Row],[Wsp]]+$W$6, Price30[[#This Row],[Wsp]]+$X$6), "")))), 10)) -> 6670
A59: 2026 | B59: 109 | C59: shawl | D59: Fine Wool | E59: ashwani | F59: kalamkari box figure + kalamkari heavy ashwani | G59: 8500 | I59: 50 | J59: =IF(SUMIF(G59:I59,"<>")=0,"",SUM(G59:I59)) -> 8550 | K59: =IF(ISNUMBER(L59), IF(CEILING(ROUND(L59*0.95,2),5)=420, 425, CEILING(ROUND(L59*0.95,2),5) ), "" ) -> 10560 | L59: =IF(AND(ISNUMBER(J59),ISNUMBER(G59)), IF(CEILING(ROUND(J59*1.3,2),5)=420, 425, CEILING(ROUND(J59*1.3,2),5) ), "" ) -> 11115 | M59: =IF(AND(ISNUMBER(J59),ISNUMBER(G59)), IF( CEILING( ROUND((J59*1.5) * IF(J59*1.5 <= 2500, 1.05, 1.18), 2), IF(ROUND((J59*1.5) * IF(J59*1.5 <= 2500, 1.05, 1.18), 2) < 2500, 25, 50) )=420, 425, CEILING( ROUND((J59*1.5) * IF(J59*1.5 <= 2500, 1.05, 1.18), 2), IF(ROUND((J59*1.5) * IF(J59*1.5 <= 2500, 1.05, 1.18), 2) < 2500, 25, 50) ) ), "" ) -> 15150 | N59: =IF(ISNUMBER(G59), IF(CEILING(ROUND(L59*0.92,2),5)=420, 425, CEILING(ROUND(L59*0.92,2),5) ), "" ) -> 10230 | O59: =IF(ISNUMBER(L59), IF(CEILING(ROUND(L59*1.07,2),5)=420, 425, CEILING(ROUND(L59*1.07,2),5) ), "" ) -> 11895 | P59: =IF((((Price30[Cost]*1.5)+50)/0.835)<2500, MROUND((((( Price30[Cost]*1.5)+50)/0.835)*1.05)*2,10), MROUND((((( Price30[Cost]*1.5)+50)/0.835)*1.18)*2,10)) -> 36180 | Q59: =IF($S$3="","", MROUND( IF($S$3="m", IF($T$3=1, Price30[[#This Row],[Mrp]]+$W$4, Price30[[#This Row],[Mrp]]+$X$4), IF($S$3="nc", IF($T$3=1, Price30[[#This Row],[Net Cash]]+$W$5, Price30[[#This Row],[Net Cash]]+$X$5), IF($S$3="npc", IF($T$3=1, Price30[[#This Row],[Net Price Credit]]+$W$6, Price30[[#This Row],[Net Price Credit]]+$X$6), IF($S$3="w", IF($T$3=1, Price30[[#This Row],[Wsp]]+$W$6, Price30[[#This Row],[Wsp]]+$X$6), "")))), 10)) -> 15220
B60: 110 | C60: Shawl | D60: Fine Wool | E60: Gaurav | F60: jamma 24097 & 24099 gw | G60: 3800 | I60: 15 | J60: =IF(SUMIF(G60:I60,"<>")=0,"",SUM(G60:I60)) -> 3815 | K60: =IF(ISNUMBER(L60), IF(CEILING(ROUND(L60*0.95,2),5)=420, 425, CEILING(ROUND(L60*0.95,2),5) ), "" ) -> 4715 | L60: =IF(AND(ISNUMBER(J60),ISNUMBER(G60)), IF(CEILING(ROUND(J60*1.3,2),5)=420, 425, CEILING(ROUND(J60*1.3,2),5) ), "" ) -> 4960 | M60: =IF(AND(ISNUMBER(J60),ISNUMBER(G60)), IF( CEILING( ROUND((J60*1.5) * IF(J60*1.5 <= 2500, 1.05, 1.18), 2), IF(ROUND((J60*1.5) * IF(J60*1.5 <= 2500, 1.05, 1.18), 2) < 2500, 25, 50) )=420, 425, CEILING( ROUND((J60*1.5) * IF(J60*1.5 <= 2500, 1.05, 1.18), 2), IF(ROUND((J60*1.5) * IF(J60*1.5 <= 2500, 1.05, 1.18), 2) < 2500, 25, 50) ) ), "" ) -> 6800 | N60: =IF(ISNUMBER(G60), IF(CEILING(ROUND(L60*0.92,2),5)=420, 425, CEILING(ROUND(L60*0.92,2),5) ), "" ) -> 4565 | O60: =IF(ISNUMBER(L60), IF(CEILING(ROUND(L60*1.07,2),5)=420, 425, CEILING(ROUND(L60*1.07,2),5) ), "" ) -> 5310 | P60: =IF((((Price30[Cost]*1.5)+50)/0.835)<2500, MROUND((((( Price30[Cost]*1.5)+50)/0.835)*1.05)*2,10), MROUND((((( Price30[Cost]*1.5)+50)/0.835)*1.18)*2,10)) -> 16250 | Q60: =IF($S$3="","", MROUND( IF($S$3="m", IF($T$3=1, Price30[[#This Row],[Mrp]]+$W$4, Price30[[#This Row],[Mrp]]+$X$4), IF($S$3="nc", IF($T$3=1, Price30[[#This Row],[Net Cash]]+$W$5, Price30[[#This Row],[Net Cash]]+$X$5), IF($S$3="npc", IF($T$3=1, Price30[[#This Row],[Net Price Credit]]+$W$6, Price30[[#This Row],[Net Price Credit]]+$X$6), IF($S$3="w", IF($T$3=1, Price30[[#This Row],[Wsp]]+$W$6, Price30[[#This Row],[Wsp]]+$X$6), "")))), 10)) -> 6870
A61: 2025 | B61: 112 | C61: shawl | D61: Fine Wool | E61: Rajesh | F61: kalamkari palla | G61: 4500 | H61: 25 | I61: 15 | J61: =IF(SUMIF(G61:I61,"<>")=0,"",SUM(G61:I61)) -> 4540 | K61: =IF(ISNUMBER(L61), IF(CEILING(ROUND(L61*0.95,2),5)=420, 425, CEILING(ROUND(L61*0.95,2),5) ), "" ) -> 5610 | L61: =IF(AND(ISNUMBER(J61),ISNUMBER(G61)), IF(CEILING(ROUND(J61*1.3,2),5)=420, 425, CEILING(ROUND(J61*1.3,2),5) ), "" ) -> 5905 | M61: =IF(AND(ISNUMBER(J61),ISNUMBER(G61)), IF( CEILING( ROUND((J61*1.5) * IF(J61*1.5 <= 2500, 1.05, 1.18), 2), IF(ROUND((J61*1.5) * IF(J61*1.5 <= 2500, 1.05, 1.18), 2) < 2500, 25, 50) )=420, 425, CEILING( ROUND((J61*1.5) * IF(J61*1.5 <= 2500, 1.05, 1.18), 2), IF(ROUND((J61*1.5) * IF(J61*1.5 <= 2500, 1.05, 1.18), 2) < 2500, 25, 50) ) ), "" ) -> 8050 | N61: =IF(ISNUMBER(G61), IF(CEILING(ROUND(L61*0.92,2),5)=420, 425, CEILING(ROUND(L61*0.92,2),5) ), "" ) -> 5435 | O61: =IF(ISNUMBER(L61), IF(CEILING(ROUND(L61*1.07,2),5)=420, 425, CEILING(ROUND(L61*1.07,2),5) ), "" ) -> 6320 | P61: =IF((((Price30[Cost]*1.5)+50)/0.835)<2500, MROUND((((( Price30[Cost]*1.5)+50)/0.835)*1.05)*2,10), MROUND((((( Price30[Cost]*1.5)+50)/0.835)*1.18)*2,10)) -> 19220 | Q61: =IF($S$3="","", MROUND( IF($S$3="m", IF($T$3=1, Price30[[#This Row],[Mrp]]+$W$4, Price30[[#This Row],[Mrp]]+$X$4), IF($S$3="nc", IF($T$3=1, Price30[[#This Row],[Net Cash]]+$W$5, Price30[[#This Row],[Net Cash]]+$X$5), IF($S$3="npc", IF($T$3=1, Price30[[#This Row],[Net Price Credit]]+$W$6, Price30[[#This Row],[Net Price Credit]]+$X$6), IF($S$3="w", IF($T$3=1, Price30[[#This Row],[Wsp]]+$W$6, Price30[[#This Row],[Wsp]]+$X$6), "")))), 10)) -> 8120
A62: 2026 | B62: 113 | C62: Shawl | D62: Fine Wool | E62: Subhash | F62: jamma | G62: 5300 | I62: 15 | J62: =IF(SUMIF(G62:I62,"<>")=0,"",SUM(G62:I62)) -> 5315 | K62: =IF(ISNUMBER(L62), IF(CEILING(ROUND(L62*0.95,2),5)=420, 425, CEILING(ROUND(L62*0.95,2),5) ), "" ) -> 6565 | L62: =IF(AND(ISNUMBER(J62),ISNUMBER(G62)), IF(CEILING(ROUND(J62*1.3,2),5)=420, 425, CEILING(ROUND(J62*1.3,2),5) ), "" ) -> 6910 | M62: =IF(AND(ISNUMBER(J62),ISNUMBER(G62)), IF( CEILING( ROUND((J62*1.5) * IF(J62*1.5 <= 2500, 1.05, 1.18), 2), IF(ROUND((J62*1.5) * IF(J62*1.5 <= 2500, 1.05, 1.18), 2) < 2500, 25, 50) )=420, 425, CEILING( ROUND((J62*1.5) * IF(J62*1.5 <= 2500, 1.05, 1.18), 2), IF(ROUND((J62*1.5) * IF(J62*1.5 <= 2500, 1.05, 1.18), 2) < 2500, 25, 50) ) ), "" ) -> 9450 | N62: =IF(ISNUMBER(G62), IF(CEILING(ROUND(L62*0.92,2),5)=420, 425, CEILING(ROUND(L62*0.92,2),5) ), "" ) -> 6360 | O62: =IF(ISNUMBER(L62), IF(CEILING(ROUND(L62*1.07,2),5)=420, 425, CEILING(ROUND(L62*1.07,2),5) ), "" ) -> 7395 | P62: =IF((((Price30[Cost]*1.5)+50)/0.835)<2500, MROUND((((( Price30[Cost]*1.5)+50)/0.835)*1.05)*2,10), MROUND((((( Price30[Cost]*1.5)+50)/0.835)*1.18)*2,10)) -> 22610 | Q62: =IF($S$3="","", MROUND( IF($S$3="m", IF($T$3=1, Price30[[#This Row],[Mrp]]+$W$4, Price30[[#This Row],[Mrp]]+$X$4), IF($S$3="nc", IF($T$3=1, Price30[[#This Row],[Net Cash]]+$W$5, Price30[[#This Row],[Net Cash]]+$X$5), IF($S$3="npc", IF($T$3=1, Price30[[#This Row],[Net Price Credit]]+$W$6, Price30[[#This Row],[Net Price Credit]]+$X$6), IF($S$3="w", IF($T$3=1, Price30[[#This Row],[Wsp]]+$W$6, Price30[[#This Row],[Wsp]]+$X$6), "")))), 10)) -> 9520
A63: 2025 | B63: 115 | C63: shawl | D63: Fine Wool | E63: Rajesh | F63: top dour multi head | G63: 1350 | H63: 10 | I63: 25 | J63: =IF(SUMIF(G63:I63,"<>")=0,"",SUM(G63:I63)) -> 1385 | K63: =IF(ISNUMBER(L63), IF(CEILING(ROUND(L63*0.95,2),5)=420, 425, CEILING(ROUND(L63*0.95,2),5) ), "" ) -> 1715 | L63: =IF(AND(ISNUMBER(J63),ISNUMBER(G63)), IF(CEILING(ROUND(J63*1.3,2),5)=420, 425, CEILING(ROUND(J63*1.3,2),5) ), "" ) -> 1805 | M63: =IF(AND(ISNUMBER(J63),ISNUMBER(G63)), IF( CEILING( ROUND((J63*1.5) * IF(J63*1.5 <= 2500, 1.05, 1.18), 2), IF(ROUND((J63*1.5) * IF(J63*1.5 <= 2500, 1.05, 1.18), 2) < 2500, 25, 50) )=420, 425, CEILING( ROUND((J63*1.5) * IF(J63*1.5 <= 2500, 1.05, 1.18), 2), IF(ROUND((J63*1.5) * IF(J63*1.5 <= 2500, 1.05, 1.18), 2) < 2500, 25, 50) ) ), "" ) -> 2200 | N63: =IF(ISNUMBER(G63), IF(CEILING(ROUND(L63*0.92,2),5)=420, 425, CEILING(ROUND(L63*0.92,2),5) ), "" ) -> 1665 | O63: =IF(ISNUMBER(L63), IF(CEILING(ROUND(L63*1.07,2),5)=420, 425, CEILING(ROUND(L63*1.07,2),5) ), "" ) -> 1935 | P63: =IF((((Price30[Cost]*1.5)+50)/0.835)<2500, MROUND((((( Price30[Cost]*1.5)+50)/0.835)*1.05)*2,10), MROUND((((( Price30[Cost]*1.5)+50)/0.835)*1.18)*2,10)) -> 5220 | Q63: =IF($S$3="","", MROUND( IF($S$3="m", IF($T$3=1, Price30[[#This Row],[Mrp]]+$W$4, Price30[[#This Row],[Mrp]]+$X$4), IF($S$3="nc", IF($T$3=1, Price30[[#This Row],[Net Cash]]+$W$5, Price30[[#This Row],[Net Cash]]+$X$5), IF($S$3="npc", IF($T$3=1, Price30[[#This Row],[Net Price Credit]]+$W$6, Price30[[#This Row],[Net Price Credit]]+$X$6), IF($S$3="w", IF($T$3=1, Price30[[#This Row],[Wsp]]+$W$6, Price30[[#This Row],[Wsp]]+$X$6), "")))), 10)) -> 2270
B64: 116 | C64: Shawl | D64: Fine Wool | E64: Gaurav | F64: jamma 24101 & 22000 gw | G64: 4200 | I64: 15 | J64: =IF(SUMIF(G64:I64,"<>")=0,"",SUM(G64:I64)) -> 4215 | K64: =IF(ISNUMBER(L64), IF(CEILING(ROUND(L64*0.95,2),5)=420, 425, CEILING(ROUND(L64*0.95,2),5) ), "" ) -> 5210 | L64: =IF(AND(ISNUMBER(J64),ISNUMBER(G64)), IF(CEILING(ROUND(J64*1.3,2),5)=420, 425, CEILING(ROUND(J64*1.3,2),5) ), "" ) -> 5480 | M64: =IF(AND(ISNUMBER(J64),ISNUMBER(G64)), IF( CEILING( ROUND((J64*1.5) * IF(J64*1.5 <= 2500, 1.05, 1.18), 2), IF(ROUND((J64*1.5) * IF(J64*1.5 <= 2500, 1.05, 1.18), 2) < 2500, 25, 50) )=420, 425, CEILING( ROUND((J64*1.5) * IF(J64*1.5 <= 2500, 1.05, 1.18), 2), IF(ROUND((J64*1.5) * IF(J64*1.5 <= 2500, 1.05, 1.18), 2) < 2500, 25, 50) ) ), "" ) -> 7500 | N64: =IF(ISNUMBER(G64), IF(CEILING(ROUND(L64*0.92,2),5)=420, 425, CEILING(ROUND(L64*0.92,2),5) ), "" ) -> 5045 | O64: =IF(ISNUMBER(L64), IF(CEILING(ROUND(L64*1.07,2),5)=420, 425, CEILING(ROUND(L64*1.07,2),5) ), "" ) -> 5865 | P64: =IF((((Price30[Cost]*1.5)+50)/0.835)<2500, MROUND((((( Price30[Cost]*1.5)+50)/0.835)*1.05)*2,10), MROUND((((( Price30[Cost]*1.5)+50)/0.835)*1.18)*2,10)) -> 17950 | Q64: =IF($S$3="","", MROUND( IF($S$3="m", IF($T$3=1, Price30[[#This Row],[Mrp]]+$W$4, Price30[[#This Row],[Mrp]]+$X$4), IF($S$3="nc", IF($T$3=1, Price30[[#This Row],[Net Cash]]+$W$5, Price30[[#This Row],[Net Cash]]+$X$5), IF($S$3="npc", IF($T$3=1, Price30[[#This Row],[Net Price Credit]]+$W$6, Price30[[#This Row],[Net Price Credit]]+$X$6), IF($S$3="w", IF($T$3=1, Price30[[#This Row],[Wsp]]+$W$6, Price30[[#This Row],[Wsp]]+$X$6), "")))), 10)) -> 7570
A65: 2025 | B65: 117 | C65: shawl | D65: Fine Wool | E65: ramesh khanna | F65: buti jamma | G65: 2250 | I65: 25 | J65: =IF(SUMIF(G65:I65,"<>")=0,"",SUM(G65:I65)) -> 2275 | K65: =IF(ISNUMBER(L65), IF(CEILING(ROUND(L65*0.95,2),5)=420, 425, CEILING(ROUND(L65*0.95,2),5) ), "" ) -> 2815 | L65: =IF(AND(ISNUMBER(J65),ISNUMBER(G65)), IF(CEILING(ROUND(J65*1.3,2),5)=420, 425, CEILING(ROUND(J65*1.3,2),5) ), "" ) -> 2960 | M65: =IF(AND(ISNUMBER(J65),ISNUMBER(G65)), IF( CEILING( ROUND((J65*1.5) * IF(J65*1.5 <= 2500, 1.05, 1.18), 2), IF(ROUND((J65*1.5) * IF(J65*1.5 <= 2500, 1.05, 1.18), 2) < 2500, 25, 50) )=420, 425, CEILING( ROUND((J65*1.5) * IF(J65*1.5 <= 2500, 1.05, 1.18), 2), IF(ROUND((J65*1.5) * IF(J65*1.5 <= 2500, 1.05, 1.18), 2) < 2500, 25, 50) ) ), "" ) -> 4050 | N65: =IF(ISNUMBER(G65), IF(CEILING(ROUND(L65*0.92,2),5)=420, 425, CEILING(ROUND(L65*0.92,2),5) ), "" ) -> 2725 | O65: =IF(ISNUMBER(L65), IF(CEILING(ROUND(L65*1.07,2),5)=420, 425, CEILING(ROUND(L65*1.07,2),5) ), "" ) -> 3170 | P65: =IF((((Price30[Cost]*1.5)+50)/0.835)<2500, MROUND((((( Price30[Cost]*1.5)+50)/0.835)*1.05)*2,10), MROUND((((( Price30[Cost]*1.5)+50)/0.835)*1.18)*2,10)) -> 9680 | Q65: =IF($S$3="","", MROUND( IF($S$3="m", IF($T$3=1, Price30[[#This Row],[Mrp]]+$W$4, Price30[[#This Row],[Mrp]]+$X$4), IF($S$3="nc", IF($T$3=1, Price30[[#This Row],[Net Cash]]+$W$5, Price30[[#This Row],[Net Cash]]+$X$5), IF($S$3="npc", IF($T$3=1, Price30[[#This Row],[Net Price Credit]]+$W$6, Price30[[#This Row],[Net Price Credit]]+$X$6), IF($S$3="w", IF($T$3=1, Price30[[#This Row],[Wsp]]+$W$6, Price30[[#This Row],[Wsp]]+$X$6), "")))), 10)) -> 4120
A66: 2025 | B66: 118 | C66: shawl | D66: Fine Wool | E66: ramesh khanna | F66: jal jamma kani | G66: 2750 | I66: 25 | J66: =IF(SUMIF(G66:I66,"<>")=0,"",SUM(G66:I66)) -> 2775 | K66: =IF(ISNUMBER(L66), IF(CEILING(ROUND(L66*0.95,2),5)=420, 425, CEILING(ROUND(L66*0.95,2),5) ), "" ) -> 3430 | L66: =IF(AND(ISNUMBER(J66),ISNUMBER(G66)), IF(CEILING(ROUND(J66*1.3,2),5)=420, 425, CEILING(ROUND(J66*1.3,2),5) ), "" ) -> 3610 | M66: =IF(AND(ISNUMBER(J66),ISNUMBER(G66)), IF( CEILING( ROUND((J66*1.5) * IF(J66*1.5 <= 2500, 1.05, 1.18), 2), IF(ROUND((J66*1.5) * IF(J66*1.5 <= 2500, 1.05, 1.18), 2) < 2500, 25, 50) )=420, 425, CEILING( ROUND((J66*1.5) * IF(J66*1.5 <= 2500, 1.05, 1.18), 2), IF(ROUND((J66*1.5) * IF(J66*1.5 <= 2500, 1.05, 1.18), 2) < 2500, 25, 50) ) ), "" ) -> 4950 | N66: =IF(ISNUMBER(G66), IF(CEILING(ROUND(L66*0.92,2),5)=420, 425, CEILING(ROUND(L66*0.92,2),5) ), "" ) -> 3325 | O66: =IF(ISNUMBER(L66), IF(CEILING(ROUND(L66*1.07,2),5)=420, 425, CEILING(ROUND(L66*1.07,2),5) ), "" ) -> 3865 | P66: =IF((((Price30[Cost]*1.5)+50)/0.835)<2500, MROUND((((( Price30[Cost]*1.5)+50)/0.835)*1.05)*2,10), MROUND((((( Price30[Cost]*1.5)+50)/0.835)*1.18)*2,10)) -> 11800 | Q66: =IF($S$3="","", MROUND( IF($S$3="m", IF($T$3=1, Price30[[#This Row],[Mrp]]+$W$4, Price30[[#This Row],[Mrp]]+$X$4), IF($S$3="nc", IF($T$3=1, Price30[[#This Row],[Net Cash]]+$W$5, Price30[[#This Row],[Net Cash]]+$X$5), IF($S$3="npc", IF($T$3=1, Price30[[#This Row],[Net Price Credit]]+$W$6, Price30[[#This Row],[Net Price Credit]]+$X$6), IF($S$3="w", IF($T$3=1, Price30[[#This Row],[Wsp]]+$W$6, Price30[[#This Row],[Wsp]]+$X$6), "")))), 10)) -> 5020
A67: 2026 | B67: 119 | C67: Shawl | D67: Fine Wool | E67: rajesh | F67: gents shahtoosh 50*100 polywool | G67: 1275 | I67: 15 | J67: =IF(SUMIF(G67:I67,"<>")=0,"",SUM(G67:I67)) -> 1290 | K67: =IF(ISNUMBER(L67), IF(CEILING(ROUND(L67*0.95,2),5)=420, 425, CEILING(ROUND(L67*0.95,2),5) ), "" ) -> 1600 | L67: =IF(AND(ISNUMBER(J67),ISNUMBER(G67)), IF(CEILING(ROUND(J67*1.3,2),5)=420, 425, CEILING(ROUND(J67*1.3,2),5) ), "" ) -> 1680 | M67: =IF(AND(ISNUMBER(J67),ISNUMBER(G67)), IF( CEILING( ROUND((J67*1.5) * IF(J67*1.5 <= 2500, 1.05, 1.18), 2), IF(ROUND((J67*1.5) * IF(J67*1.5 <= 2500, 1.05, 1.18), 2) < 2500, 25, 50) )=420, 425, CEILING( ROUND((J67*1.5) * IF(J67*1.5 <= 2500, 1.05, 1.18), 2), IF(ROUND((J67*1.5) * IF(J67*1.5 <= 2500, 1.05, 1.18), 2) < 2500, 25, 50) ) ), "" ) -> 2050 | N67: =IF(ISNUMBER(G67), IF(CEILING(ROUND(L67*0.92,2),5)=420, 425, CEILING(ROUND(L67*0.92,2),5) ), "" ) -> 1550 | O67: =IF(ISNUMBER(L67), IF(CEILING(ROUND(L67*1.07,2),5)=420, 425, CEILING(ROUND(L67*1.07,2),5) ), "" ) -> 1800 | P67: =IF((((Price30[Cost]*1.5)+50)/0.835)<2500, MROUND((((( Price30[Cost]*1.5)+50)/0.835)*1.05)*2,10), MROUND((((( Price30[Cost]*1.5)+50)/0.835)*1.18)*2,10)) -> 4940 | Q67: =IF($S$3="","", MROUND( IF($S$3="m", IF($T$3=1, Price30[[#This Row],[Mrp]]+$W$4, Price30[[#This Row],[Mrp]]+$X$4), IF($S$3="nc", IF($T$3=1, Price30[[#This Row],[Net Cash]]+$W$5, Price30[[#This Row],[Net Cash]]+$X$5), IF($S$3="npc", IF($T$3=1, Price30[[#This Row],[Net Price Credit]]+$W$6, Price30[[#This Row],[Net Price Credit]]+$X$6), IF($S$3="w", IF($T$3=1, Price30[[#This Row],[Wsp]]+$W$6, Price30[[#This Row],[Wsp]]+$X$6), "")))), 10)) -> 2120
B68: 121 | C68: Lohi | D68: Fine Wool | E68: Gaurav | F68: gents KANI GW jal pure | G68: 3350 | I68: 15 | J68: =IF(SUMIF(G68:I68,"<>")=0,"",SUM(G68:I68)) -> 3365 | K68: =IF(ISNUMBER(L68), IF(CEILING(ROUND(L68*0.95,2),5)=420, 425, CEILING(ROUND(L68*0.95,2),5) ), "" ) -> 4160 | L68: =IF(AND(ISNUMBER(J68),ISNUMBER(G68)), IF(CEILING(ROUND(J68*1.3,2),5)=420, 425, CEILING(ROUND(J68*1.3,2),5) ), "" ) -> 4375 | M68: =IF(AND(ISNUMBER(J68),ISNUMBER(G68)), IF( CEILING( ROUND((J68*1.5) * IF(J68*1.5 <= 2500, 1.05, 1.18), 2), IF(ROUND((J68*1.5) * IF(J68*1.5 <= 2500, 1.05, 1.18), 2) < 2500, 25, 50) )=420, 425, CEILING( ROUND((J68*1.5) * IF(J68*1.5 <= 2500, 1.05, 1.18), 2), IF(ROUND((J68*1.5) * IF(J68*1.5 <= 2500, 1.05, 1.18), 2) < 2500, 25, 50) ) ), "" ) -> 6000 | N68: =IF(ISNUMBER(G68), IF(CEILING(ROUND(L68*0.92,2),5)=420, 425, CEILING(ROUND(L68*0.92,2),5) ), "" ) -> 4025 | O68: =IF(ISNUMBER(L68), IF(CEILING(ROUND(L68*1.07,2),5)=420, 425, CEILING(ROUND(L68*1.07,2),5) ), "" ) -> 4685 | P68: =IF((((Price30[Cost]*1.5)+50)/0.835)<2500, MROUND((((( Price30[Cost]*1.5)+50)/0.835)*1.05)*2,10), MROUND((((( Price30[Cost]*1.5)+50)/0.835)*1.18)*2,10)) -> 14340 | Q68: =IF($S$3="","", MROUND( IF($S$3="m", IF($T$3=1, Price30[[#This Row],[Mrp]]+$W$4, Price30[[#This Row],[Mrp]]+$X$4), IF($S$3="nc", IF($T$3=1, Price30[[#This Row],[Net Cash]]+$W$5, Price30[[#This Row],[Net Cash]]+$X$5), IF($S$3="npc", IF($T$3=1, Price30[[#This Row],[Net Price Credit]]+$W$6, Price30[[#This Row],[Net Price Credit]]+$X$6), IF($S$3="w", IF($T$3=1, Price30[[#This Row],[Wsp]]+$W$6, Price30[[#This Row],[Wsp]]+$X$6), "")))), 10)) -> 6070
A69: 2025 | B69: 1211 | C69: Lohi | D69: Fine Wool | E69: Gaurav | F69: gents kani jal polywool | G69: 1960 | I69: 15 | J69: =IF(SUMIF(G69:I69,"<>")=0,"",SUM(G69:I69)) -> 1975 | K69: =IF(ISNUMBER(L69), IF(CEILING(ROUND(L69*0.95,2),5)=420, 425, CEILING(ROUND(L69*0.95,2),5) ), "" ) -> 2445 | L69: =IF(AND(ISNUMBER(J69),ISNUMBER(G69)), IF(CEILING(ROUND(J69*1.3,2),5)=420, 425, CEILING(ROUND(J69*1.3,2),5) ), "" ) -> 2570 | M69: =IF(AND(ISNUMBER(J69),ISNUMBER(G69)), IF( CEILING( ROUND((J69*1.5) * IF(J69*1.5 <= 2500, 1.05, 1.18), 2), IF(ROUND((J69*1.5) * IF(J69*1.5 <= 2500, 1.05, 1.18), 2) < 2500, 25, 50) )=420, 425, CEILING( ROUND((J69*1.5) * IF(J69*1.5 <= 2500, 1.05, 1.18), 2), IF(ROUND((J69*1.5) * IF(J69*1.5 <= 2500, 1.05, 1.18), 2) < 2500, 25, 50) ) ), "" ) -> 3500 | N69: =IF(ISNUMBER(G69), IF(CEILING(ROUND(L69*0.92,2),5)=420, 425, CEILING(ROUND(L69*0.92,2),5) ), "" ) -> 2365 | O69: =IF(ISNUMBER(L69), IF(CEILING(ROUND(L69*1.07,2),5)=420, 425, CEILING(ROUND(L69*1.07,2),5) ), "" ) -> 2750 | P69: =IF((((Price30[Cost]*1.5)+50)/0.835)<2500, MROUND((((( Price30[Cost]*1.5)+50)/0.835)*1.05)*2,10), MROUND((((( Price30[Cost]*1.5)+50)/0.835)*1.18)*2,10)) -> 8450 | Q69: =IF($S$3="","", MROUND( IF($S$3="m", IF($T$3=1, Price30[[#This Row],[Mrp]]+$W$4, Price30[[#This Row],[Mrp]]+$X$4), IF($S$3="nc", IF($T$3=1, Price30[[#This Row],[Net Cash]]+$W$5, Price30[[#This Row],[Net Cash]]+$X$5), IF($S$3="npc", IF($T$3=1, Price30[[#This Row],[Net Price Credit]]+$W$6, Price30[[#This Row],[Net Price Credit]]+$X$6), IF($S$3="w", IF($T$3=1, Price30[[#This Row],[Wsp]]+$W$6, Price30[[#This Row],[Wsp]]+$X$6), "")))), 10)) -> 3570
A70: 2025 | B70: 1212 | C70: Lohi | D70: Fine Wool | E70: Gaurav | F70: gents kani palla polywool | G70: 1405 | I70: 15 | J70: =IF(SUMIF(G70:I70,"<>")=0,"",SUM(G70:I70)) -> 1420 | K70: =IF(ISNUMBER(L70), IF(CEILING(ROUND(L70*0.95,2),5)=420, 425, CEILING(ROUND(L70*0.95,2),5) ), "" ) -> 1760 | L70: =IF(AND(ISNUMBER(J70),ISNUMBER(G70)), IF(CEILING(ROUND(J70*1.3,2),5)=420, 425, CEILING(ROUND(J70*1.3,2),5) ), "" ) -> 1850 | M70: =IF(AND(ISNUMBER(J70),ISNUMBER(G70)), IF( CEILING( ROUND((J70*1.5) * IF(J70*1.5 <= 2500, 1.05, 1.18), 2), IF(ROUND((J70*1.5) * IF(J70*1.5 <= 2500, 1.05, 1.18), 2) < 2500, 25, 50) )=420, 425, CEILING( ROUND((J70*1.5) * IF(J70*1.5 <= 2500, 1.05, 1.18), 2), IF(ROUND((J70*1.5) * IF(J70*1.5 <= 2500, 1.05, 1.18), 2) < 2500, 25, 50) ) ), "" ) -> 2250 | N70: =IF(ISNUMBER(G70), IF(CEILING(ROUND(L70*0.92,2),5)=420, 425, CEILING(ROUND(L70*0.92,2),5) ), "" ) -> 1705 | O70: =IF(ISNUMBER(L70), IF(CEILING(ROUND(L70*1.07,2),5)=420, 425, CEILING(ROUND(L70*1.07,2),5) ), "" ) -> 1980 | P70: =IF((((Price30[Cost]*1.5)+50)/0.835)<2500, MROUND((((( Price30[Cost]*1.5)+50)/0.835)*1.05)*2,10), MROUND((((( Price30[Cost]*1.5)+50)/0.835)*1.18)*2,10)) -> 6100 | Q70: =IF($S$3="","", MROUND( IF($S$3="m", IF($T$3=1, Price30[[#This Row],[Mrp]]+$W$4, Price30[[#This Row],[Mrp]]+$X$4), IF($S$3="nc", IF($T$3=1, Price30[[#This Row],[Net Cash]]+$W$5, Price30[[#This Row],[Net Cash]]+$X$5), IF($S$3="npc", IF($T$3=1, Price30[[#This Row],[Net Price Credit]]+$W$6, Price30[[#This Row],[Net Price Credit]]+$X$6), IF($S$3="w", IF($T$3=1, Price30[[#This Row],[Wsp]]+$W$6, Price30[[#This Row],[Wsp]]+$X$6), "")))), 10)) -> 2320
A71: 2025 | B71: 1213 | C71: Lohi | D71: Fine Wool | E71: Gaurav | F71: gents kani dour polywool | G71: 1860 | I71: 15 | J71: =IF(SUMIF(G71:I71,"<>")=0,"",SUM(G71:I71)) -> 1875 | K71: =IF(ISNUMBER(L71), IF(CEILING(ROUND(L71*0.95,2),5)=420, 425, CEILING(ROUND(L71*0.95,2),5) ), "" ) -> 2320 | L71: =IF(AND(ISNUMBER(J71),ISNUMBER(G71)), IF(CEILING(ROUND(J71*1.3,2),5)=420, 425, CEILING(ROUND(J71*1.3,2),5) ), "" ) -> 2440 | M71: =IF(AND(ISNUMBER(J71),ISNUMBER(G71)), IF( CEILING( ROUND((J71*1.5) * IF(J71*1.5 <= 2500, 1.05, 1.18), 2), IF(ROUND((J71*1.5) * IF(J71*1.5 <= 2500, 1.05, 1.18), 2) < 2500, 25, 50) )=420, 425, CEILING( ROUND((J71*1.5) * IF(J71*1.5 <= 2500, 1.05, 1.18), 2), IF(ROUND((J71*1.5) * IF(J71*1.5 <= 2500, 1.05, 1.18), 2) < 2500, 25, 50) ) ), "" ) -> 3350 | N71: =IF(ISNUMBER(G71), IF(CEILING(ROUND(L71*0.92,2),5)=420, 425, CEILING(ROUND(L71*0.92,2),5) ), "" ) -> 2245 | O71: =IF(ISNUMBER(L71), IF(CEILING(ROUND(L71*1.07,2),5)=420, 425, CEILING(ROUND(L71*1.07,2),5) ), "" ) -> 2615 | P71: =IF((((Price30[Cost]*1.5)+50)/0.835)<2500, MROUND((((( Price30[Cost]*1.5)+50)/0.835)*1.05)*2,10), MROUND((((( Price30[Cost]*1.5)+50)/0.835)*1.18)*2,10)) -> 8030 | Q71: =IF($S$3="","", MROUND( IF($S$3="m", IF($T$3=1, Price30[[#This Row],[Mrp]]+$W$4, Price30[[#This Row],[Mrp]]+$X$4), IF($S$3="nc", IF($T$3=1, Price30[[#This Row],[Net Cash]]+$W$5, Price30[[#This Row],[Net Cash]]+$X$5), IF($S$3="npc", IF($T$3=1, Price30[[#This Row],[Net Price Credit]]+$W$6, Price30[[#This Row],[Net Price Credit]]+$X$6), IF($S$3="w", IF($T$3=1, Price30[[#This Row],[Wsp]]+$W$6, Price30[[#This Row],[Wsp]]+$X$6), "")))), 10)) -> 3420
A72: 2025 | B72: 1214 | C72: lohi | D72: Fine Wool | E72: Sanjay trading | F72: genta kani 15035 | G72: 2700 | I72: 25 | J72: =IF(SUMIF(G72:I72,"<>")=0,"",SUM(G72:I72)) -> 2725 | K72: =IF(ISNUMBER(L72), IF(CEILING(ROUND(L72*0.95,2),5)=420, 425, CEILING(ROUND(L72*0.95,2),5) ), "" ) -> 3370 | L72: =IF(AND(ISNUMBER(J72),ISNUMBER(G72)), IF(CEILING(ROUND(J72*1.3,2),5)=420, 425, CEILING(ROUND(J72*1.3,2),5) ), "" ) -> 3545 | M72: =IF(AND(ISNUMBER(J72),ISNUMBER(G72)), IF( CEILING( ROUND((J72*1.5) * IF(J72*1.5 <= 2500, 1.05, 1.18), 2), IF(ROUND((J72*1.5) * IF(J72*1.5 <= 2500, 1.05, 1.18), 2) < 2500, 25, 50) )=420, 425, CEILING( ROUND((J72*1.5) * IF(J72*1.5 <= 2500, 1.05, 1.18), 2), IF(ROUND((J72*1.5) * IF(J72*1.5 <= 2500, 1.05, 1.18), 2) < 2500, 25, 50) ) ), "" ) -> 4850 | N72: =IF(ISNUMBER(G72), IF(CEILING(ROUND(L72*0.92,2),5)=420, 425, CEILING(ROUND(L72*0.92,2),5) ), "" ) -> 3265 | O72: =IF(ISNUMBER(L72), IF(CEILING(ROUND(L72*1.07,2),5)=420, 425, CEILING(ROUND(L72*1.07,2),5) ), "" ) -> 3795 | P72: =IF((((Price30[Cost]*1.5)+50)/0.835)<2500, MROUND((((( Price30[Cost]*1.5)+50)/0.835)*1.05)*2,10), MROUND((((( Price30[Cost]*1.5)+50)/0.835)*1.18)*2,10)) -> 11590 | Q72: =IF($S$3="","", MROUND( IF($S$3="m", IF($T$3=1, Price30[[#This Row],[Mrp]]+$W$4, Price30[[#This Row],[Mrp]]+$X$4), IF($S$3="nc", IF($T$3=1, Price30[[#This Row],[Net Cash]]+$W$5, Price30[[#This Row],[Net Cash]]+$X$5), IF($S$3="npc", IF($T$3=1, Price30[[#This Row],[Net Price Credit]]+$W$6, Price30[[#This Row],[Net Price Credit]]+$X$6), IF($S$3="w", IF($T$3=1, Price30[[#This Row],[Wsp]]+$W$6, Price30[[#This Row],[Wsp]]+$X$6), "")))), 10)) -> 4920
B73: 122 | C73: Lohi | D73: Fine Wool | E73: Maya | F73: gents kani polywool maya | G73: 1150 | I73: 15 | J73: =IF(SUMIF(G73:I73,"<>")=0,"",SUM(G73:I73)) -> 1165 | K73: =IF(ISNUMBER(L73), IF(CEILING(ROUND(L73*0.95,2),5)=420, 425, CEILING(ROUND(L73*0.95,2),5) ), "" ) -> 1440 | L73: =IF(AND(ISNUMBER(J73),ISNUMBER(G73)), IF(CEILING(ROUND(J73*1.3,2),5)=420, 425, CEILING(ROUND(J73*1.3,2),5) ), "" ) -> 1515 | M73: =IF(AND(ISNUMBER(J73),ISNUMBER(G73)), IF( CEILING( ROUND((J73*1.5) * IF(J73*1.5 <= 2500, 1.05, 1.18), 2), IF(ROUND((J73*1.5) * IF(J73*1.5 <= 2500, 1.05, 1.18), 2) < 2500, 25, 50) )=420, 425, CEILING( ROUND((J73*1.5) * IF(J73*1.5 <= 2500, 1.05, 1.18), 2), IF(ROUND((J73*1.5) * IF(J73*1.5 <= 2500, 1.05, 1.18), 2) < 2500, 25, 50) ) ), "" ) -> 1850 | N73: =IF(ISNUMBER(G73), IF(CEILING(ROUND(L73*0.92,2),5)=420, 425, CEILING(ROUND(L73*0.92,2),5) ), "" ) -> 1395 | O73: =IF(ISNUMBER(L73), IF(CEILING(ROUND(L73*1.07,2),5)=420, 425, CEILING(ROUND(L73*1.07,2),5) ), "" ) -> 1625 | P73: =IF((((Price30[Cost]*1.5)+50)/0.835)<2500, MROUND((((( Price30[Cost]*1.5)+50)/0.835)*1.05)*2,10), MROUND((((( Price30[Cost]*1.5)+50)/0.835)*1.18)*2,10)) -> 4460 | Q73: =IF($S$3="","", MROUND( IF($S$3="m", IF($T$3=1, Price30[[#This Row],[Mrp]]+$W$4, Price30[[#This Row],[Mrp]]+$X$4), IF($S$3="nc", IF($T$3=1, Price30[[#This Row],[Net Cash]]+$W$5, Price30[[#This Row],[Net Cash]]+$X$5), IF($S$3="npc", IF($T$3=1, Price30[[#This Row],[Net Price Credit]]+$W$6, Price30[[#This Row],[Net Price Credit]]+$X$6), IF($S$3="w", IF($T$3=1, Price30[[#This Row],[Wsp]]+$W$6, Price30[[#This Row],[Wsp]]+$X$6), "")))), 10)) -> 1920
A74: 2026 | B74: 123 | C74: Lohi | D74: Fine Wool | E74: Dh | F74: gents kani d.h | G74: 1525 | H74: 5 | I74: 15 | J74: =IF(SUMIF(G74:I74,"<>")=0,"",SUM(G74:I74)) -> 1545 | K74: =IF(ISNUMBER(L74), IF(CEILING(ROUND(L74*0.95,2),5)=420, 425, CEILING(ROUND(L74*0.95,2),5) ), "" ) -> 1910 | L74: =IF(AND(ISNUMBER(J74),ISNUMBER(G74)), IF(CEILING(ROUND(J74*1.3,2),5)=420, 425, CEILING(ROUND(J74*1.3,2),5) ), "" ) -> 2010 | M74: =IF(AND(ISNUMBER(J74),ISNUMBER(G74)), IF( CEILING( ROUND((J74*1.5) * IF(J74*1.5 <= 2500, 1.05, 1.18), 2), IF(ROUND((J74*1.5) * IF(J74*1.5 <= 2500, 1.05, 1.18), 2) < 2500, 25, 50) )=420, 425, CEILING( ROUND((J74*1.5) * IF(J74*1.5 <= 2500, 1.05, 1.18), 2), IF(ROUND((J74*1.5) * IF(J74*1.5 <= 2500, 1.05, 1.18), 2) < 2500, 25, 50) ) ), "" ) -> 2450 | N74: =IF(ISNUMBER(G74), IF(CEILING(ROUND(L74*0.92,2),5)=420, 425, CEILING(ROUND(L74*0.92,2),5) ), "" ) -> 1850 | O74: =IF(ISNUMBER(L74), IF(CEILING(ROUND(L74*1.07,2),5)=420, 425, CEILING(ROUND(L74*1.07,2),5) ), "" ) -> 2155 | P74: =IF((((Price30[Cost]*1.5)+50)/0.835)<2500, MROUND((((( Price30[Cost]*1.5)+50)/0.835)*1.05)*2,10), MROUND((((( Price30[Cost]*1.5)+50)/0.835)*1.18)*2,10)) -> 6610 | Q74: =IF($S$3="","", MROUND( IF($S$3="m", IF($T$3=1, Price30[[#This Row],[Mrp]]+$W$4, Price30[[#This Row],[Mrp]]+$X$4), IF($S$3="nc", IF($T$3=1, Price30[[#This Row],[Net Cash]]+$W$5, Price30[[#This Row],[Net Cash]]+$X$5), IF($S$3="npc", IF($T$3=1, Price30[[#This Row],[Net Price Credit]]+$W$6, Price30[[#This Row],[Net Price Credit]]+$X$6), IF($S$3="w", IF($T$3=1, Price30[[#This Row],[Wsp]]+$W$6, Price30[[#This Row],[Wsp]]+$X$6), "")))), 10)) -> 2520
B75: 124 | C75: Shawl | D75: Fine Wool | E75: Subhash | F75: 40 * 80 neem dour subhash | G75: 3000 | I75: 15 | J75: =IF(SUMIF(G75:I75,"<>")=0,"",SUM(G75:I75)) -> 3015 | K75: =IF(ISNUMBER(L75), IF(CEILING(ROUND(L75*0.95,2),5)=420, 425, CEILING(ROUND(L75*0.95,2),5) ), "" ) -> 3725 | L75: =IF(AND(ISNUMBER(J75),ISNUMBER(G75)), IF(CEILING(ROUND(J75*1.3,2),5)=420, 425, CEILING(ROUND(J75*1.3,2),5) ), "" ) -> 3920 | M75: =IF(AND(ISNUMBER(J75),ISNUMBER(G75)), IF( CEILING( ROUND((J75*1.5) * IF(J75*1.5 <= 2500, 1.05, 1.18), 2), IF(ROUND((J75*1.5) * IF(J75*1.5 <= 2500, 1.05, 1.18), 2) < 2500, 25, 50) )=420, 425, CEILING( ROUND((J75*1.5) * IF(J75*1.5 <= 2500, 1.05, 1.18), 2), IF(ROUND((J75*1.5) * IF(J75*1.5 <= 2500, 1.05, 1.18), 2) < 2500, 25, 50) ) ), "" ) -> 5350 | N75: =IF(ISNUMBER(G75), IF(CEILING(ROUND(L75*0.92,2),5)=420, 425, CEILING(ROUND(L75*0.92,2),5) ), "" ) -> 3610 | O75: =IF(ISNUMBER(L75), IF(CEILING(ROUND(L75*1.07,2),5)=420, 425, CEILING(ROUND(L75*1.07,2),5) ), "" ) -> 4195 | P75: =IF((((Price30[Cost]*1.5)+50)/0.835)<2500, MROUND((((( Price30[Cost]*1.5)+50)/0.835)*1.05)*2,10), MROUND((((( Price30[Cost]*1.5)+50)/0.835)*1.18)*2,10)) -> 12860 | Q75: =IF($S$3="","", MROUND( IF($S$3="m", IF($T$3=1, Price30[[#This Row],[Mrp]]+$W$4, Price30[[#This Row],[Mrp]]+$X$4), IF($S$3="nc", IF($T$3=1, Price30[[#This Row],[Net Cash]]+$W$5, Price30[[#This Row],[Net Cash]]+$X$5), IF($S$3="npc", IF($T$3=1, Price30[[#This Row],[Net Price Credit]]+$W$6, Price30[[#This Row],[Net Price Credit]]+$X$6), IF($S$3="w", IF($T$3=1, Price30[[#This Row],[Wsp]]+$W$6, Price30[[#This Row],[Wsp]]+$X$6), "")))), 10)) -> 5420
A76: 2026 | B76: 125 | C76: Shawl | D76: Fine Wool | E76: Subhash | F76: sangeen jamma | G76: 4800 | I76: 25 | J76: =IF(SUMIF(G76:I76,"<>")=0,"",SUM(G76:I76)) -> 4825 | K76: =IF(ISNUMBER(L76), IF(CEILING(ROUND(L76*0.95,2),5)=420, 425, CEILING(ROUND(L76*0.95,2),5) ), "" ) -> 5965 | L76: =IF(AND(ISNUMBER(J76),ISNUMBER(G76)), IF(CEILING(ROUND(J76*1.3,2),5)=420, 425, CEILING(ROUND(J76*1.3,2),5) ), "" ) -> 6275 | M76: =IF(AND(ISNUMBER(J76),ISNUMBER(G76)), IF( CEILING( ROUND((J76*1.5) * IF(J76*1.5 <= 2500, 1.05, 1.18), 2), IF(ROUND((J76*1.5) * IF(J76*1.5 <= 2500, 1.05, 1.18), 2) < 2500, 25, 50) )=420, 425, CEILING( ROUND((J76*1.5) * IF(J76*1.5 <= 2500, 1.05, 1.18), 2), IF(ROUND((J76*1.5) * IF(J76*1.5 <= 2500, 1.05, 1.18), 2) < 2500, 25, 50) ) ), "" ) -> 8550 | N76: =IF(ISNUMBER(G76), IF(CEILING(ROUND(L76*0.92,2),5)=420, 425, CEILING(ROUND(L76*0.92,2),5) ), "" ) -> 5775 | O76: =IF(ISNUMBER(L76), IF(CEILING(ROUND(L76*1.07,2),5)=420, 425, CEILING(ROUND(L76*1.07,2),5) ), "" ) -> 6715 | P76: =IF((((Price30[Cost]*1.5)+50)/0.835)<2500, MROUND((((( Price30[Cost]*1.5)+50)/0.835)*1.05)*2,10), MROUND((((( Price30[Cost]*1.5)+50)/0.835)*1.18)*2,10)) -> 20490 | Q76: =IF($S$3="","", MROUND( IF($S$3="m", IF($T$3=1, Price30[[#This Row],[Mrp]]+$W$4, Price30[[#This Row],[Mrp]]+$X$4), IF($S$3="nc", IF($T$3=1, Price30[[#This Row],[Net Cash]]+$W$5, Price30[[#This Row],[Net Cash]]+$X$5), IF($S$3="npc", IF($T$3=1, Price30[[#This Row],[Net Price Credit]]+$W$6, Price30[[#This Row],[Net Price Credit]]+$X$6), IF($S$3="w", IF($T$3=1, Price30[[#This Row],[Wsp]]+$W$6, Price30[[#This Row],[Wsp]]+$X$6), "")))), 10)) -> 8620
B77: 126 | C77: Shawl | D77: Fine Wool | E77: ashwani | F77: gents shahtoosh pure | G77: 2000 | I77: 15 | J77: =IF(SUMIF(G77:I77,"<>")=0,"",SUM(G77:I77)) -> 2015 | K77: =IF(ISNUMBER(L77), IF(CEILING(ROUND(L77*0.95,2),5)=420, 425, CEILING(ROUND(L77*0.95,2),5) ), "" ) -> 2490 | L77: =IF(AND(ISNUMBER(J77),ISNUMBER(G77)), IF(CEILING(ROUND(J77*1.3,2),5)=420, 425, CEILING(ROUND(J77*1.3,2),5) ), "" ) -> 2620 | M77: =IF(AND(ISNUMBER(J77),ISNUMBER(G77)), IF( CEILING( ROUND((J77*1.5) * IF(J77*1.5 <= 2500, 1.05, 1.18), 2), IF(ROUND((J77*1.5) * IF(J77*1.5 <= 2500, 1.05, 1.18), 2) < 2500, 25, 50) )=420, 425, CEILING( ROUND((J77*1.5) * IF(J77*1.5 <= 2500, 1.05, 1.18), 2), IF(ROUND((J77*1.5) * IF(J77*1.5 <= 2500, 1.05, 1.18), 2) < 2500, 25, 50) ) ), "" ) -> 3600 | N77: =IF(ISNUMBER(G77), IF(CEILING(ROUND(L77*0.92,2),5)=420, 425, CEILING(ROUND(L77*0.92,2),5) ), "" ) -> 2415 | O77: =IF(ISNUMBER(L77), IF(CEILING(ROUND(L77*1.07,2),5)=420, 425, CEILING(ROUND(L77*1.07,2),5) ), "" ) -> 2805 | P77: =IF((((Price30[Cost]*1.5)+50)/0.835)<2500, MROUND((((( Price30[Cost]*1.5)+50)/0.835)*1.05)*2,10), MROUND((((( Price30[Cost]*1.5)+50)/0.835)*1.18)*2,10)) -> 8620 | Q77: =IF($S$3="","", MROUND( IF($S$3="m", IF($T$3=1, Price30[[#This Row],[Mrp]]+$W$4, Price30[[#This Row],[Mrp]]+$X$4), IF($S$3="nc", IF($T$3=1, Price30[[#This Row],[Net Cash]]+$W$5, Price30[[#This Row],[Net Cash]]+$X$5), IF($S$3="npc", IF($T$3=1, Price30[[#This Row],[Net Price Credit]]+$W$6, Price30[[#This Row],[Net Price Credit]]+$X$6), IF($S$3="w", IF($T$3=1, Price30[[#This Row],[Wsp]]+$W$6, Price30[[#This Row],[Wsp]]+$X$6), "")))), 10)) -> 3670
A78: 2025 | B78: 127 | C78: Lohi | D78: Fine Wool | E78: m.r | F78: kunj lohi kani | G78: 1100 | I78: 15 | J78: =IF(SUMIF(G78:I78,"<>")=0,"",SUM(G78:I78)) -> 1115 | K78: =IF(ISNUMBER(L78), IF(CEILING(ROUND(L78*0.95,2),5)=420, 425, CEILING(ROUND(L78*0.95,2),5) ), "" ) -> 1380 | L78: =IF(AND(ISNUMBER(J78),ISNUMBER(G78)), IF(CEILING(ROUND(J78*1.3,2),5)=420, 425, CEILING(ROUND(J78*1.3,2),5) ), "" ) -> 1450 | M78: =IF(AND(ISNUMBER(J78),ISNUMBER(G78)), IF( CEILING( ROUND((J78*1.5) * IF(J78*1.5 <= 2500, 1.05, 1.18), 2), IF(ROUND((J78*1.5) * IF(J78*1.5 <= 2500, 1.05, 1.18), 2) < 2500, 25, 50) )=420, 425, CEILING( ROUND((J78*1.5) * IF(J78*1.5 <= 2500, 1.05, 1.18), 2), IF(ROUND((J78*1.5) * IF(J78*1.5 <= 2500, 1.05, 1.18), 2) < 2500, 25, 50) ) ), "" ) -> 1775 | N78: =IF(ISNUMBER(G78), IF(CEILING(ROUND(L78*0.92,2),5)=420, 425, CEILING(ROUND(L78*0.92,2),5) ), "" ) -> 1335 | O78: =IF(ISNUMBER(L78), IF(CEILING(ROUND(L78*1.07,2),5)=420, 425, CEILING(ROUND(L78*1.07,2),5) ), "" ) -> 1555 | P78: =IF((((Price30[Cost]*1.5)+50)/0.835)<2500, MROUND((((( Price30[Cost]*1.5)+50)/0.835)*1.05)*2,10), MROUND((((( Price30[Cost]*1.5)+50)/0.835)*1.18)*2,10)) -> 4280 | Q78: =IF($S$3="","", MROUND( IF($S$3="m", IF($T$3=1, Price30[[#This Row],[Mrp]]+$W$4, Price30[[#This Row],[Mrp]]+$X$4), IF($S$3="nc", IF($T$3=1, Price30[[#This Row],[Net Cash]]+$W$5, Price30[[#This Row],[Net Cash]]+$X$5), IF($S$3="npc", IF($T$3=1, Price30[[#This Row],[Net Price Credit]]+$W$6, Price30[[#This Row],[Net Price Credit]]+$X$6), IF($S$3="w", IF($T$3=1, Price30[[#This Row],[Wsp]]+$W$6, Price30[[#This Row],[Wsp]]+$X$6), "")))), 10)) -> 1850
A79: 2025 | B79: 128 | C79: shawl | D79: Fine Wool | E79: Subhash | F79: sangeen jal no.25208 | G79: 2100 | I79: 15 | J79: =IF(SUMIF(G79:I79,"<>")=0,"",SUM(G79:I79)) -> 2115 | K79: =IF(ISNUMBER(L79), IF(CEILING(ROUND(L79*0.95,2),5)=420, 425, CEILING(ROUND(L79*0.95,2),5) ), "" ) -> 2615 | L79: =IF(AND(ISNUMBER(J79),ISNUMBER(G79)), IF(CEILING(ROUND(J79*1.3,2),5)=420, 425, CEILING(ROUND(J79*1.3,2),5) ), "" ) -> 2750 | M79: =IF(AND(ISNUMBER(J79),ISNUMBER(G79)), IF( CEILING( ROUND((J79*1.5) * IF(J79*1.5 <= 2500, 1.05, 1.18), 2), IF(ROUND((J79*1.5) * IF(J79*1.5 <= 2500, 1.05, 1.18), 2) < 2500, 25, 50) )=420, 425, CEILING( ROUND((J79*1.5) * IF(J79*1.5 <= 2500, 1.05, 1.18), 2), IF(ROUND((J79*1.5) * IF(J79*1.5 <= 2500, 1.05, 1.18), 2) < 2500, 25, 50) ) ), "" ) -> 3750 | N79: =IF(ISNUMBER(G79), IF(CEILING(ROUND(L79*0.92,2),5)=420, 425, CEILING(ROUND(L79*0.92,2),5) ), "" ) -> 2530 | O79: =IF(ISNUMBER(L79), IF(CEILING(ROUND(L79*1.07,2),5)=420, 425, CEILING(ROUND(L79*1.07,2),5) ), "" ) -> 2945 | P79: =IF((((Price30[Cost]*1.5)+50)/0.835)<2500, MROUND((((( Price30[Cost]*1.5)+50)/0.835)*1.05)*2,10), MROUND((((( Price30[Cost]*1.5)+50)/0.835)*1.18)*2,10)) -> 9040 | Q79: =IF($S$3="","", MROUND( IF($S$3="m", IF($T$3=1, Price30[[#This Row],[Mrp]]+$W$4, Price30[[#This Row],[Mrp]]+$X$4), IF($S$3="nc", IF($T$3=1, Price30[[#This Row],[Net Cash]]+$W$5, Price30[[#This Row],[Net Cash]]+$X$5), IF($S$3="npc", IF($T$3=1, Price30[[#This Row],[Net Price Credit]]+$W$6, Price30[[#This Row],[Net Price Credit]]+$X$6), IF($S$3="w", IF($T$3=1, Price30[[#This Row],[Wsp]]+$W$6, Price30[[#This Row],[Wsp]]+$X$6), "")))), 10)) -> 3820
A80: 2026 | B80: 129 | C80: Shawl | D80: Fine Wool | E80: Subhash | F80: neem dour subhash | G80: 2100 | I80: 15 | J80: =IF(SUMIF(G80:I80,"<>")=0,"",SUM(G80:I80)) -> 2115 | K80: =IF(ISNUMBER(L80), IF(CEILING(ROUND(L80*0.95,2),5)=420, 425, CEILING(ROUND(L80*0.95,2),5) ), "" ) -> 2615 | L80: =IF(AND(ISNUMBER(J80),ISNUMBER(G80)), IF(CEILING(ROUND(J80*1.3,2),5)=420, 425, CEILING(ROUND(J80*1.3,2),5) ), "" ) -> 2750 | M80: =IF(AND(ISNUMBER(J80),ISNUMBER(G80)), IF( CEILING( ROUND((J80*1.5) * IF(J80*1.5 <= 2500, 1.05, 1.18), 2), IF(ROUND((J80*1.5) * IF(J80*1.5 <= 2500, 1.05, 1.18), 2) < 2500, 25, 50) )=420, 425, CEILING( ROUND((J80*1.5) * IF(J80*1.5 <= 2500, 1.05, 1.18), 2), IF(ROUND((J80*1.5) * IF(J80*1.5 <= 2500, 1.05, 1.18), 2) < 2500, 25, 50) ) ), "" ) -> 3750 | N80: =IF(ISNUMBER(G80), IF(CEILING(ROUND(L80*0.92,2),5)=420, 425, CEILING(ROUND(L80*0.92,2),5) ), "" ) -> 2530 | O80: =IF(ISNUMBER(L80), IF(CEILING(ROUND(L80*1.07,2),5)=420, 425, CEILING(ROUND(L80*1.07,2),5) ), "" ) -> 2945 | P80: =IF((((Price30[Cost]*1.5)+50)/0.835)<2500, MROUND((((( Price30[Cost]*1.5)+50)/0.835)*1.05)*2,10), MROUND((((( Price30[Cost]*1.5)+50)/0.835)*1.18)*2,10)) -> 9040 | Q80: =IF($S$3="","", MROUND( IF($S$3="m", IF($T$3=1, Price30[[#This Row],[Mrp]]+$W$4, Price30[[#This Row],[Mrp]]+$X$4), IF($S$3="nc", IF($T$3=1, Price30[[#This Row],[Net Cash]]+$W$5, Price30[[#This Row],[Net Cash]]+$X$5), IF($S$3="npc", IF($T$3=1, Price30[[#This Row],[Net Price Credit]]+$W$6, Price30[[#This Row],[Net Price Credit]]+$X$6), IF($S$3="w", IF($T$3=1, Price30[[#This Row],[Wsp]]+$W$6, Price30[[#This Row],[Wsp]]+$X$6), "")))), 10)) -> 3820
A81: 2026 | B81: 130 | C81: shawl | D81: Fine Wool | E81: Subhash | F81: sangeen dour multihead 25205 | G81: 1800 | I81: 15 | J81: =IF(SUMIF(G81:I81,"<>")=0,"",SUM(G81:I81)) -> 1815 | K81: =IF(ISNUMBER(L81), IF(CEILING(ROUND(L81*0.95,2),5)=420, 425, CEILING(ROUND(L81*0.95,2),5) ), "" ) -> 2245 | L81: =IF(AND(ISNUMBER(J81),ISNUMBER(G81)), IF(CEILING(ROUND(J81*1.3,2),5)=420, 425, CEILING(ROUND(J81*1.3,2),5) ), "" ) -> 2360 | M81: =IF(AND(ISNUMBER(J81),ISNUMBER(G81)), IF( CEILING( ROUND((J81*1.5) * IF(J81*1.5 <= 2500, 1.05, 1.18), 2), IF(ROUND((J81*1.5) * IF(J81*1.5 <= 2500, 1.05, 1.18), 2) < 2500, 25, 50) )=420, 425, CEILING( ROUND((J81*1.5) * IF(J81*1.5 <= 2500, 1.05, 1.18), 2), IF(ROUND((J81*1.5) * IF(J81*1.5 <= 2500, 1.05, 1.18), 2) < 2500, 25, 50) ) ), "" ) -> 3250 | N81: =IF(ISNUMBER(G81), IF(CEILING(ROUND(L81*0.92,2),5)=420, 425, CEILING(ROUND(L81*0.92,2),5) ), "" ) -> 2175 | O81: =IF(ISNUMBER(L81), IF(CEILING(ROUND(L81*1.07,2),5)=420, 425, CEILING(ROUND(L81*1.07,2),5) ), "" ) -> 2530 | P81: =IF((((Price30[Cost]*1.5)+50)/0.835)<2500, MROUND((((( Price30[Cost]*1.5)+50)/0.835)*1.05)*2,10), MROUND((((( Price30[Cost]*1.5)+50)/0.835)*1.18)*2,10)) -> 7770 | Q81: =IF($S$3="","", MROUND( IF($S$3="m", IF($T$3=1, Price30[[#This Row],[Mrp]]+$W$4, Price30[[#This Row],[Mrp]]+$X$4), IF($S$3="nc", IF($T$3=1, Price30[[#This Row],[Net Cash]]+$W$5, Price30[[#This Row],[Net Cash]]+$X$5), IF($S$3="npc", IF($T$3=1, Price30[[#This Row],[Net Price Credit]]+$W$6, Price30[[#This Row],[Net Price Credit]]+$X$6), IF($S$3="w", IF($T$3=1, Price30[[#This Row],[Wsp]]+$W$6, Price30[[#This Row],[Wsp]]+$X$6), "")))), 10)) -> 3320
B82: 131 | C82: Shawl | D82: Fine Wool | F82: gents char hashia toosh 50*100 | G82: 3000 | I82: 15 | J82: =IF(SUMIF(G82:I82,"<>")=0,"",SUM(G82:I82)) -> 3015 | K82: =IF(ISNUMBER(L82), IF(CEILING(ROUND(L82*0.95,2),5)=420, 425, CEILING(ROUND(L82*0.95,2),5) ), "" ) -> 3725 | L82: =IF(AND(ISNUMBER(J82),ISNUMBER(G82)), IF(CEILING(ROUND(J82*1.3,2),5)=420, 425, CEILING(ROUND(J82*1.3,2),5) ), "" ) -> 3920 | M82: =IF(AND(ISNUMBER(J82),ISNUMBER(G82)), IF( CEILING( ROUND((J82*1.5) * IF(J82*1.5 <= 2500, 1.05, 1.18), 2), IF(ROUND((J82*1.5) * IF(J82*1.5 <= 2500, 1.05, 1.18), 2) < 2500, 25, 50) )=420, 425, CEILING( ROUND((J82*1.5) * IF(J82*1.5 <= 2500, 1.05, 1.18), 2), IF(ROUND((J82*1.5) * IF(J82*1.5 <= 2500, 1.05, 1.18), 2) < 2500, 25, 50) ) ), "" ) -> 5350 | N82: =IF(ISNUMBER(G82), IF(CEILING(ROUND(L82*0.92,2),5)=420, 425, CEILING(ROUND(L82*0.92,2),5) ), "" ) -> 3610 | O82: =IF(ISNUMBER(L82), IF(CEILING(ROUND(L82*1.07,2),5)=420, 425, CEILING(ROUND(L82*1.07,2),5) ), "" ) -> 4195 | P82: =IF((((Price30[Cost]*1.5)+50)/0.835)<2500, MROUND((((( Price30[Cost]*1.5)+50)/0.835)*1.05)*2,10), MROUND((((( Price30[Cost]*1.5)+50)/0.835)*1.18)*2,10)) -> 12860 | Q82: =IF($S$3="","", MROUND( IF($S$3="m", IF($T$3=1, Price30[[#This Row],[Mrp]]+$W$4, Price30[[#This Row],[Mrp]]+$X$4), IF($S$3="nc", IF($T$3=1, Price30[[#This Row],[Net Cash]]+$W$5, Price30[[#This Row],[Net Cash]]+$X$5), IF($S$3="npc", IF($T$3=1, Price30[[#This Row],[Net Price Credit]]+$W$6, Price30[[#This Row],[Net Price Credit]]+$X$6), IF($S$3="w", IF($T$3=1, Price30[[#This Row],[Wsp]]+$W$6, Price30[[#This Row],[Wsp]]+$X$6), "")))), 10)) -> 5420
A83: 2025 | B83: 132 | C83: shawl | D83: Fine Wool | E83: Subhash | F83: medium dour multihead 25204 | G83: 1700 | I83: 15 | J83: =IF(SUMIF(G83:I83,"<>")=0,"",SUM(G83:I83)) -> 1715 | K83: =IF(ISNUMBER(L83), IF(CEILING(ROUND(L83*0.95,2),5)=420, 425, CEILING(ROUND(L83*0.95,2),5) ), "" ) -> 2120 | L83: =IF(AND(ISNUMBER(J83),ISNUMBER(G83)), IF(CEILING(ROUND(J83*1.3,2),5)=420, 425, CEILING(ROUND(J83*1.3,2),5) ), "" ) -> 2230 | M83: =IF(AND(ISNUMBER(J83),ISNUMBER(G83)), IF( CEILING( ROUND((J83*1.5) * IF(J83*1.5 <= 2500, 1.05, 1.18), 2), IF(ROUND((J83*1.5) * IF(J83*1.5 <= 2500, 1.05, 1.18), 2) < 2500, 25, 50) )=420, 425, CEILING( ROUND((J83*1.5) * IF(J83*1.5 <= 2500, 1.05, 1.18), 2), IF(ROUND((J83*1.5) * IF(J83*1.5 <= 2500, 1.05, 1.18), 2) < 2500, 25, 50) ) ), "" ) -> 3050 | N83: =IF(ISNUMBER(G83), IF(CEILING(ROUND(L83*0.92,2),5)=420, 425, CEILING(ROUND(L83*0.92,2),5) ), "" ) -> 2055 | O83: =IF(ISNUMBER(L83), IF(CEILING(ROUND(L83*1.07,2),5)=420, 425, CEILING(ROUND(L83*1.07,2),5) ), "" ) -> 2390 | P83: =IF((((Price30[Cost]*1.5)+50)/0.835)<2500, MROUND((((( Price30[Cost]*1.5)+50)/0.835)*1.05)*2,10), MROUND((((( Price30[Cost]*1.5)+50)/0.835)*1.18)*2,10)) -> 7350 | Q83: =IF($S$3="","", MROUND( IF($S$3="m", IF($T$3=1, Price30[[#This Row],[Mrp]]+$W$4, Price30[[#This Row],[Mrp]]+$X$4), IF($S$3="nc", IF($T$3=1, Price30[[#This Row],[Net Cash]]+$W$5, Price30[[#This Row],[Net Cash]]+$X$5), IF($S$3="npc", IF($T$3=1, Price30[[#This Row],[Net Price Credit]]+$W$6, Price30[[#This Row],[Net Price Credit]]+$X$6), IF($S$3="w", IF($T$3=1, Price30[[#This Row],[Wsp]]+$W$6, Price30[[#This Row],[Wsp]]+$X$6), "")))), 10)) -> 3120
A84: 2026 | B84: 133 | C84: Shawl | D84: Fine Wool | E84: subhash | F84: silky jamma | G84: 6000 | I84: 15 | J84: =IF(SUMIF(G84:I84,"<>")=0,"",SUM(G84:I84)) -> 6015 | K84: =IF(ISNUMBER(L84), IF(CEILING(ROUND(L84*0.95,2),5)=420, 425, CEILING(ROUND(L84*0.95,2),5) ), "" ) -> 7430 | L84: =IF(AND(ISNUMBER(J84),ISNUMBER(G84)), IF(CEILING(ROUND(J84*1.3,2),5)=420, 425, CEILING(ROUND(J84*1.3,2),5) ), "" ) -> 7820 | M84: =IF(AND(ISNUMBER(J84),ISNUMBER(G84)), IF( CEILING( ROUND((J84*1.5) * IF(J84*1.5 <= 2500, 1.05, 1.18), 2), IF(ROUND((J84*1.5) * IF(J84*1.5 <= 2500, 1.05, 1.18), 2) < 2500, 25, 50) )=420, 425, CEILING( ROUND((J84*1.5) * IF(J84*1.5 <= 2500, 1.05, 1.18), 2), IF(ROUND((J84*1.5) * IF(J84*1.5 <= 2500, 1.05, 1.18), 2) < 2500, 25, 50) ) ), "" ) -> 10650 | N84: =IF(ISNUMBER(G84), IF(CEILING(ROUND(L84*0.92,2),5)=420, 425, CEILING(ROUND(L84*0.92,2),5) ), "" ) -> 7195 | O84: =IF(ISNUMBER(L84), IF(CEILING(ROUND(L84*1.07,2),5)=420, 425, CEILING(ROUND(L84*1.07,2),5) ), "" ) -> 8370 | P84: =IF((((Price30[Cost]*1.5)+50)/0.835)<2500, MROUND((((( Price30[Cost]*1.5)+50)/0.835)*1.05)*2,10), MROUND((((( Price30[Cost]*1.5)+50)/0.835)*1.18)*2,10)) -> 25580 | Q84: =IF($S$3="","", MROUND( IF($S$3="m", IF($T$3=1, Price30[[#This Row],[Mrp]]+$W$4, Price30[[#This Row],[Mrp]]+$X$4), IF($S$3="nc", IF($T$3=1, Price30[[#This Row],[Net Cash]]+$W$5, Price30[[#This Row],[Net Cash]]+$X$5), IF($S$3="npc", IF($T$3=1, Price30[[#This Row],[Net Price Credit]]+$W$6, Price30[[#This Row],[Net Price Credit]]+$X$6), IF($S$3="w", IF($T$3=1, Price30[[#This Row],[Wsp]]+$W$6, Price30[[#This Row],[Wsp]]+$X$6), "")))), 10)) -> 10720
A85: 2026 | B85: 134 | C85: Shawl | D85: Fine Wool | E85: Rajesh | F85: 40*80 shahtoosh polywool | G85: 900 | I85: 15 | J85: =IF(SUMIF(G85:I85,"<>")=0,"",SUM(G85:I85)) -> 915 | K85: =IF(ISNUMBER(L85), IF(CEILING(ROUND(L85*0.95,2),5)=420, 425, CEILING(ROUND(L85*0.95,2),5) ), "" ) -> 1135 | L85: =IF(AND(ISNUMBER(J85),ISNUMBER(G85)), IF(CEILING(ROUND(J85*1.3,2),5)=420, 425, CEILING(ROUND(J85*1.3,2),5) ), "" ) -> 1190 | M85: =IF(AND(ISNUMBER(J85),ISNUMBER(G85)), IF( CEILING( ROUND((J85*1.5) * IF(J85*1.5 <= 2500, 1.05, 1.18), 2), IF(ROUND((J85*1.5) * IF(J85*1.5 <= 2500, 1.05, 1.18), 2) < 2500, 25, 50) )=420, 425, CEILING( ROUND((J85*1.5) * IF(J85*1.5 <= 2500, 1.05, 1.18), 2), IF(ROUND((J85*1.5) * IF(J85*1.5 <= 2500, 1.05, 1.18), 2) < 2500, 25, 50) ) ), "" ) -> 1450 | N85: =IF(ISNUMBER(G85), IF(CEILING(ROUND(L85*0.92,2),5)=420, 425, CEILING(ROUND(L85*0.92,2),5) ), "" ) -> 1095 | O85: =IF(ISNUMBER(L85), IF(CEILING(ROUND(L85*1.07,2),5)=420, 425, CEILING(ROUND(L85*1.07,2),5) ), "" ) -> 1275 | P85: =IF((((Price30[Cost]*1.5)+50)/0.835)<2500, MROUND((((( Price30[Cost]*1.5)+50)/0.835)*1.05)*2,10), MROUND((((( Price30[Cost]*1.5)+50)/0.835)*1.18)*2,10)) -> 3520 | Q85: =IF($S$3="","", MROUND( IF($S$3="m", IF($T$3=1, Price30[[#This Row],[Mrp]]+$W$4, Price30[[#This Row],[Mrp]]+$X$4), IF($S$3="nc", IF($T$3=1, Price30[[#This Row],[Net Cash]]+$W$5, Price30[[#This Row],[Net Cash]]+$X$5), IF($S$3="npc", IF($T$3=1, Price30[[#This Row],[Net Price Credit]]+$W$6, Price30[[#This Row],[Net Price Credit]]+$X$6), IF($S$3="w", IF($T$3=1, Price30[[#This Row],[Wsp]]+$W$6, Price30[[#This Row],[Wsp]]+$X$6), "")))), 10)) -> 1520
B86: 135 | C86: Shawl | D86: Fine Wool | E86: Sun | F86: hashia 40" pure sun woollen | G86: 1500 | I86: 15 | J86: =IF(SUMIF(G86:I86,"<>")=0,"",SUM(G86:I86)) -> 1515 | K86: =IF(ISNUMBER(L86), IF(CEILING(ROUND(L86*0.95,2),5)=420, 425, CEILING(ROUND(L86*0.95,2),5) ), "" ) -> 1875 | L86: =IF(AND(ISNUMBER(J86),ISNUMBER(G86)), IF(CEILING(ROUND(J86*1.3,2),5)=420, 425, CEILING(ROUND(J86*1.3,2),5) ), "" ) -> 1970 | M86: =IF(AND(ISNUMBER(J86),ISNUMBER(G86)), IF( CEILING( ROUND((J86*1.5) * IF(J86*1.5 <= 2500, 1.05, 1.18), 2), IF(ROUND((J86*1.5) * IF(J86*1.5 <= 2500, 1.05, 1.18), 2) < 2500, 25, 50) )=420, 425, CEILING( ROUND((J86*1.5) * IF(J86*1.5 <= 2500, 1.05, 1.18), 2), IF(ROUND((J86*1.5) * IF(J86*1.5 <= 2500, 1.05, 1.18), 2) < 2500, 25, 50) ) ), "" ) -> 2400 | N86: =IF(ISNUMBER(G86), IF(CEILING(ROUND(L86*0.92,2),5)=420, 425, CEILING(ROUND(L86*0.92,2),5) ), "" ) -> 1815 | O86: =IF(ISNUMBER(L86), IF(CEILING(ROUND(L86*1.07,2),5)=420, 425, CEILING(ROUND(L86*1.07,2),5) ), "" ) -> 2110 | P86: =IF((((Price30[Cost]*1.5)+50)/0.835)<2500, MROUND((((( Price30[Cost]*1.5)+50)/0.835)*1.05)*2,10), MROUND((((( Price30[Cost]*1.5)+50)/0.835)*1.18)*2,10)) -> 6500 | Q86: =IF($S$3="","", MROUND( IF($S$3="m", IF($T$3=1, Price30[[#This Row],[Mrp]]+$W$4, Price30[[#This Row],[Mrp]]+$X$4), IF($S$3="nc", IF($T$3=1, Price30[[#This Row],[Net Cash]]+$W$5, Price30[[#This Row],[Net Cash]]+$X$5), IF($S$3="npc", IF($T$3=1, Price30[[#This Row],[Net Price Credit]]+$W$6, Price30[[#This Row],[Net Price Credit]]+$X$6), IF($S$3="w", IF($T$3=1, Price30[[#This Row],[Wsp]]+$W$6, Price30[[#This Row],[Wsp]]+$X$6), "")))), 10)) -> 2470
A87: 2025 | B87: 136 | C87: shawl | D87: Fine Wool | E87: ramesh khanna | F87: self jal | G87: 1375 | I87: 15 | J87: =IF(SUMIF(G87:I87,"<>")=0,"",SUM(G87:I87)) -> 1390 | K87: =IF(ISNUMBER(L87), IF(CEILING(ROUND(L87*0.95,2),5)=420, 425, CEILING(ROUND(L87*0.95,2),5) ), "" ) -> 1720 | L87: =IF(AND(ISNUMBER(J87),ISNUMBER(G87)), IF(CEILING(ROUND(J87*1.3,2),5)=420, 425, CEILING(ROUND(J87*1.3,2),5) ), "" ) -> 1810 | M87: =IF(AND(ISNUMBER(J87),ISNUMBER(G87)), IF( CEILING( ROUND((J87*1.5) * IF(J87*1.5 <= 2500, 1.05, 1.18), 2), IF(ROUND((J87*1.5) * IF(J87*1.5 <= 2500, 1.05, 1.18), 2) < 2500, 25, 50) )=420, 425, CEILING( ROUND((J87*1.5) * IF(J87*1.5 <= 2500, 1.05, 1.18), 2), IF(ROUND((J87*1.5) * IF(J87*1.5 <= 2500, 1.05, 1.18), 2) < 2500, 25, 50) ) ), "" ) -> 2200 | N87: =IF(ISNUMBER(G87), IF(CEILING(ROUND(L87*0.92,2),5)=420, 425, CEILING(ROUND(L87*0.92,2),5) ), "" ) -> 1670 | O87: =IF(ISNUMBER(L87), IF(CEILING(ROUND(L87*1.07,2),5)=420, 425, CEILING(ROUND(L87*1.07,2),5) ), "" ) -> 1940 | P87: =IF((((Price30[Cost]*1.5)+50)/0.835)<2500, MROUND((((( Price30[Cost]*1.5)+50)/0.835)*1.05)*2,10), MROUND((((( Price30[Cost]*1.5)+50)/0.835)*1.18)*2,10)) -> 5970 | Q87: =IF($S$3="","", MROUND( IF($S$3="m", IF($T$3=1, Price30[[#This Row],[Mrp]]+$W$4, Price30[[#This Row],[Mrp]]+$X$4), IF($S$3="nc", IF($T$3=1, Price30[[#This Row],[Net Cash]]+$W$5, Price30[[#This Row],[Net Cash]]+$X$5), IF($S$3="npc", IF($T$3=1, Price30[[#This Row],[Net Price Credit]]+$W$6, Price30[[#This Row],[Net Price Credit]]+$X$6), IF($S$3="w", IF($T$3=1, Price30[[#This Row],[Wsp]]+$W$6, Price30[[#This Row],[Wsp]]+$X$6), "")))), 10)) -> 2270
A88: 2025 | B88: 137 | C88: Shawl | D88: Fine Wool | E88: Ashwani | F88: digital print kalamkari ashwani | G88: 6500 | I88: 15 | J88: =IF(SUMIF(G88:I88,"<>")=0,"",SUM(G88:I88)) -> 6515 | K88: =IF(ISNUMBER(L88), IF(CEILING(ROUND(L88*0.95,2),5)=420, 425, CEILING(ROUND(L88*0.95,2),5) ), "" ) -> 8050 | L88: =IF(AND(ISNUMBER(J88),ISNUMBER(G88)), IF(CEILING(ROUND(J88*1.3,2),5)=420, 425, CEILING(ROUND(J88*1.3,2),5) ), "" ) -> 8470 | M88: =IF(AND(ISNUMBER(J88),ISNUMBER(G88)), IF( CEILING( ROUND((J88*1.5) * IF(J88*1.5 <= 2500, 1.05, 1.18), 2), IF(ROUND((J88*1.5) * IF(J88*1.5 <= 2500, 1.05, 1.18), 2) < 2500, 25, 50) )=420, 425, CEILING( ROUND((J88*1.5) * IF(J88*1.5 <= 2500, 1.05, 1.18), 2), IF(ROUND((J88*1.5) * IF(J88*1.5 <= 2500, 1.05, 1.18), 2) < 2500, 25, 50) ) ), "" ) -> 11550 | N88: =IF(ISNUMBER(G88), IF(CEILING(ROUND(L88*0.92,2),5)=420, 425, CEILING(ROUND(L88*0.92,2),5) ), "" ) -> 7795 | O88: =IF(ISNUMBER(L88), IF(CEILING(ROUND(L88*1.07,2),5)=420, 425, CEILING(ROUND(L88*1.07,2),5) ), "" ) -> 9065 | P88: =IF((((Price30[Cost]*1.5)+50)/0.835)<2500, MROUND((((( Price30[Cost]*1.5)+50)/0.835)*1.05)*2,10), MROUND((((( Price30[Cost]*1.5)+50)/0.835)*1.18)*2,10)) -> 27700 | Q88: =IF($S$3="","", MROUND( IF($S$3="m", IF($T$3=1, Price30[[#This Row],[Mrp]]+$W$4, Price30[[#This Row],[Mrp]]+$X$4), IF($S$3="nc", IF($T$3=1, Price30[[#This Row],[Net Cash]]+$W$5, Price30[[#This Row],[Net Cash]]+$X$5), IF($S$3="npc", IF($T$3=1, Price30[[#This Row],[Net Price Credit]]+$W$6, Price30[[#This Row],[Net Price Credit]]+$X$6), IF($S$3="w", IF($T$3=1, Price30[[#This Row],[Wsp]]+$W$6, Price30[[#This Row],[Wsp]]+$X$6), "")))), 10)) -> 11620
A89: 2026 | B89: 138 | C89: Shawl | D89: Fine Wool | E89: subhash | F89: jamma ashwani + subhash pajley jamma 7900 | G89: 9000 | I89: 15 | J89: =IF(SUMIF(G89:I89,"<>")=0,"",SUM(G89:I89)) -> 9015 | K89: =IF(ISNUMBER(L89), IF(CEILING(ROUND(L89*0.95,2),5)=420, 425, CEILING(ROUND(L89*0.95,2),5) ), "" ) -> 11135 | L89: =IF(AND(ISNUMBER(J89),ISNUMBER(G89)), IF(CEILING(ROUND(J89*1.3,2),5)=420, 425, CEILING(ROUND(J89*1.3,2),5) ), "" ) -> 11720 | M89: =IF(AND(ISNUMBER(J89),ISNUMBER(G89)), IF( CEILING( ROUND((J89*1.5) * IF(J89*1.5 <= 2500, 1.05, 1.18), 2), IF(ROUND((J89*1.5) * IF(J89*1.5 <= 2500, 1.05, 1.18), 2) < 2500, 25, 50) )=420, 425, CEILING( ROUND((J89*1.5) * IF(J89*1.5 <= 2500, 1.05, 1.18), 2), IF(ROUND((J89*1.5) * IF(J89*1.5 <= 2500, 1.05, 1.18), 2) < 2500, 25, 50) ) ), "" ) -> 16000 | N89: =IF(ISNUMBER(G89), IF(CEILING(ROUND(L89*0.92,2),5)=420, 425, CEILING(ROUND(L89*0.92,2),5) ), "" ) -> 10785 | O89: =IF(ISNUMBER(L89), IF(CEILING(ROUND(L89*1.07,2),5)=420, 425, CEILING(ROUND(L89*1.07,2),5) ), "" ) -> 12545 | P89: =IF((((Price30[Cost]*1.5)+50)/0.835)<2500, MROUND((((( Price30[Cost]*1.5)+50)/0.835)*1.05)*2,10), MROUND((((( Price30[Cost]*1.5)+50)/0.835)*1.18)*2,10)) -> 38300 | Q89: =IF($S$3="","", MROUND( IF($S$3="m", IF($T$3=1, Price30[[#This Row],[Mrp]]+$W$4, Price30[[#This Row],[Mrp]]+$X$4), IF($S$3="nc", IF($T$3=1, Price30[[#This Row],[Net Cash]]+$W$5, Price30[[#This Row],[Net Cash]]+$X$5), IF($S$3="npc", IF($T$3=1, Price30[[#This Row],[Net Price Credit]]+$W$6, Price30[[#This Row],[Net Price Credit]]+$X$6), IF($S$3="w", IF($T$3=1, Price30[[#This Row],[Wsp]]+$W$6, Price30[[#This Row],[Wsp]]+$X$6), "")))), 10)) -> 16070
B90: 139 | C90: Shawl | D90: Fine Wool | E90: ashwani | F90: kalamkari shawl fabric ankit + embroidery ashwani | G90: 1050 | I90: 4100 | J90: =IF(SUMIF(G90:I90,"<>")=0,"",SUM(G90:I90)) -> 5150 | K90: =IF(ISNUMBER(L90), IF(CEILING(ROUND(L90*0.95,2),5)=420, 425, CEILING(ROUND(L90*0.95,2),5) ), "" ) -> 6365 | L90: =IF(AND(ISNUMBER(J90),ISNUMBER(G90)), IF(CEILING(ROUND(J90*1.3,2),5)=420, 425, CEILING(ROUND(J90*1.3,2),5) ), "" ) -> 6695 | M90: =IF(AND(ISNUMBER(J90),ISNUMBER(G90)), IF( CEILING( ROUND((J90*1.5) * IF(J90*1.5 <= 2500, 1.05, 1.18), 2), IF(ROUND((J90*1.5) * IF(J90*1.5 <= 2500, 1.05, 1.18), 2) < 2500, 25, 50) )=420, 425, CEILING( ROUND((J90*1.5) * IF(J90*1.5 <= 2500, 1.05, 1.18), 2), IF(ROUND((J90*1.5) * IF(J90*1.5 <= 2500, 1.05, 1.18), 2) < 2500, 25, 50) ) ), "" ) -> 9150 | N90: =IF(ISNUMBER(G90), IF(CEILING(ROUND(L90*0.92,2),5)=420, 425, CEILING(ROUND(L90*0.92,2),5) ), "" ) -> 6160 | O90: =IF(ISNUMBER(L90), IF(CEILING(ROUND(L90*1.07,2),5)=420, 425, CEILING(ROUND(L90*1.07,2),5) ), "" ) -> 7165 | P90: =IF((((Price30[Cost]*1.5)+50)/0.835)<2500, MROUND((((( Price30[Cost]*1.5)+50)/0.835)*1.05)*2,10), MROUND((((( Price30[Cost]*1.5)+50)/0.835)*1.18)*2,10)) -> 4090 | Q90: =IF($S$3="","", MROUND( IF($S$3="m", IF($T$3=1, Price30[[#This Row],[Mrp]]+$W$4, Price30[[#This Row],[Mrp]]+$X$4), IF($S$3="nc", IF($T$3=1, Price30[[#This Row],[Net Cash]]+$W$5, Price30[[#This Row],[Net Cash]]+$X$5), IF($S$3="npc", IF($T$3=1, Price30[[#This Row],[Net Price Credit]]+$W$6, Price30[[#This Row],[Net Price Credit]]+$X$6), IF($S$3="w", IF($T$3=1, Price30[[#This Row],[Wsp]]+$W$6, Price30[[#This Row],[Wsp]]+$X$6), "")))), 10)) -> 9220
A91: 2025 | B91: 141 | C91: Shawl | D91: Fine Wool | E91: Ashwani | F91: kalamkari shawl light | G91: 4500 | I91: 25 | J91: =IF(SUMIF(G91:I91,"<>")=0,"",SUM(G91:I91)) -> 4525 | K91: =IF(ISNUMBER(L91), IF(CEILING(ROUND(L91*0.95,2),5)=420, 425, CEILING(ROUND(L91*0.95,2),5) ), "" ) -> 5595 | L91: =IF(AND(ISNUMBER(J91),ISNUMBER(G91)), IF(CEILING(ROUND(J91*1.3,2),5)=420, 425, CEILING(ROUND(J91*1.3,2),5) ), "" ) -> 5885 | M91: =IF(AND(ISNUMBER(J91),ISNUMBER(G91)), IF( CEILING( ROUND((J91*1.5) * IF(J91*1.5 <= 2500, 1.05, 1.18), 2), IF(ROUND((J91*1.5) * IF(J91*1.5 <= 2500, 1.05, 1.18), 2) < 2500, 25, 50) )=420, 425, CEILING( ROUND((J91*1.5) * IF(J91*1.5 <= 2500, 1.05, 1.18), 2), IF(ROUND((J91*1.5) * IF(J91*1.5 <= 2500, 1.05, 1.18), 2) < 2500, 25, 50) ) ), "" ) -> 8050 | N91: =IF(ISNUMBER(G91), IF(CEILING(ROUND(L91*0.92,2),5)=420, 425, CEILING(ROUND(L91*0.92,2),5) ), "" ) -> 5415 | O91: =IF(ISNUMBER(L91), IF(CEILING(ROUND(L91*1.07,2),5)=420, 425, CEILING(ROUND(L91*1.07,2),5) ), "" ) -> 6300 | P91: =IF((((Price30[Cost]*1.5)+50)/0.835)<2500, MROUND((((( Price30[Cost]*1.5)+50)/0.835)*1.05)*2,10), MROUND((((( Price30[Cost]*1.5)+50)/0.835)*1.18)*2,10)) -> 19220 | Q91: =IF($S$3="","", MROUND( IF($S$3="m", IF($T$3=1, Price30[[#This Row],[Mrp]]+$W$4, Price30[[#This Row],[Mrp]]+$X$4), IF($S$3="nc", IF($T$3=1, Price30[[#This Row],[Net Cash]]+$W$5, Price30[[#This Row],[Net Cash]]+$X$5), IF($S$3="npc", IF($T$3=1, Price30[[#This Row],[Net Price Credit]]+$W$6, Price30[[#This Row],[Net Price Credit]]+$X$6), IF($S$3="w", IF($T$3=1, Price30[[#This Row],[Wsp]]+$W$6, Price30[[#This Row],[Wsp]]+$X$6), "")))), 10)) -> 8120
A92: 2026 | B92: 144 | C92: Shawl | D92: Fine Wool | E92: Rajesh | F92: gents hashia 50*100 | G92: 1450 | I92: 25 | J92: =IF(SUMIF(G92:I92,"<>")=0,"",SUM(G92:I92)) -> 1475 | K92: =IF(ISNUMBER(L92), IF(CEILING(ROUND(L92*0.95,2),5)=420, 425, CEILING(ROUND(L92*0.95,2),5) ), "" ) -> 1825 | L92: =IF(AND(ISNUMBER(J92),ISNUMBER(G92)), IF(CEILING(ROUND(J92*1.3,2),5)=420, 425, CEILING(ROUND(J92*1.3,2),5) ), "" ) -> 1920 | M92: =IF(AND(ISNUMBER(J92),ISNUMBER(G92)), IF( CEILING( ROUND((J92*1.5) * IF(J92*1.5 <= 2500, 1.05, 1.18), 2), IF(ROUND((J92*1.5) * IF(J92*1.5 <= 2500, 1.05, 1.18), 2) < 2500, 25, 50) )=420, 425, CEILING( ROUND((J92*1.5) * IF(J92*1.5 <= 2500, 1.05, 1.18), 2), IF(ROUND((J92*1.5) * IF(J92*1.5 <= 2500, 1.05, 1.18), 2) < 2500, 25, 50) ) ), "" ) -> 2325 | N92: =IF(ISNUMBER(G92), IF(CEILING(ROUND(L92*0.92,2),5)=420, 425, CEILING(ROUND(L92*0.92,2),5) ), "" ) -> 1770 | O92: =IF(ISNUMBER(L92), IF(CEILING(ROUND(L92*1.07,2),5)=420, 425, CEILING(ROUND(L92*1.07,2),5) ), "" ) -> 2055 | P92: =IF((((Price30[Cost]*1.5)+50)/0.835)<2500, MROUND((((( Price30[Cost]*1.5)+50)/0.835)*1.05)*2,10), MROUND((((( Price30[Cost]*1.5)+50)/0.835)*1.18)*2,10)) -> 6290 | Q92: =IF($S$3="","", MROUND( IF($S$3="m", IF($T$3=1, Price30[[#This Row],[Mrp]]+$W$4, Price30[[#This Row],[Mrp]]+$X$4), IF($S$3="nc", IF($T$3=1, Price30[[#This Row],[Net Cash]]+$W$5, Price30[[#This Row],[Net Cash]]+$X$5), IF($S$3="npc", IF($T$3=1, Price30[[#This Row],[Net Price Credit]]+$W$6, Price30[[#This Row],[Net Price Credit]]+$X$6), IF($S$3="w", IF($T$3=1, Price30[[#This Row],[Wsp]]+$W$6, Price30[[#This Row],[Wsp]]+$X$6), "")))), 10)) -> 2400
A93: 2026 | B93: 145 | C93: Shawl | D93: Fine Wool | E93: Rajesh | F93: kalamkari shawl | G93: 13000 | I93: 25 | J93: =IF(SUMIF(G93:I93,"<>")=0,"",SUM(G93:I93)) -> 13025 | K93: =IF(ISNUMBER(L93), IF(CEILING(ROUND(L93*0.95,2),5)=420, 425, CEILING(ROUND(L93*0.95,2),5) ), "" ) -> 16090 | L93: =IF(AND(ISNUMBER(J93),ISNUMBER(G93)), IF(CEILING(ROUND(J93*1.3,2),5)=420, 425, CEILING(ROUND(J93*1.3,2),5) ), "" ) -> 16935 | M93: =IF(AND(ISNUMBER(J93),ISNUMBER(G93)), IF( CEILING( ROUND((J93*1.5) * IF(J93*1.5 <= 2500, 1.05, 1.18), 2), IF(ROUND((J93*1.5) * IF(J93*1.5 <= 2500, 1.05, 1.18), 2) < 2500, 25, 50) )=420, 425, CEILING( ROUND((J93*1.5) * IF(J93*1.5 <= 2500, 1.05, 1.18), 2), IF(ROUND((J93*1.5) * IF(J93*1.5 <= 2500, 1.05, 1.18), 2) < 2500, 25, 50) ) ), "" ) -> 23100 | N93: =IF(ISNUMBER(G93), IF(CEILING(ROUND(L93*0.92,2),5)=420, 425, CEILING(ROUND(L93*0.92,2),5) ), "" ) -> 15585 | O93: =IF(ISNUMBER(L93), IF(CEILING(ROUND(L93*1.07,2),5)=420, 425, CEILING(ROUND(L93*1.07,2),5) ), "" ) -> 18125 | P93: =IF((((Price30[Cost]*1.5)+50)/0.835)<2500, MROUND((((( Price30[Cost]*1.5)+50)/0.835)*1.05)*2,10), MROUND((((( Price30[Cost]*1.5)+50)/0.835)*1.18)*2,10)) -> 55260 | Q93: =IF($S$3="","", MROUND( IF($S$3="m", IF($T$3=1, Price30[[#This Row],[Mrp]]+$W$4, Price30[[#This Row],[Mrp]]+$X$4), IF($S$3="nc", IF($T$3=1, Price30[[#This Row],[Net Cash]]+$W$5, Price30[[#This Row],[Net Cash]]+$X$5), IF($S$3="npc", IF($T$3=1, Price30[[#This Row],[Net Price Credit]]+$W$6, Price30[[#This Row],[Net Price Credit]]+$X$6), IF($S$3="w", IF($T$3=1, Price30[[#This Row],[Wsp]]+$W$6, Price30[[#This Row],[Wsp]]+$X$6), "")))), 10)) -> 23170
A94: 2026 | B94: 146 | C94: Shawl | D94: Fine Wool | E94: Rajesh | F94: kalamkari shawl | G94: 16000 | I94: 25 | J94: =IF(SUMIF(G94:I94,"<>")=0,"",SUM(G94:I94)) -> 16025 | K94: =IF(ISNUMBER(L94), IF(CEILING(ROUND(L94*0.95,2),5)=420, 425, CEILING(ROUND(L94*0.95,2),5) ), "" ) -> 19795 | L94: =IF(AND(ISNUMBER(J94),ISNUMBER(G94)), IF(CEILING(ROUND(J94*1.3,2),5)=420, 425, CEILING(ROUND(J94*1.3,2),5) ), "" ) -> 20835 | M94: =IF(AND(ISNUMBER(J94),ISNUMBER(G94)), IF( CEILING( ROUND((J94*1.5) * IF(J94*1.5 <= 2500, 1.05, 1.18), 2), IF(ROUND((J94*1.5) * IF(J94*1.5 <= 2500, 1.05, 1.18), 2) < 2500, 25, 50) )=420, 425, CEILING( ROUND((J94*1.5) * IF(J94*1.5 <= 2500, 1.05, 1.18), 2), IF(ROUND((J94*1.5) * IF(J94*1.5 <= 2500, 1.05, 1.18), 2) < 2500, 25, 50) ) ), "" ) -> 28400 | N94: =IF(ISNUMBER(G94), IF(CEILING(ROUND(L94*0.92,2),5)=420, 425, CEILING(ROUND(L94*0.92,2),5) ), "" ) -> 19170 | O94: =IF(ISNUMBER(L94), IF(CEILING(ROUND(L94*1.07,2),5)=420, 425, CEILING(ROUND(L94*1.07,2),5) ), "" ) -> 22295 | P94: =IF((((Price30[Cost]*1.5)+50)/0.835)<2500, MROUND((((( Price30[Cost]*1.5)+50)/0.835)*1.05)*2,10), MROUND((((( Price30[Cost]*1.5)+50)/0.835)*1.18)*2,10)) -> 67970 | Q94: =IF($S$3="","", MROUND( IF($S$3="m", IF($T$3=1, Price30[[#This Row],[Mrp]]+$W$4, Price30[[#This Row],[Mrp]]+$X$4), IF($S$3="nc", IF($T$3=1, Price30[[#This Row],[Net Cash]]+$W$5, Price30[[#This Row],[Net Cash]]+$X$5), IF($S$3="npc", IF($T$3=1, Price30[[#This Row],[Net Price Credit]]+$W$6, Price30[[#This Row],[Net Price Credit]]+$X$6), IF($S$3="w", IF($T$3=1, Price30[[#This Row],[Wsp]]+$W$6, Price30[[#This Row],[Wsp]]+$X$6), "")))), 10)) -> 28470
A95: 2025 | B95: 147 | C95: shawl | D95: Fine Wool | E95: Rajesh | F95: kalamkari shawl | G95: 18000 | I95: 25 | J95: =IF(SUMIF(G95:I95,"<>")=0,"",SUM(G95:I95)) -> 18025 | K95: =IF(ISNUMBER(L95), IF(CEILING(ROUND(L95*0.95,2),5)=420, 425, CEILING(ROUND(L95*0.95,2),5) ), "" ) -> 22265 | L95: =IF(AND(ISNUMBER(J95),ISNUMBER(G95)), IF(CEILING(ROUND(J95*1.3,2),5)=420, 425, CEILING(ROUND(J95*1.3,2),5) ), "" ) -> 23435 | M95: =IF(AND(ISNUMBER(J95),ISNUMBER(G95)), IF( CEILING( ROUND((J95*1.5) * IF(J95*1.5 <= 2500, 1.05, 1.18), 2), IF(ROUND((J95*1.5) * IF(J95*1.5 <= 2500, 1.05, 1.18), 2) < 2500, 25, 50) )=420, 425, CEILING( ROUND((J95*1.5) * IF(J95*1.5 <= 2500, 1.05, 1.18), 2), IF(ROUND((J95*1.5) * IF(J95*1.5 <= 2500, 1.05, 1.18), 2) < 2500, 25, 50) ) ), "" ) -> 31950 | N95: =IF(ISNUMBER(G95), IF(CEILING(ROUND(L95*0.92,2),5)=420, 425, CEILING(ROUND(L95*0.92,2),5) ), "" ) -> 21565 | O95: =IF(ISNUMBER(L95), IF(CEILING(ROUND(L95*1.07,2),5)=420, 425, CEILING(ROUND(L95*1.07,2),5) ), "" ) -> 25080 | P95: =IF((((Price30[Cost]*1.5)+50)/0.835)<2500, MROUND((((( Price30[Cost]*1.5)+50)/0.835)*1.05)*2,10), MROUND((((( Price30[Cost]*1.5)+50)/0.835)*1.18)*2,10)) -> 76450 | Q95: =IF($S$3="","", MROUND( IF($S$3="m", IF($T$3=1, Price30[[#This Row],[Mrp]]+$W$4, Price30[[#This Row],[Mrp]]+$X$4), IF($S$3="nc", IF($T$3=1, Price30[[#This Row],[Net Cash]]+$W$5, Price30[[#This Row],[Net Cash]]+$X$5), IF($S$3="npc", IF($T$3=1, Price30[[#This Row],[Net Price Credit]]+$W$6, Price30[[#This Row],[Net Price Credit]]+$X$6), IF($S$3="w", IF($T$3=1, Price30[[#This Row],[Wsp]]+$W$6, Price30[[#This Row],[Wsp]]+$X$6), "")))), 10)) -> 32020
A96: 2025 | B96: 148 | C96: shawl | D96: Fine Wool | E96: Rajesh | F96: kalamkari shawl | G96: 19000 | I96: 25 | J96: =IF(SUMIF(G96:I96,"<>")=0,"",SUM(G96:I96)) -> 19025 | K96: =IF(ISNUMBER(L96), IF(CEILING(ROUND(L96*0.95,2),5)=420, 425, CEILING(ROUND(L96*0.95,2),5) ), "" ) -> 23500 | L96: =IF(AND(ISNUMBER(J96),ISNUMBER(G96)), IF(CEILING(ROUND(J96*1.3,2),5)=420, 425, CEILING(ROUND(J96*1.3,2),5) ), "" ) -> 24735 | M96: =IF(AND(ISNUMBER(J96),ISNUMBER(G96)), IF( CEILING( ROUND((J96*1.5) * IF(J96*1.5 <= 2500, 1.05, 1.18), 2), IF(ROUND((J96*1.5) * IF(J96*1.5 <= 2500, 1.05, 1.18), 2) < 2500, 25, 50) )=420, 425, CEILING( ROUND((J96*1.5) * IF(J96*1.5 <= 2500, 1.05, 1.18), 2), IF(ROUND((J96*1.5) * IF(J96*1.5 <= 2500, 1.05, 1.18), 2) < 2500, 25, 50) ) ), "" ) -> 33700 | N96: =IF(ISNUMBER(G96), IF(CEILING(ROUND(L96*0.92,2),5)=420, 425, CEILING(ROUND(L96*0.92,2),5) ), "" ) -> 22760 | O96: =IF(ISNUMBER(L96), IF(CEILING(ROUND(L96*1.07,2),5)=420, 425, CEILING(ROUND(L96*1.07,2),5) ), "" ) -> 26470 | P96: =IF((((Price30[Cost]*1.5)+50)/0.835)<2500, MROUND((((( Price30[Cost]*1.5)+50)/0.835)*1.05)*2,10), MROUND((((( Price30[Cost]*1.5)+50)/0.835)*1.18)*2,10)) -> 80690 | Q96: =IF($S$3="","", MROUND( IF($S$3="m", IF($T$3=1, Price30[[#This Row],[Mrp]]+$W$4, Price30[[#This Row],[Mrp]]+$X$4), IF($S$3="nc", IF($T$3=1, Price30[[#This Row],[Net Cash]]+$W$5, Price30[[#This Row],[Net Cash]]+$X$5), IF($S$3="npc", IF($T$3=1, Price30[[#This Row],[Net Price Credit]]+$W$6, Price30[[#This Row],[Net Price Credit]]+$X$6), IF($S$3="w", IF($T$3=1, Price30[[#This Row],[Wsp]]+$W$6, Price30[[#This Row],[Wsp]]+$X$6), "")))), 10)) -> 33770
A97: 2026 | B97: 149 | C97: shawl | D97: Fine Wool | E97: Gaurav | F97: 25093 & 26084 | G97: 3935 | I97: 25 | J97: =IF(SUMIF(G97:I97,"<>")=0,"",SUM(G97:I97)) -> 3960 | K97: =IF(ISNUMBER(L97), IF(CEILING(ROUND(L97*0.95,2),5)=420, 425, CEILING(ROUND(L97*0.95,2),5) ), "" ) -> 4895 | L97: =IF(AND(ISNUMBER(J97),ISNUMBER(G97)), IF(CEILING(ROUND(J97*1.3,2),5)=420, 425, CEILING(ROUND(J97*1.3,2),5) ), "" ) -> 5150 | M97: =IF(AND(ISNUMBER(J97),ISNUMBER(G97)), IF( CEILING( ROUND((J97*1.5) * IF(J97*1.5 <= 2500, 1.05, 1.18), 2), IF(ROUND((J97*1.5) * IF(J97*1.5 <= 2500, 1.05, 1.18), 2) < 2500, 25, 50) )=420, 425, CEILING( ROUND((J97*1.5) * IF(J97*1.5 <= 2500, 1.05, 1.18), 2), IF(ROUND((J97*1.5) * IF(J97*1.5 <= 2500, 1.05, 1.18), 2) < 2500, 25, 50) ) ), "" ) -> 7050 | N97: =IF(ISNUMBER(G97), IF(CEILING(ROUND(L97*0.92,2),5)=420, 425, CEILING(ROUND(L97*0.92,2),5) ), "" ) -> 4740 | O97: =IF(ISNUMBER(L97), IF(CEILING(ROUND(L97*1.07,2),5)=420, 425, CEILING(ROUND(L97*1.07,2),5) ), "" ) -> 5515 | P97: =IF((((Price30[Cost]*1.5)+50)/0.835)<2500, MROUND((((( Price30[Cost]*1.5)+50)/0.835)*1.05)*2,10), MROUND((((( Price30[Cost]*1.5)+50)/0.835)*1.18)*2,10)) -> 16820 | Q97: =IF($S$3="","", MROUND( IF($S$3="m", IF($T$3=1, Price30[[#This Row],[Mrp]]+$W$4, Price30[[#This Row],[Mrp]]+$X$4), IF($S$3="nc", IF($T$3=1, Price30[[#This Row],[Net Cash]]+$W$5, Price30[[#This Row],[Net Cash]]+$X$5), IF($S$3="npc", IF($T$3=1, Price30[[#This Row],[Net Price Credit]]+$W$6, Price30[[#This Row],[Net Price Credit]]+$X$6), IF($S$3="w", IF($T$3=1, Price30[[#This Row],[Wsp]]+$W$6, Price30[[#This Row],[Wsp]]+$X$6), "")))), 10)) -> 7120
A98: 2026 | B98: 151 | C98: shawl | D98: Fine Wool | E98: Gaurav | F98: 26085 & 26086 | G98: 3745 | I98: 25 | J98: =IF(SUMIF(G98:I98,"<>")=0,"",SUM(G98:I98)) -> 3770 | K98: =IF(ISNUMBER(L98), IF(CEILING(ROUND(L98*0.95,2),5)=420, 425, CEILING(ROUND(L98*0.95,2),5) ), "" ) -> 4660 | L98: =IF(AND(ISNUMBER(J98),ISNUMBER(G98)), IF(CEILING(ROUND(J98*1.3,2),5)=420, 425, CEILING(ROUND(J98*1.3,2),5) ), "" ) -> 4905 | M98: =IF(AND(ISNUMBER(J98),ISNUMBER(G98)), IF( CEILING( ROUND((J98*1.5) * IF(J98*1.5 <= 2500, 1.05, 1.18), 2), IF(ROUND((J98*1.5) * IF(J98*1.5 <= 2500, 1.05, 1.18), 2) < 2500, 25, 50) )=420, 425, CEILING( ROUND((J98*1.5) * IF(J98*1.5 <= 2500, 1.05, 1.18), 2), IF(ROUND((J98*1.5) * IF(J98*1.5 <= 2500, 1.05, 1.18), 2) < 2500, 25, 50) ) ), "" ) -> 6700 | N98: =IF(ISNUMBER(G98), IF(CEILING(ROUND(L98*0.92,2),5)=420, 425, CEILING(ROUND(L98*0.92,2),5) ), "" ) -> 4515 | O98: =IF(ISNUMBER(L98), IF(CEILING(ROUND(L98*1.07,2),5)=420, 425, CEILING(ROUND(L98*1.07,2),5) ), "" ) -> 5250 | P98: =IF((((Price30[Cost]*1.5)+50)/0.835)<2500, MROUND((((( Price30[Cost]*1.5)+50)/0.835)*1.05)*2,10), MROUND((((( Price30[Cost]*1.5)+50)/0.835)*1.18)*2,10)) -> 16020 | Q98: =IF($S$3="","", MROUND( IF($S$3="m", IF($T$3=1, Price30[[#This Row],[Mrp]]+$W$4, Price30[[#This Row],[Mrp]]+$X$4), IF($S$3="nc", IF($T$3=1, Price30[[#This Row],[Net Cash]]+$W$5, Price30[[#This Row],[Net Cash]]+$X$5), IF($S$3="npc", IF($T$3=1, Price30[[#This Row],[Net Price Credit]]+$W$6, Price30[[#This Row],[Net Price Credit]]+$X$6), IF($S$3="w", IF($T$3=1, Price30[[#This Row],[Wsp]]+$W$6, Price30[[#This Row],[Wsp]]+$X$6), "")))), 10)) -> 6770
A99: 2026 | B99: 152 | C99: shawl | D99: Fine Wool | E99: Gaurav | F99: 26082 | G99: 3640 | I99: 25 | J99: =IF(SUMIF(G99:I99,"<>")=0,"",SUM(G99:I99)) -> 3665 | K99: =IF(ISNUMBER(L99), IF(CEILING(ROUND(L99*0.95,2),5)=420, 425, CEILING(ROUND(L99*0.95,2),5) ), "" ) -> 4530 | L99: =IF(AND(ISNUMBER(J99),ISNUMBER(G99)), IF(CEILING(ROUND(J99*1.3,2),5)=420, 425, CEILING(ROUND(J99*1.3,2),5) ), "" ) -> 4765 | M99: =IF(AND(ISNUMBER(J99),ISNUMBER(G99)), IF( CEILING( ROUND((J99*1.5) * IF(J99*1.5 <= 2500, 1.05, 1.18), 2), IF(ROUND((J99*1.5) * IF(J99*1.5 <= 2500, 1.05, 1.18), 2) < 2500, 25, 50) )=420, 425, CEILING( ROUND((J99*1.5) * IF(J99*1.5 <= 2500, 1.05, 1.18), 2), IF(ROUND((J99*1.5) * IF(J99*1.5 <= 2500, 1.05, 1.18), 2) < 2500, 25, 50) ) ), "" ) -> 6500 | N99: =IF(ISNUMBER(G99), IF(CEILING(ROUND(L99*0.92,2),5)=420, 425, CEILING(ROUND(L99*0.92,2),5) ), "" ) -> 4385 | O99: =IF(ISNUMBER(L99), IF(CEILING(ROUND(L99*1.07,2),5)=420, 425, CEILING(ROUND(L99*1.07,2),5) ), "" ) -> 5100 | P99: =IF((((Price30[Cost]*1.5)+50)/0.835)<2500, MROUND((((( Price30[Cost]*1.5)+50)/0.835)*1.05)*2,10), MROUND((((( Price30[Cost]*1.5)+50)/0.835)*1.18)*2,10)) -> 15570 | Q99: =IF($S$3="","", MROUND( IF($S$3="m", IF($T$3=1, Price30[[#This Row],[Mrp]]+$W$4, Price30[[#This Row],[Mrp]]+$X$4), IF($S$3="nc", IF($T$3=1, Price30[[#This Row],[Net Cash]]+$W$5, Price30[[#This Row],[Net Cash]]+$X$5), IF($S$3="npc", IF($T$3=1, Price30[[#This Row],[Net Price Credit]]+$W$6, Price30[[#This Row],[Net Price Credit]]+$X$6), IF($S$3="w", IF($T$3=1, Price30[[#This Row],[Wsp]]+$W$6, Price30[[#This Row],[Wsp]]+$X$6), "")))), 10)) -> 6570
A100: 2026 | B100: 153 | C100: shawl | D100: Fine Wool | E100: Gaurav | F100: 26087 & 23012 | G100: 3000 | I100: 25 | J100: =IF(SUMIF(G100:I100,"<>")=0,"",SUM(G100:I100)) -> 3025 | K100: =IF(ISNUMBER(L100), IF(CEILING(ROUND(L100*0.95,2),5)=420, 425, CEILING(ROUND(L100*0.95,2),5) ), "" ) -> 3740 | L100: =IF(AND(ISNUMBER(J100),ISNUMBER(G100)), IF(CEILING(ROUND(J100*1.3,2),5)=420, 425, CEILING(ROUND(J100*1.3,2),5) ), "" ) -> 3935 | M100: =IF(AND(ISNUMBER(J100),ISNUMBER(G100)), IF( CEILING( ROUND((J100*1.5) * IF(J100*1.5 <= 2500, 1.05, 1.18), 2), IF(ROUND((J100*1.5) * IF(J100*1.5 <= 2500, 1.05, 1.18), 2) < 2500, 25, 50) )=420, 425, CEILING( ROUND((J100*1.5) * IF(J100*1.5 <= 2500, 1.05, 1.18), 2), IF(ROUND((J100*1.5) * IF(J100*1.5 <= 2500, 1.05, 1.18), 2) < 2500, 25, 50) ) ), "" ) -> 5400 | N100: =IF(ISNUMBER(G100), IF(CEILING(ROUND(L100*0.92,2),5)=420, 425, CEILING(ROUND(L100*0.92,2),5) ), "" ) -> 3625 | O100: =IF(ISNUMBER(L100), IF(CEILING(ROUND(L100*1.07,2),5)=420, 425, CEILING(ROUND(L100*1.07,2),5) ), "" ) -> 4215 | P100: =IF((((Price30[Cost]*1.5)+50)/0.835)<2500, MROUND((((( Price30[Cost]*1.5)+50)/0.835)*1.05)*2,10), MROUND((((( Price30[Cost]*1.5)+50)/0.835)*1.18)*2,10)) -> 12860 | Q100: =IF($S$3="","", MROUND( IF($S$3="m", IF($T$3=1, Price30[[#This Row],[Mrp]]+$W$4, Price30[[#This Row],[Mrp]]+$X$4), IF($S$3="nc", IF($T$3=1, Price30[[#This Row],[Net Cash]]+$W$5, Price30[[#This Row],[Net Cash]]+$X$5), IF($S$3="npc", IF($T$3=1, Price30[[#This Row],[Net Price Credit]]+$W$6, Price30[[#This Row],[Net Price Credit]]+$X$6), IF($S$3="w", IF($T$3=1, Price30[[#This Row],[Wsp]]+$W$6, Price30[[#This Row],[Wsp]]+$X$6), "")))), 10)) -> 5470
A101: 2026 | B101: 154 | C101: shawl | D101: Fine Wool | E101: Gaurav | F101: 25085 | G101: 3420 | I101: 25 | J101: =IF(SUMIF(G101:I101,"<>")=0,"",SUM(G101:I101)) -> 3445 | K101: =IF(ISNUMBER(L101), IF(CEILING(ROUND(L101*0.95,2),5)=420, 425, CEILING(ROUND(L101*0.95,2),5) ), "" ) -> 4260 | L101: =IF(AND(ISNUMBER(J101),ISNUMBER(G101)), IF(CEILING(ROUND(J101*1.3,2),5)=420, 425, CEILING(ROUND(J101*1.3,2),5) ), "" ) -> 4480 | M101: =IF(AND(ISNUMBER(J101),ISNUMBER(G101)), IF( CEILING( ROUND((J101*1.5) * IF(J101*1.5 <= 2500, 1.05, 1.18), 2), IF(ROUND((J101*1.5) * IF(J101*1.5 <= 2500, 1.05, 1.18), 2) < 2500, 25, 50) )=420, 425, CEILING( ROUND((J101*1.5) * IF(J101*1.5 <= 2500, 1.05, 1.18), 2), IF(ROUND((J101*1.5) * IF(J101*1.5 <= 2500, 1.05, 1.18), 2) < 2500, 25, 50) ) ), "" ) -> 6100 | N101: =IF(ISNUMBER(G101), IF(CEILING(ROUND(L101*0.92,2),5)=420, 425, CEILING(ROUND(L101*0.92,2),5) ), "" ) -> 4125 | O101: =IF(ISNUMBER(L101), IF(CEILING(ROUND(L101*1.07,2),5)=420, 425, CEILING(ROUND(L101*1.07,2),5) ), "" ) -> 4795 | P101: =IF((((Price30[Cost]*1.5)+50)/0.835)<2500, MROUND((((( Price30[Cost]*1.5)+50)/0.835)*1.05)*2,10), MROUND((((( Price30[Cost]*1.5)+50)/0.835)*1.18)*2,10)) -> 14640 | Q101: =IF($S$3="","", MROUND( IF($S$3="m", IF($T$3=1, Price30[[#This Row],[Mrp]]+$W$4, Price30[[#This Row],[Mrp]]+$X$4), IF($S$3="nc", IF($T$3=1, Price30[[#This Row],[Net Cash]]+$W$5, Price30[[#This Row],[Net Cash]]+$X$5), IF($S$3="npc", IF($T$3=1, Price30[[#This Row],[Net Price Credit]]+$W$6, Price30[[#This Row],[Net Price Credit]]+$X$6), IF($S$3="w", IF($T$3=1, Price30[[#This Row],[Wsp]]+$W$6, Price30[[#This Row],[Wsp]]+$X$6), "")))), 10)) -> 6170
A102: 2026 | B102: 155 | C102: shawl | D102: Fine Wool | E102: Subhash | F102: Silky Jamma | G102: 11500 | I102: 25 | J102: =IF(SUMIF(G102:I102,"<>")=0,"",SUM(G102:I102)) -> 11525 | K102: =IF(ISNUMBER(L102), IF(CEILING(ROUND(L102*0.95,2),5)=420, 425, CEILING(ROUND(L102*0.95,2),5) ), "" ) -> 14240 | L102: =IF(AND(ISNUMBER(J102),ISNUMBER(G102)), IF(CEILING(ROUND(J102*1.3,2),5)=420, 425, CEILING(ROUND(J102*1.3,2),5) ), "" ) -> 14985 | M102: =IF(AND(ISNUMBER(J102),ISNUMBER(G102)), IF( CEILING( ROUND((J102*1.5) * IF(J102*1.5 <= 2500, 1.05, 1.18), 2), IF(ROUND((J102*1.5) * IF(J102*1.5 <= 2500, 1.05, 1.18), 2) < 2500, 25, 50) )=420, 425, CEILING( ROUND((J102*1.5) * IF(J102*1.5 <= 2500, 1.05, 1.18), 2), IF(ROUND((J102*1.5) * IF(J102*1.5 <= 2500, 1.05, 1.18), 2) < 2500, 25, 50) ) ), "" ) -> 20400 | N102: =IF(ISNUMBER(G102), IF(CEILING(ROUND(L102*0.92,2),5)=420, 425, CEILING(ROUND(L102*0.92,2),5) ), "" ) -> 13790 | O102: =IF(ISNUMBER(L102), IF(CEILING(ROUND(L102*1.07,2),5)=420, 425, CEILING(ROUND(L102*1.07,2),5) ), "" ) -> 16035 | P102: =IF((((Price30[Cost]*1.5)+50)/0.835)<2500, MROUND((((( Price30[Cost]*1.5)+50)/0.835)*1.05)*2,10), MROUND((((( Price30[Cost]*1.5)+50)/0.835)*1.18)*2,10)) -> 48900 | Q102: =IF($S$3="","", MROUND( IF($S$3="m", IF($T$3=1, Price30[[#This Row],[Mrp]]+$W$4, Price30[[#This Row],[Mrp]]+$X$4), IF($S$3="nc", IF($T$3=1, Price30[[#This Row],[Net Cash]]+$W$5, Price30[[#This Row],[Net Cash]]+$X$5), IF($S$3="npc", IF($T$3=1, Price30[[#This Row],[Net Price Credit]]+$W$6, Price30[[#This Row],[Net Price Credit]]+$X$6), IF($S$3="w", IF($T$3=1, Price30[[#This Row],[Wsp]]+$W$6, Price30[[#This Row],[Wsp]]+$X$6), "")))), 10)) -> 20470
A103: 2026 | B103: 190 | C103: Lohi | D103: polywool | E103: ankur | F103: 2/72 polywool 360 gm | G103: 450 | I103: 50 | J103: =IF(SUMIF(G103:I103,"<>")=0,"",SUM(G103:I103)) -> 500 | K103: =IF(ISNUMBER(L103), IF(CEILING(ROUND(L103*0.95,2),5)=420, 425, CEILING(ROUND(L103*0.95,2),5) ), "" ) -> 620 | L103: =IF(AND(ISNUMBER(J103),ISNUMBER(G103)), IF(CEILING(ROUND(J103*1.3,2),5)=420, 425, CEILING(ROUND(J103*1.3,2),5) ), "" ) -> 650 | M103: =IF(AND(ISNUMBER(J103),ISNUMBER(G103)), IF( CEILING( ROUND((J103*1.5) * IF(J103*1.5 <= 2500, 1.05, 1.18), 2), IF(ROUND((J103*1.5) * IF(J103*1.5 <= 2500, 1.05, 1.18), 2) < 2500, 25, 50) )=420, 425, CEILING( ROUND((J103*1.5) * IF(J103*1.5 <= 2500, 1.05, 1.18), 2), IF(ROUND((J103*1.5) * IF(J103*1.5 <= 2500, 1.05, 1.18), 2) < 2500, 25, 50) ) ), "" ) -> 800 | N103: =IF(ISNUMBER(G103), IF(CEILING(ROUND(L103*0.92,2),5)=420, 425, CEILING(ROUND(L103*0.92,2),5) ), "" ) -> 600 | O103: =IF(ISNUMBER(L103), IF(CEILING(ROUND(L103*1.07,2),5)=420, 425, CEILING(ROUND(L103*1.07,2),5) ), "" ) -> 700 | P103: =IF((((Price30[Cost]*1.5)+50)/0.835)<2500, MROUND((((( Price30[Cost]*1.5)+50)/0.835)*1.05)*2,10), MROUND((((( Price30[Cost]*1.5)+50)/0.835)*1.18)*2,10)) -> 1820 | Q103: =IF($S$3="","", MROUND( IF($S$3="m", IF($T$3=1, Price30[[#This Row],[Mrp]]+$W$4, Price30[[#This Row],[Mrp]]+$X$4), IF($S$3="nc", IF($T$3=1, Price30[[#This Row],[Net Cash]]+$W$5, Price30[[#This Row],[Net Cash]]+$X$5), IF($S$3="npc", IF($T$3=1, Price30[[#This Row],[Net Price Credit]]+$W$6, Price30[[#This Row],[Net Price Credit]]+$X$6), IF($S$3="w", IF($T$3=1, Price30[[#This Row],[Wsp]]+$W$6, Price30[[#This Row],[Wsp]]+$X$6), "")))), 10)) -> 870
...

Sheet Full Price List
A1: Yom | B1: Art no. | C1: Item | D1: Quality | E1: Supplier | F1: Description | G1: Cost | H1: Increase | I1: Expenses | J1: Total Cost | K1: Net Price Credit | L1: Wsp | M1: Mrp | N1: Net Cash | O1: South | P1: Amazon
A2: 2025 | B2: 120 | C2: Lohi | D2: polywool | E2: m.r | F2: self lohi m.r | G2: 540 | I2: 25 | J2: 565 | K2: 675 | L2: 710 | M2: 900 | N2: 655 | O2: 760 | P2: 2160
B3: 121 | C3: Lohi | D3: Fine Wool | E3: Gaurav | F3: gents KANI GW jal pure | G3: 3350 | I3: 15 | J3: 3365 | K3: 4160 | L3: 4375 | M3: 6000 | N3: 4025 | O3: 4685 | P3: 14340
B4: 122 | C4: Lohi | D4: Fine Wool | E4: Maya | F4: gents kani polywool maya | G4: 1150 | I4: 15 | J4: 1165 | K4: 1440 | L4: 1515 | M4: 1850 | N4: 1395 | O4: 1625 | P4: 4460
A5: 2026 | B5: 123 | C5: Lohi | D5: Fine Wool | E5: Dh | F5: gents kani d.h | G5: 1525 | H5: 5 | I5: 15 | J5: 1545 | K5: 1910 | L5: 2010 | M5: 2450 | N5: 1850 | O5: 2155 | P5: 6610
A6: 2025 | B6: 127 | C6: Lohi | D6: Fine Wool | E6: m.r | F6: kunj lohi kani | G6: 1100 | I6: 15 | J6: 1115 | K6: 1380 | L6: 1450 | M6: 1775 | N6: 1335 | O6: 1555 | P6: 4280
A7: 2026 | B7: 150 | C7: Lohi | D7: Fine Wool | E7: ankur | F7: fine wool 270 gm | G7: 970 | H7: 300 | I7: 60 | J7: 1330 | K7: 1710 | L7: 1800 | M7: 2100 | N7: 1660 | O7: 1930 | P7: 3790
A8: 2026 | B8: 170 | C8: Lohi | D8: Fine Wool | F8: toosha gents plain 350 gm | G8: 980 | H8: 170 | I8: 60 | J8: 1210 | K8: 1555 | L8: 1635 | M8: 1925 | N8: 1505 | O8: 1750 | P8: 3820
A9: 2026 | B9: 190 | C9: Lohi | D9: polywool | E9: ankur | F9: 2/72 polywool 360 gm | G9: 450 | I9: 50 | J9: 500 | K9: 620 | L9: 650 | M9: 800 | N9: 600 | O9: 700 | P9: 1820
A10: 2026 | B10: 191 | C10: Lohi | D10: poywool | E10: wooemb | F10: lohi check wool emb. | G10: 725 | I10: 25 | J10: 750 | K10: 930 | L10: 975 | M10: 1200 | N10: 900 | O10: 1045 | P10: 2860
A11: 2026 | B11: 192 | C11: Lohi | D11: polywool | E11: m.r | F11: check lohi | G11: 545 | H11: -55 | I11: 25 | J11: 515 | K11: 615 | L11: 645 | M11: 825 | N11: 595 | O11: 695 | P11: 2180
B12: 193 | C12: Lohi | D12: Fine Wool | E12: gaurav | F12: 120 count fine wool lohi | G12: 2500 | I12: 25 | J12: 2525 | K12: 3240 | L12: 3410 | M12: 4500 | N12: 3140 | O12: 3650 | P12: 10740
A13: 2026 | B13: 194 | C13: Lohi | D13: Fine Wool | E13: m.r | F13: check lohi fine wool | G13: 1250 | I13: 25 | J13: 1275 | K13: 1520 | L13: 1595 | M13: 2025 | N13: 1470 | O13: 1710 | P13: 4840
A14: 2026 | B14: 275 | C14: Lohi | D14: Polywool | E14: Ps Mehra | F14: paras | G14: 203 | I14: 10 | J14: 213 | K14: 260 | L14: 270 | M14: 350 | N14: 250 | O14: 290 | P14: 890
A15: 2025 | B15: 276 | C15: Lohi | D15: Polywool | E15: Ps Mehra | F15: jannayak | G15: 130 | I15: 10 | J15: 140 | K15: 170 | L15: 175 | M15: 225 | N15: 165 | O15: 190 | P15: 620
A16: 2026 | B16: 402 | C16: Lohi | D16: print lohi | F16: print lohi b.k.sabharwal | G16: 205 | I16: 15 | J16: 220 | K16: 265 | L16: 275 | M16: 350 | N16: 255 | O16: 295 | P16: 900
B17: 406 | C17: Lohi | D17: Polywool | E17: Rama krishna | F17: 3019 | G17: 120 | I17: 15 | J17: 135 | K17: 165 | L17: 170 | M17: 225 | N17: 160 | O17: 185 | P17: 580
A18: 2026 | B18: 444 | C18: Lohi | D18: Polywool | E18: sewa singh | F18: P/V Lohi 400 gm | G18: 100 | I18: 25 | J18: 125 | K18: 155 | L18: 160 | M18: 200 | N18: 150 | O18: 175 | P18: 500
B19: 472 | C19: Lohi | D19: Polywool | E19: Rama krishna | F19: 3006 | G19: 185 | I19: 10 | J19: 195 | K19: 235 | L19: 245 | M19: 325 | N19: 230 | O19: 265 | P19: 820
A20: 2026 | B20: 550 | C20: Lohi | D20: Polywool | E20: h.r | F20: rubru lohi 500 gm | G20: 280 | I20: 20 | J20: 300 | K20: 360 | L20: 375 | M20: 475 | N20: 345 | O20: 405 | P20: 1180
A21: 2026 | B21: 555 | C21: Lohi | D21: Polywool | E21: h.r | F21: p/v mixture | G21: 125 | I21: 35 | J21: 160 | K21: 190 | L21: 200 | M21: 275 | N21: 185 | O21: 215 | P21: 600
A22: 2026 | B22: 666 | C22: Lohi | D22: Polywool | F22: P/A lohi 600 gm mixture | G22: 150 | I22: 35 | J22: 185 | K22: 225 | L22: 235 | M22: 300 | N22: 220 | O22: 255 | P22: 690
B23: 710 | C23: Lohi | D23: wool | F23: 45*90 gents | G23: 340 | I23: 50 | J23: 390 | K23: 505 | L23: 530 | M23: 625 | N23: 490 | O23: 570 | P23: 1410
A24: 2026 | B24: 747 | C24: Lohi | D24: polywool | E24: BM GUPTA | F24: day night lohi | G24: 400 | I24: 15 | J24: 415 | K24: 495 | L24: 520 | M24: 675 | N24: 480 | O24: 560 | P24: 1630
A25: 2026 | B25: 749 | C25: Lohi | D25: Polywool | F25: s.s lohi 570 gm gurdeep | G25: 295 | I25: 25 | J25: 320 | K25: 380 | L25: 400 | M25: 525 | N25: 370 | O25: 430 | P25: 1240
A26: 2026 | B26: 751 | C26: Lohi | D26: Polywool | F26: 450 gm s.s lohi nagpal | G26: 235 | I26: 25 | J26: 260 | K26: 310 | L26: 325 | M26: 425 | N26: 300 | O26: 350 | P26: 1010
A27: 2025 | B27: 761 | C27: Lohi | D27: export lohi | E27: jagdish weaving | F27: export lohi 700 gms cream print | G27: 192 | I27: 15 | J27: 207 | K27: 260 | L27: 270 | M27: 350 | N27: 250 | O27: 290 | P27: 850
A28: 2025 | B28: 762 | C28: Lohi | D28: export lohi | E28: jagdish weaving | F28: export lohi 730 gms cdf print | G28: 190 | I28: 15 | J28: 205 | K28: 260 | L28: 270 | M28: 325 | N28: 250 | O28: 290 | P28: 840
A29: 2026 | B29: 888 | C29: Lohi | D29: Polywool | F29: lohi p/v 800 gm jay dee with bag 275/- kg | G29: 210 | I29: 50 | J29: 260 | K29: 310 | L29: 325 | M29: 425 | N29: 300 | O29: 350 | P29: 920
A30: 2026 | B30: 910 | C30: Lohi | D30: wool | F30: malida | G30: 500 | I30: 100 | J30: 600 | K30: 770 | L30: 810 | M30: 950 | N30: 750 | O30: 870 | P30: 2010
A31: 2026 | B31: 1000 | C31: Lohi | D31: wool | F31: ramayan lohi jay dee 80 x 20 | G31: 693 | I31: 15 | J31: 708 | K31: 915 | L31: 960 | M31: 1125 | N31: 885 | O31: 1030 | P31: 2740
B32: 1010 | C32: Lohi | D32: wool | F32: malida 10 no. | G32: 480 | I32: 80 | J32: 560 | K32: 725 | L32: 760 | M32: 900 | N32: 700 | O32: 815 | P32: 1940
A33: 2026 | B33: 1111 | C33: Lohi | D33: Polywool | F33: P/A LOHI 1000 GM with bag | G33: 270 | I33: 50 | J33: 320 | K33: 380 | L33: 400 | M33: 525 | N33: 370 | O33: 430 | P33: 1140
B34: 1200 | C34: Lohi | D34: polywool | F34: toosh polywool h.r 700 gm | G34: 630 | I34: 15 | J34: 645 | K34: 770 | L34: 810 | M34: 1025 | N34: 750 | O34: 870 | P34: 2500
A35: 2025 | B35: 1211 | C35: Lohi | D35: Fine Wool | E35: Gaurav | F35: gents kani jal polywool | G35: 1960 | I35: 15 | J35: 1975 | K35: 2445 | L35: 2570 | M35: 3500 | N35: 2365 | O35: 2750 | P35: 8450
A36: 2025 | B36: 1212 | C36: Lohi | D36: Fine Wool | E36: Gaurav | F36: gents kani palla polywool | G36: 1405 | I36: 15 | J36: 1420 | K36: 1760 | L36: 1850 | M36: 2250 | N36: 1705 | O36: 1980 | P36: 6100
A37: 2025 | B37: 1213 | C37: Lohi | D37: Fine Wool | E37: Gaurav | F37: gents kani dour polywool | G37: 1860 | I37: 15 | J37: 1875 | K37: 2320 | L37: 2440 | M37: 3350 | N37: 2245 | O37: 2615 | P37: 8030
A38: 2025 | B38: 1214 | C38: lohi | D38: Fine Wool | E38: Sanjay trading | F38: genta kani 15035 | G38: 2700 | I38: 25 | J38: 2725 | K38: 3370 | L38: 3545 | M38: 4850 | N38: 3265 | O38: 3795 | P38: 11590
A39: 2026 | B39: 1400 | C39: Lohi | D39: polywool | E39: sewa singh | F39: P/A Lohi 700 gm mixture lohi | G39: 175 | I39: 35 | J39: 210 | K39: 255 | L39: 265 | M39: 350 | N39: 245 | O39: 285 | P39: 790
A40: 2025 | B40: 1600 | C40: Lohi | D40: polywool | F40: Karthike Lohi 500 gm international | G40: 285 | I40: 15 | J40: 300 | K40: 360 | L40: 375 | M40: 475 | N40: 345 | O40: 405 | P40: 1200
A41: 2026 | B41: 1651 | C41: Lohi | D41: wool | E41: international | F41: malida 1651 no.pure wool 450 gm | G41: 881 | I41: 25 | J41: 906 | K41: 1165 | L41: 1225 | M41: 1450 | N41: 1130 | O41: 1315 | P41: 3450
A42: 2025 | B42: 1800 | C42: Lohi | D42: polywool | F42: jashan lohi 900 gm international | G42: 435 | I42: 15 | J42: 450 | K42: 540 | L42: 565 | M42: 725 | N42: 520 | O42: 605 | P42: 1770
A43: 2026 | B43: 2010 | C43: Lohi | D43: polywool | E43: international | F43: polywool lohi international shivam | G43: 554 | I43: 15 | J43: 569 | K43: 680 | L43: 715 | M43: 900 | N43: 660 | O43: 770 | P43: 2220
A44: 2025 | B44: 2011 | C44: Lohi | D44: polywool | E44: h.r | F44: orange lohi h.r | G44: 550 | I44: 15 | J44: 565 | K44: 675 | L44: 710 | M44: 900 | N44: 655 | O44: 760 | P44: 2200
A45: 2026 | B45: 2400 | C45: Lohi | D45: wool | F45: lohi govinda 80 x 20 jay dee | G45: 936 | I45: 15 | J45: 951 | K45: 1225 | L45: 1285 | M45: 1500 | N45: 1185 | O45: 1375 | P45: 3660
A46: 2026 | B46: 2451 | C46: Lohi | D46: wool | E46: international | F46: malida 2451 no. pure wool 650gm | G46: 1303 | I46: 25 | J46: 1328 | K46: 1710 | L46: 1795 | M46: 2100 | N46: 1655 | O46: 1925 | P46: 5040
A47: 2025 | B47: 2751 | C47: Lohi | D47: Polywool | E47: Ps Mehra | F47: vikrant | G47: 142 | I47: 10 | J47: 152 | K47: 185 | L47: 190 | M47: 250 | N47: 175 | O47: 205 | P47: 660
A48: 2026 | B48: 2752 | C48: Lohi | D48: Polywool | E48: Ps Mehra | F48: akshay | G48: 169 | I48: 10 | J48: 179 | K48: 215 | L48: 225 | M48: 300 | N48: 210 | O48: 245 | P48: 760
A49: 2026 | B49: 2753 | C49: Lohi | D49: Polywool | E49: Ps Mehra | F49: manyavar | G49: 245 | I49: 10 | J49: 255 | K49: 305 | L49: 320 | M49: 425 | N49: 295 | O49: 345 | P49: 1050
A50: 2026 | B50: 2754 | C50: Lohi | D50: Polywool | E50: Ps Mehra | F50: danveer | G50: 134 | I50: 10 | J50: 144 | K50: 175 | L50: 180 | M50: 250 | N50: 170 | O50: 195 | P50: 630
A51: 2025 | B51: 2755 | C51: Lohi | D51: Polywool | E51: Ps Mehra | F51: sambandh | G51: 145 | I51: 10 | J51: 155 | K51: 190 | L51: 195 | M51: 250 | N51: 180 | O51: 210 | P51: 670
A52: 2025 | B52: 2756 | C52: Lohi | D52: Polywool | E52: Ps Mehra | F52: mahavtar | G52: 108 | I52: 10 | J52: 118 | K52: 145 | L52: 150 | M52: 200 | N52: 140 | O52: 165 | P52: 530
A53: 2026 | B53: 2757 | C53: Lohi | D53: Polywool | E53: Ps Mehra | F53: bahuballi | G53: 115 | I53: 10 | J53: 125 | K53: 155 | L53: 160 | M53: 200 | N53: 150 | O53: 175 | P53: 560
A54: 2025 | B54: 2758 | C54: Lohi | D54: Polywool | E54: Ps Mehra | F54: samrat | G54: 99 | I54: 10 | J54: 109 | K54: 135 | L54: 140 | M54: 175 | N54: 130 | O54: 150 | P54: 500
A55: 2026 | B55: 2759 | C55: Lohi | D55: Polywool | E55: Ps Mehra | F55: bharat | G55: 144 | I55: 10 | J55: 154 | K55: 190 | L55: 195 | M55: 250 | N55: 180 | O55: 210 | P55: 670
A56: 2025 | B56: 2760 | C56: Lohi | D56: Polywool | E56: Ps Mehra | F56: mla | G56: 145 | I56: 10 | J56: 155 | K56: 190 | L56: 195 | M56: 250 | N56: 180 | O56: 210 | P56: 670
A57: 2026 | B57: 2766 | C57: Lohi | D57: Polywool | E57: Ps Mehra | F57: kuber | G57: 142 | I57: 10 | J57: 152 | K57: 185 | L57: 190 | M57: 250 | N57: 175 | O57: 205 | P57: 660
B58: 4502 | C58: Lohi | D58: Polywool | E58: hemant | F58: chairman | G58: 170 | I58: 10 | J58: 180 | K58: 215 | L58: 225 | M58: 300 | N58: 210 | O58: 245 | P58: 770
B59: 4503 | C59: Lohi | D59: Polywool | E59: hemant | F59: orchid | G59: 116 | I59: 10 | J59: 126 | K59: 155 | L59: 160 | M59: 200 | N59: 150 | O59: 175 | P59: 560
B60: 4509 | C60: Lohi | D60: Polywool | E60: hemant | F60: minister new | G60: 55 | I60: 10 | J60: 65 | K60: 85 | L60: 85 | M60: 125 | N60: 80 | O60: 95 | P60: 330
A61: 2026 | B61: 1400 white/kesari | C61: Lohi | D61: Polywool | E61: sewa singh | F61: p/a lohi white & keasri 700 gm | G61: 196 | I61: 35 | J61: 231 | K61: 280 | L61: 290 | M61: 375 | N61: 270 | O61: 315 | P61: 870
B62: 1403 | C62: lohi | D62: pashmina | E62: woolco | F62: gents pashmina reversible | G62: 5500 | I62: 50 | J62: 5550 | K62: 6595 | L62: 6940 | M62: 11800 | N62: 6385 | O62: 7430 | P62: 23460
B63: 1404 | C63: lohi | D63: pashmina | E63: woolco | F63: gents pashminaheavy | G63: 6000 | I63: 50 | J63: 6050 | K63: 7190 | L63: 7565 | M63: 12900 | N63: 6960 | O63: 8095 | P63: 25580
A64: 2026 | B64: 555 white/kesari | C64: Lohi | D64: Polywool | F64: p/v white | G64: 140 | I64: 35 | J64: 175 | K64: 210 | L64: 220 | M64: 300 | N64: 205 | O64: 240 | P64: 650
A65: 2026 | B65: 666 white/kesari | C65: Lohi | D65: Polywool | F65: p/v/lohi orange 600 gm | G65: 168 | I65: 35 | J65: 203 | K65: 245 | L65: 255 | M65: 325 | N65: 235 | O65: 275 | P65: 760
A66: 2026 | B66: 701 Check Lohi | C66: Lohi | D66: Polywool | E66: BM GUPTA | F66: CHECK LOHI | G66: 305 | I66: 15 | J66: 320 | K66: 380 | L66: 400 | M66: 525 | N66: 370 | O66: 430 | P66: 1280
A67: 2026 | B67: Arjun | C67: Lohi | D67: Polywool | E67: dee kay | F67: border lohi pvr | G67: 185 | I67: 10 | J67: 195 | K67: 235 | L67: 245 | M67: 325 | N67: 230 | O67: 265 | P67: 820
A68: 2025 | B68: Crystal no.4000 | C68: Lohi | D68: Polywool | E68: h.r | F68: 400 gm without wash packed | G68: 94 | I68: 10 | J68: 104 | K68: 125 | L68: 130 | M68: 175 | N68: 120 | O68: 140 | P68: 480
A69: 2025 | B69: Crystal no.5000 | C69: Lohi | D69: Polywool | E69: h.r | F69: 500 gm without wash packed | G69: 155 | I69: 5 | J69: 160 | K69: 190 | L69: 200 | M69: 275 | N69: 185 | O69: 215 | P69: 710
A70: 2025 | B70: Crystal no.6000 | C70: Lohi | D70: Polywool | E70: h.r | F70: 600 gm without wash packed | G70: 141 | I70: 10 | J70: 151 | K70: 185 | L70: 190 | M70: 250 | N70: 175 | O70: 205 | P70: 660
A71: 2025 | B71: Crystal no.7000 | C71: Lohi | D71: Polywool | E71: h.r | F71: 700 gm without wash packed | G71: 164.5 | I71: 10 | J71: 174.5 | K71: 210 | L71: 220 | M71: 275 | N71: 205 | O71: 240 | P71: 750
A72: 2025 | B72: Crystal no.8000 | C72: Lohi | D72: Polywool | E72: h.r | F72: 800 gm without wash packed | G72: 285 | I72: 5 | J72: 290 | K72: 350 | L72: 365 | M72: 475 | N72: 340 | O72: 395 | P72: 1200
A73: 2025 | B73: Crystal no.9000 | C73: Lohi | D73: Polywool | E73: h.r | F73: 900 gm without wash packed | G73: 211.5 | H73: 2.5 | I73: 10 | J73: 224 | K73: 270 | L73: 280 | M73: 375 | N73: 260 | O73: 300 | P73: 920
A74: 2025 | B74: Dhariwal no.10000 | C74: Lohi | D74: Polywool | E74: h.r | F74: 1000 gm without wash packed | G74: 235 | H74: 2.5 | I74: 10 | J74: 247.5 | K74: 295 | L74: 310 | M74: 400 | N74: 290 | O74: 335 | P74: 1010
A75: 2026 | B75: Swagat | C75: Lohi | D75: Polywool | E75: dee kay | F75: ss tape pvr | G75: 185 | I75: 10 | J75: 195 | K75: 235 | L75: 245 | M75: 325 | N75: 230 | O75: 265 | P75: 820
B76: lohi sahil | C76: Lohi | D76: Polywool | F76: sahil jay dee | G76: 310 | I76: 10 | J76: 320 | K76: 380 | L76: 400 | M76: 525 | N76: 370 | O76: 430 | P76: 1300
B77: M1 | C77: muffler | D77: muffler | E77: v.s | F77: EX N3 | G77: 95 | I77: 5 | J77: 100 | K77: 120 | L77: 125 | M77: 175 | N77: 115 | O77: 135 | P77: 480
A78: 2026 | B78: 847 | C78: Odni | D78: Polywool | E78: Asian | F78: modal dupatta | G78: 850 | I78: 25 | J78: 875 | K78: 1085 | L78: 1140 | M78: 1400 | N78: 1050 | O78: 1220 | P78: 3330
B79: N3 | C79: Ponchu | D79: muffler | E79: Dharm | F79: N3 | G79: 240 | I79: 10 | J79: 250 | K79: 300 | L79: 315 | M79: 400 | N79: 290 | O79: 340 | P79: 1030
B80: P 14 | C80: Ponchu | D80: China | E80: Dharm | F80: P 14 | G80: 395 | I80: 10 | J80: 405 | K80: 485 | L80: 510 | M80: 650 | N80: 470 | O80: 550 | P80: 1620
B81: P 169 | C81: Ponchu | D81: China | E81: Dharm | F81: P 169 | G81: 295 | J81: 295 | K81: 355 | L81: 370 | M81: 475 | N81: 345 | O81: 400 | P81: 1240
B82: P 171 | C82: Ponchu | D82: China | E82: Dharm | F82: P 171 | G82: 320 | I82: 10 | J82: 330 | K82: 395 | L82: 415 | M82: 525 | N82: 385 | O82: 445 | P82: 1330
B83: P 8 | C83: Ponchu | D83: China | E83: Dharm | F83: P 8 | G83: 330 | I83: 10 | J83: 340 | K83: 405 | L83: 425 | M83: 550 | N83: 395 | O83: 455 | P83: 1370
B84: 5201 | C84: scarf | D84: Polywool | E84: D.C | F84: scarf modal d.c | G84: 210 | I84: 12 | J84: 222 | K84: 270 | L84: 280 | M84: 350 | N84: 260 | O84: 300 | P84: 920
B85: 101 | C85: shawl | D85: Wool | F85: plain 40 x 80 | G85: 380 | I85: 20 | J85: 400 | K85: 515 | L85: 540 | M85: 650 | N85: 500 | O85: 580 | P85: 1560
B86: 102 | C86: shawl | D86: wool | E86: Usha | F86: s.s tape 40 | G86: 380 | I86: 15 | J86: 395 | K86: 510 | L86: 535 | M86: 625 | N86: 495 | O86: 575 | P86: 1560
A87: 2026 | B87: 105 | C87: shawl | D87: Fine Wool | E87: Rajesh | F87: kalamkari | G87: 12500 | I87: 50 | J87: 12550 | K87: 15500 | L87: 16315 | M87: 22250 | N87: 15010 | O87: 17460 | P87: 53140
A88: 2025 | B88: 106 | C88: shawl | D88: Fine Wool | E88: Rajesh | F88: kalamkari | G88: 8500 | H88: 15 | I88: 25 | J88: 8540 | K88: 10550 | L88: 11105 | M88: 15150 | N88: 10220 | O88: 11885 | P88: 36180
B89: 107 | C89: Shawl | D89: Fine Wool | E89: Subhash | F89: multihead sangeen dour subhash | G89: 2700 | I89: 15 | J89: 2715 | K89: 3355 | L89: 3530 | M89: 4850 | N89: 3250 | O89: 3780 | P89: 11590
A90: 2026 | B90: 108 | C90: Shawl | D90: Fine Wool | E90: Subhash | F90: gents hashia multihead subhash 2350 | G90: 3700 | I90: 25 | J90: 3725 | K90: 4605 | L90: 4845 | M90: 6600 | N90: 4460 | O90: 5185 | P90: 15830
A91: 2026 | B91: 109 | C91: shawl | D91: Fine Wool | E91: ashwani | F91: kalamkari box figure + kalamkari heavy ashwani | G91: 8500 | I91: 50 | J91: 8550 | K91: 10560 | L91: 11115 | M91: 15150 | N91: 10230 | O91: 11895 | P91: 36180
B92: 110 | C92: Shawl | D92: Fine Wool | E92: Gaurav | F92: jamma 24097 & 24099 gw | G92: 3800 | I92: 15 | J92: 3815 | K92: 4715 | L92: 4960 | M92: 6800 | N92: 4565 | O92: 5310 | P92: 16250
A93: 2025 | B93: 112 | C93: shawl | D93: Fine Wool | E93: Rajesh | F93: kalamkari palla | G93: 4500 | H93: 25 | I93: 15 | J93: 4540 | K93: 5610 | L93: 5905 | M93: 8050 | N93: 5435 | O93: 6320 | P93: 19220
A94: 2026 | B94: 113 | C94: Shawl | D94: Fine Wool | E94: Subhash | F94: jamma | G94: 5300 | I94: 15 | J94: 5315 | K94: 6565 | L94: 6910 | M94: 9450 | N94: 6360 | O94: 7395 | P94: 22610
A95: 2026 | B95: 114 | C95: Shawl | D95: Polywool | F95: plain solo polywool 40 x 80 220gm | G95: 250 | H95: 55 | I95: 35 | J95: 340 | K95: 405 | L95: 425 | M95: 550 | N95: 395 | O95: 455 | P95: 1070
A96: 2025 | B96: 115 | C96: shawl | D96: Fine Wool | E96: Rajesh | F96: top dour multi head | G96: 1350 | H96: 10 | I96: 25 | J96: 1385 | K96: 1715 | L96: 1805 | M96: 2200 | N96: 1665 | O96: 1935 | P96: 5220
B97: 116 | C97: Shawl | D97: Fine Wool | E97: Gaurav | F97: jamma 24101 & 22000 gw | G97: 4200 | I97: 15 | J97: 4215 | K97: 5210 | L97: 5480 | M97: 7500 | N97: 5045 | O97: 5865 | P97: 17950
A98: 2025 | B98: 117 | C98: shawl | D98: Fine Wool | E98: ramesh khanna | F98: buti jamma | G98: 2250 | I98: 25 | J98: 2275 | K98: 2815 | L98: 2960 | M98: 4050 | N98: 2725 | O98: 3170 | P98: 9680
A99: 2025 | B99: 118 | C99: shawl | D99: Fine Wool | E99: ramesh khanna | F99: jal jamma kani | G99: 2750 | I99: 25 | J99: 2775 | K99: 3430 | L99: 3610 | M99: 4950 | N99: 3325 | O99: 3865 | P99: 11800
A100: 2026 | B100: 119 | C100: Shawl | D100: Fine Wool | E100: rajesh | F100: gents shahtoosh 50*100 polywool | G100: 1275 | I100: 15 | J100: 1290 | K100: 1600 | L100: 1680 | M100: 2050 | N100: 1550 | O100: 1800 | P100: 4940
...

Sheet Price Finder
A1: Item | B1: Wsp | E1: Item | F1: Mrp | I1: Item | J1: Net Price Credit | M1: Item | N1: Net Price Cash | Q1: Item | R1: South | T1: Item | U1: Amazon
B2: =IF(A2>0,VLOOKUP(A2,'Full Price List'!$B$1:$O$1131,11,FALSE),"") | F2: =IF(E2>0,VLOOKUP(E2,'Full Price List'!$B$1:$O$1131,12,FALSE),"") | J2: =IF(I2>0,VLOOKUP(I2,'Full Price List'!$B$1:$O$1131,10,FALSE),"") | N2: =IF(M2>0,VLOOKUP(M2,'Full Price List'!$B$1:$O$1131,13,FALSE),"") | R2: =IF(Q2>0,VLOOKUP(Q2,'Full Price List'!$B$1:$O$1131,14,FALSE),"") | U2: =IF(T2>0,VLOOKUP(T2,'Full Price List'!$B$1:$P$1131,15,FALSE),"")
B3: =IF(A3>0,VLOOKUP(A3,'Full Price List'!$B$1:$O$1131,11,FALSE),"") | F3: =IF(E3>0,VLOOKUP(E3,'Full Price List'!$B$1:$O$1131,12,FALSE),"") | J3: =IF(I3>0,VLOOKUP(I3,'Full Price List'!$B$1:$O$1131,10,FALSE),"") | N3: =IF(M3>0,VLOOKUP(M3,'Full Price List'!$B$1:$O$1131,13,FALSE),"") | R3: =IF(Q3>0,VLOOKUP(Q3,'Full Price List'!$B$1:$O$1131,14,FALSE),"") | U3: =IF(T3>0,VLOOKUP(T3,'Full Price List'!$B$1:$P$1131,15,FALSE),"")
B4: =IF(A4>0,VLOOKUP(A4,'Full Price List'!$B$1:$O$1131,11,FALSE),"") | F4: =IF(E4>0,VLOOKUP(E4,'Full Price List'!$B$1:$O$1131,12,FALSE),"") | J4: =IF(I4>0,VLOOKUP(I4,'Full Price List'!$B$1:$O$1131,10,FALSE),"") | N4: =IF(M4>0,VLOOKUP(M4,'Full Price List'!$B$1:$O$1131,13,FALSE),"") | R4: =IF(Q4>0,VLOOKUP(Q4,'Full Price List'!$B$1:$O$1131,14,FALSE),"") | U4: =IF(T4>0,VLOOKUP(T4,'Full Price List'!$B$1:$P$1131,15,FALSE),"")
B5: =IF(A5>0,VLOOKUP(A5,'Full Price List'!$B$1:$O$1131,11,FALSE),"") | F5: =IF(E5>0,VLOOKUP(E5,'Full Price List'!$B$1:$O$1131,12,FALSE),"") | J5: =IF(I5>0,VLOOKUP(I5,'Full Price List'!$B$1:$O$1131,10,FALSE),"") | N5: =IF(M5>0,VLOOKUP(M5,'Full Price List'!$B$1:$O$1131,13,FALSE),"") | R5: =IF(Q5>0,VLOOKUP(Q5,'Full Price List'!$B$1:$O$1131,14,FALSE),"") | U5: =IF(T5>0,VLOOKUP(T5,'Full Price List'!$B$1:$P$1131,15,FALSE),"")
B6: =IF(A6>0,VLOOKUP(A6,'Full Price List'!$B$1:$O$1131,11,FALSE),"") | F6: =IF(E6>0,VLOOKUP(E6,'Full Price List'!$B$1:$O$1131,12,FALSE),"") | J6: =IF(I6>0,VLOOKUP(I6,'Full Price List'!$B$1:$O$1131,10,FALSE),"") | N6: =IF(M6>0,VLOOKUP(M6,'Full Price List'!$B$1:$O$1131,13,FALSE),"") | R6: =IF(Q6>0,VLOOKUP(Q6,'Full Price List'!$B$1:$O$1131,14,FALSE),"") | U6: =IF(T6>0,VLOOKUP(T6,'Full Price List'!$B$1:$P$1131,15,FALSE),"")
B7: =IF(A7>0,VLOOKUP(A7,'Full Price List'!$B$1:$O$1131,11,FALSE),"") | F7: =IF(E7>0,VLOOKUP(E7,'Full Price List'!$B$1:$O$1131,12,FALSE),"") | J7: =IF(I7>0,VLOOKUP(I7,'Full Price List'!$B$1:$O$1131,10,FALSE),"") | N7: =IF(M7>0,VLOOKUP(M7,'Full Price List'!$B$1:$O$1131,13,FALSE),"") | R7: =IF(Q7>0,VLOOKUP(Q7,'Full Price List'!$B$1:$O$1131,14,FALSE),"") | U7: =IF(T7>0,VLOOKUP(T7,'Full Price List'!$B$1:$P$1131,15,FALSE),"")
B8: =IF(A8>0,VLOOKUP(A8,'Full Price List'!$B$1:$O$1131,11,FALSE),"") | F8: =IF(E8>0,VLOOKUP(E8,'Full Price List'!$B$1:$O$1131,12,FALSE),"") | J8: =IF(I8>0,VLOOKUP(I8,'Full Price List'!$B$1:$O$1131,10,FALSE),"") | N8: =IF(M8>0,VLOOKUP(M8,'Full Price List'!$B$1:$O$1131,13,FALSE),"") | R8: =IF(Q8>0,VLOOKUP(Q8,'Full Price List'!$B$1:$O$1131,14,FALSE),"") | U8: =IF(T8>0,VLOOKUP(T8,'Full Price List'!$B$1:$P$1131,15,FALSE),"")
B9: =IF(A9>0,VLOOKUP(A9,'Full Price List'!$B$1:$O$1131,11,FALSE),"") | F9: =IF(E9>0,VLOOKUP(E9,'Full Price List'!$B$1:$O$1131,12,FALSE),"") | J9: =IF(I9>0,VLOOKUP(I9,'Full Price List'!$B$1:$O$1131,10,FALSE),"") | N9: =IF(M9>0,VLOOKUP(M9,'Full Price List'!$B$1:$O$1131,13,FALSE),"") | R9: =IF(Q9>0,VLOOKUP(Q9,'Full Price List'!$B$1:$O$1131,14,FALSE),"") | U9: =IF(T9>0,VLOOKUP(T9,'Full Price List'!$B$1:$P$1131,15,FALSE),"")
B10: =IF(A10>0,VLOOKUP(A10,'Full Price List'!$B$1:$O$1131,11,FALSE),"") | F10: =IF(E10>0,VLOOKUP(E10,'Full Price List'!$B$1:$O$1131,12,FALSE),"") | J10: =IF(I10>0,VLOOKUP(I10,'Full Price List'!$B$1:$O$1131,10,FALSE),"") | N10: =IF(M10>0,VLOOKUP(M10,'Full Price List'!$B$1:$O$1131,13,FALSE),"") | R10: =IF(Q10>0,VLOOKUP(Q10,'Full Price List'!$B$1:$O$1131,14,FALSE),"") | U10: =IF(T10>0,VLOOKUP(T10,'Full Price List'!$B$1:$P$1131,15,FALSE),"")
B11: =IF(A11>0,VLOOKUP(A11,'Full Price List'!$B$1:$O$1131,11,FALSE),"") | F11: =IF(E11>0,VLOOKUP(E11,'Full Price List'!$B$1:$O$1131,12,FALSE),"") | J11: =IF(I11>0,VLOOKUP(I11,'Full Price List'!$B$1:$O$1131,10,FALSE),"") | N11: =IF(M11>0,VLOOKUP(M11,'Full Price List'!$B$1:$O$1131,13,FALSE),"") | R11: =IF(Q11>0,VLOOKUP(Q11,'Full Price List'!$B$1:$O$1131,14,FALSE),"") | U11: =IF(T11>0,VLOOKUP(T11,'Full Price List'!$B$1:$P$1131,15,FALSE),"")
B12: =IF(A12>0,VLOOKUP(A12,'Full Price List'!$B$1:$O$1131,11,FALSE),"") | F12: =IF(E12>0,VLOOKUP(E12,'Full Price List'!$B$1:$O$1131,12,FALSE),"") | J12: =IF(I12>0,VLOOKUP(I12,'Full Price List'!$B$1:$O$1131,10,FALSE),"") | N12: =IF(M12>0,VLOOKUP(M12,'Full Price List'!$B$1:$O$1131,13,FALSE),"") | R12: =IF(Q12>0,VLOOKUP(Q12,'Full Price List'!$B$1:$O$1131,14,FALSE),"") | U12: =IF(T12>0,VLOOKUP(T12,'Full Price List'!$B$1:$P$1131,15,FALSE),"")
B13: =IF(A13>0,VLOOKUP(A13,'Full Price List'!$B$1:$O$1131,11,FALSE),"") | F13: =IF(E13>0,VLOOKUP(E13,'Full Price List'!$B$1:$O$1131,12,FALSE),"") | J13: =IF(I13>0,VLOOKUP(I13,'Full Price List'!$B$1:$O$1131,10,FALSE),"") | N13: =IF(M13>0,VLOOKUP(M13,'Full Price List'!$B$1:$O$1131,13,FALSE),"") | R13: =IF(Q13>0,VLOOKUP(Q13,'Full Price List'!$B$1:$O$1131,14,FALSE),"") | U13: =IF(T13>0,VLOOKUP(T13,'Full Price List'!$B$1:$P$1131,15,FALSE),"")
... B60: =IF(A60>0,VLOOKUP(A60,'Full Price List'!$B$1:$O$1131,11,FALSE),"") | F60: =IF(E60>0,VLOOKUP(E60,'Full Price List'!$B$1:$O$1131,12,FALSE),"") | J60: =IF(I60>0,VLOOKUP(I60,'Full Price List'!$B$1:$O$1131,10,FALSE),"") | N60: =IF(M60>0,VLOOKUP(M60,'Full Price List'!$B$1:$O$1131,13,FALSE),"") | R60: =IF(Q60>0,VLOOKUP(Q60,'Full Price List'!$B$1:$O$1131,14,FALSE),"") | U60: =IF(T60>0,VLOOKUP(T60,'Full Price List'!$B$1:$P$1131,15,FALSE),"")
B61: =SUBTOTAL(109,Table18[Wsp]) -> 0 | F61: =SUBTOTAL(109,Table19[Mrp]) -> 0 | J61: =SUBTOTAL(109,Table21[Net Price Credit]) -> 0 | N61: =SUBTOTAL(109,Table8[Net Price Cash]) -> 0 | R61: =SUBTOTAL(109,Table10[South]) -> 0 | T61: Total | U61: =SUBTOTAL(109,Table9[Amazon]) -> 0

Sheet Mrp Challan
A1: Art no. | B1: Quantity | C1: Item | D1: Price | E1: =IF(AND(ISNUMBER(E2),E2>0),"Net Price","Tax") -> Tax | F1: Total | H1: Mrp | I1: Discount
C2: =IFERROR(PROPER(VLOOKUP(A2,#REF!,2,FALSE)),"") | D2: =IF(A2<>"",VLOOKUP(A2,'Full Price List'!$B$2:$O$2076,12,FALSE),"") | E2: =IF(AND($J$1<>"",A2<>""), CEILING( VLOOKUP(A2,#REF!,12,FALSE) * (1 - $J$1/IF($J$1>=1,100,1)), 5 ), "" ) | F2: =IF(A2<>"", IF(E2<>"", B2*E2, IF(D2<>"",B2*D2,"") ), "" )
C3: =IFERROR(PROPER(VLOOKUP(A3,#REF!,2,FALSE)),"") | D3: =IF(A3<>"",VLOOKUP(A3,'Full Price List'!$B$2:$O$2076,12,FALSE),"") | E3: =IF(AND($J$1<>"",A3<>""), CEILING( VLOOKUP(A3,#REF!,12,FALSE) * (1 - $J$1/IF($J$1>=1,100,1)), 5 ), "" ) | F3: =IF(A3<>"", IF(E3<>"", B3*E3, IF(D3<>"",B3*D3,"") ), "" )
C4: =IFERROR(PROPER(VLOOKUP(A4,#REF!,2,FALSE)),"") | D4: =IF(A4<>"",VLOOKUP(A4,'Full Price List'!$B$2:$O$2076,12,FALSE),"") | E4: =IF(AND($J$1<>"",A4<>""), CEILING( VLOOKUP(A4,#REF!,12,FALSE) * (1 - $J$1/IF($J$1>=1,100,1)), 5 ), "" ) | F4: =IF(A4<>"", IF(E4<>"", B4*E4, IF(D4<>"",B4*D4,"") ), "" )
C5: =IFERROR(PROPER(VLOOKUP(A5,#REF!,2,FALSE)),"") | D5: =IF(A5<>"",VLOOKUP(A5,'Full Price List'!$B$2:$O$2076,12,FALSE),"") | E5: =IF(AND($J$1<>"",A5<>""), CEILING( VLOOKUP(A5,#REF!,12,FALSE) * (1 - $J$1/IF($J$1>=1,100,1)), 5 ), "" ) | F5: =IF(A5<>"", IF(E5<>"", B5*E5, IF(D5<>"",B5*D5,"") ), "" )
C6: =IFERROR(PROPER(VLOOKUP(A6,#REF!,2,FALSE)),"") | D6: =IF(A6<>"",VLOOKUP(A6,'Full Price List'!$B$2:$O$2076,12,FALSE),"") | E6: =IF(AND($J$1<>"",A6<>""), CEILING( VLOOKUP(A6,#REF!,12,FALSE) * (1 - $J$1/IF($J$1>=1,100,1)), 5 ), "" ) | F6: =IF(A6<>"", IF(E6<>"", B6*E6, IF(D6<>"",B6*D6,"") ), "" )
C7: =IFERROR(PROPER(VLOOKUP(A7,#REF!,2,FALSE)),"") | D7: =IF(A7<>"",VLOOKUP(A7,'Full Price List'!$B$2:$O$2076,12,FALSE),"") | E7: =IF(AND($J$1<>"",A7<>""), CEILING( VLOOKUP(A7,#REF!,12,FALSE) * (1 - $J$1/IF($J$1>=1,100,1)), 5 ), "" ) | F7: =IF(A7<>"", IF(E7<>"", B7*E7, IF(D7<>"",B7*D7,"") ), "" )
C8: =IFERROR(PROPER(VLOOKUP(A8,#REF!,2,FALSE)),"") | D8: =IF(A8<>"",VLOOKUP(A8,'Full Price List'!$B$2:$O$2076,12,FALSE),"") | E8: =IF(AND($J$1<>"",A8<>""), CEILING( VLOOKUP(A8,#REF!,12,FALSE) * (1 - $J$1/IF($J$1>=1,100,1)), 5 ), "" ) | F8: =IF(A8<>"", IF(E8<>"", B8*E8, IF(D8<>"",B8*D8,"") ), "" )
C9: =IFERROR(PROPER(VLOOKUP(A9,#REF!,2,FALSE)),"") | D9: =IF(A9<>"",VLOOKUP(A9,'Full Price List'!$B$2:$O$2076,12,FALSE),"") | E9: =IF(AND($J$1<>"",A9<>""), CEILING( VLOOKUP(A9,#REF!,12,FALSE) * (1 - $J$1/IF($J$1>=1,100,1)), 5 ), "" ) | F9: =IF(A9<>"", IF(E9<>"", B9*E9, IF(D9<>"",B9*D9,"") ), "" )
C10: =IFERROR(PROPER(VLOOKUP(A10,#REF!,2,FALSE)),"") | D10: =IF(A10<>"",VLOOKUP(A10,'Full Price List'!$B$2:$O$2076,12,FALSE),"") | E10: =IF(AND($J$1<>"",A10<>""), CEILING( VLOOKUP(A10,#REF!,12,FALSE) * (1 - $J$1/IF($J$1>=1,100,1)), 5 ), "" ) | F10: =IF(A10<>"", IF(E10<>"", B10*E10, IF(D10<>"",B10*D10,"") ), "" )
C11: =IFERROR(PROPER(VLOOKUP(A11,#REF!,2,FALSE)),"") | D11: =IF(A11<>"",VLOOKUP(A11,'Full Price List'!$B$2:$O$2076,12,FALSE),"") | E11: =IF(AND($J$1<>"",A11<>""), CEILING( VLOOKUP(A11,#REF!,12,FALSE) * (1 - $J$1/IF($J$1>=1,100,1)), 5 ), "" ) | F11: =IF(A11<>"", IF(E11<>"", B11*E11, IF(D11<>"",B11*D11,"") ), "" )
C12: =IFERROR(PROPER(VLOOKUP(A12,#REF!,2,FALSE)),"") | D12: =IF(A12<>"",VLOOKUP(A12,'Full Price List'!$B$2:$O$2076,12,FALSE),"") | E12: =IF(AND($J$1<>"",A12<>""), CEILING( VLOOKUP(A12,#REF!,12,FALSE) * (1 - $J$1/IF($J$1>=1,100,1)), 5 ), "" ) | F12: =IF(A12<>"", IF(E12<>"", B12*E12, IF(D12<>"",B12*D12,"") ), "" )
C13: =IFERROR(PROPER(VLOOKUP(A13,#REF!,2,FALSE)),"") | D13: =IF(A13<>"",VLOOKUP(A13,'Full Price List'!$B$2:$O$2076,12,FALSE),"") | E13: =IF(AND($J$1<>"",A13<>""), CEILING( VLOOKUP(A13,#REF!,12,FALSE) * (1 - $J$1/IF($J$1>=1,100,1)), 5 ), "" ) | F13: =IF(A13<>"", IF(E13<>"", B13*E13, IF(D13<>"",B13*D13,"") ), "" )
... C30: =IFERROR(PROPER(VLOOKUP(A30,#REF!,2,FALSE)),"") | D30: =IF(A30<>"",VLOOKUP(A30,'Full Price List'!$B$2:$O$2076,12,FALSE),"") | E30: =IF(AND($J$1<>"",A30<>""), CEILING( VLOOKUP(A30,#REF!,12,FALSE) * (1 - $J$1/IF($J$1>=1,100,1)), 5 ), "" ) | F30: =IF(A30<>"", IF(E30<>"", B30*E30, IF(D30<>"",B30*D30,"") ), "" )
A31: Total | B31: =IF(SUBTOTAL(109,Table423[Quantity])=0,"",SUBTOTAL(109,Table423[Quantity])) | F31: =IF(SUBTOTAL(109,Table423[Total])=0,"",SUBTOTAL(109,Table423[Total]))
C32: =IF(ISNUMBER(E32),"Discount","") | F32: =IF(ISNUMBER(E32),MROUND(F31*E32,5),"") | G32: Discount
C33: Balance | F33: =IF(AND(ISNUMBER(F31),ISNUMBER(F32)),F31-F32,IF(F31<>"",F31,""))

Sheet Wsp Challan
A1: Art no. | B1: Quantity | C1: Item | D1: Price | E1: =IF(AND(ISNUMBER(E2),E2>0),"Net Price","Tax") -> Tax | F1: Total | H1: WSP | I1: Discount
C2: =IFERROR(PROPER(VLOOKUP(A2,#REF!,2,FALSE)),"") | D2: =IF(A2<>"",VLOOKUP(A2,'Full Price List'!$B$2:$O$2076,11,FALSE),"") | E2: =IF(AND($J$1<>"",A2<>""), CEILING( VLOOKUP(A2,#REF!,11,FALSE) * (1 - $J$1/IF($J$1>=1,100,1)), 5 ), "" ) | F2: =IF(A2<>"", IF(E2<>"", B2*E2, IF(D2<>"",B2*D2,"") ), "" )
C3: =IFERROR(PROPER(VLOOKUP(A3,#REF!,2,FALSE)),"") | D3: =IF(A3<>"",VLOOKUP(A3,'Full Price List'!$B$2:$O$2076,11,FALSE),"") | E3: =IF(AND($J$1<>"",A3<>""), CEILING( VLOOKUP(A3,#REF!,11,FALSE) * (1 - $J$1/IF($J$1>=1,100,1)), 5 ), "" ) | F3: =IF(A3<>"", IF(E3<>"", B3*E3, IF(D3<>"",B3*D3,"") ), "" )
C4: =IFERROR(PROPER(VLOOKUP(A4,#REF!,2,FALSE)),"") | D4: =IF(A4<>"",VLOOKUP(A4,'Full Price List'!$B$2:$O$2076,11,FALSE),"") | E4: =IF(AND($J$1<>"",A4<>""), CEILING( VLOOKUP(A4,#REF!,11,FALSE) * (1 - $J$1/IF($J$1>=1,100,1)), 5 ), "" ) | F4: =IF(A4<>"", IF(E4<>"", B4*E4, IF(D4<>"",B4*D4,"") ), "" )
C5: =IFERROR(PROPER(VLOOKUP(A5,#REF!,2,FALSE)),"") | D5: =IF(A5<>"",VLOOKUP(A5,'Full Price List'!$B$2:$O$2076,11,FALSE),"") | E5: =IF(AND($J$1<>"",A5<>""), CEILING( VLOOKUP(A5,#REF!,11,FALSE) * (1 - $J$1/IF($J$1>=1,100,1)), 5 ), "" ) | F5: =IF(A5<>"", IF(E5<>"", B5*E5, IF(D5<>"",B5*D5,"") ), "" )
C6: =IFERROR(PROPER(VLOOKUP(A6,#REF!,2,FALSE)),"") | D6: =IF(A6<>"",VLOOKUP(A6,'Full Price List'!$B$2:$O$2076,11,FALSE),"") | E6: =IF(AND($J$1<>"",A6<>""), CEILING( VLOOKUP(A6,#REF!,11,FALSE) * (1 - $J$1/IF($J$1>=1,100,1)), 5 ), "" ) | F6: =IF(A6<>"", IF(E6<>"", B6*E6, IF(D6<>"",B6*D6,"") ), "" )
C7: =IFERROR(PROPER(VLOOKUP(A7,#REF!,2,FALSE)),"") | D7: =IF(A7<>"",VLOOKUP(A7,'Full Price List'!$B$2:$O$2076,11,FALSE),"") | E7: =IF(AND($J$1<>"",A7<>""), CEILING( VLOOKUP(A7,#REF!,11,FALSE) * (1 - $J$1/IF($J$1>=1,100,1)), 5 ), "" ) | F7: =IF(A7<>"", IF(E7<>"", B7*E7, IF(D7<>"",B7*D7,"") ), "" )
C8: =IFERROR(PROPER(VLOOKUP(A8,#REF!,2,FALSE)),"") | D8: =IF(A8<>"",VLOOKUP(A8,'Full Price List'!$B$2:$O$2076,11,FALSE),"") | E8: =IF(AND($J$1<>"",A8<>""), CEILING( VLOOKUP(A8,#REF!,11,FALSE) * (1 - $J$1/IF($J$1>=1,100,1)), 5 ), "" ) | F8: =IF(A8<>"", IF(E8<>"", B8*E8, IF(D8<>"",B8*D8,"") ), "" )
C9: =IFERROR(PROPER(VLOOKUP(A9,#REF!,2,FALSE)),"") | D9: =IF(A9<>"",VLOOKUP(A9,'Full Price List'!$B$2:$O$2076,11,FALSE),"") | E9: =IF(AND($J$1<>"",A9<>""), CEILING( VLOOKUP(A9,#REF!,11,FALSE) * (1 - $J$1/IF($J$1>=1,100,1)), 5 ), "" ) | F9: =IF(A9<>"", IF(E9<>"", B9*E9, IF(D9<>"",B9*D9,"") ), "" )
C10: =IFERROR(PROPER(VLOOKUP(A10,#REF!,2,FALSE)),"") | D10: =IF(A10<>"",VLOOKUP(A10,'Full Price List'!$B$2:$O$2076,11,FALSE),"") | E10: =IF(AND($J$1<>"",A10<>""), CEILING( VLOOKUP(A10,#REF!,11,FALSE) * (1 - $J$1/IF($J$1>=1,100,1)), 5 ), "" ) | F10: =IF(A10<>"", IF(E10<>"", B10*E10, IF(D10<>"",B10*D10,"") ), "" )
C11: =IFERROR(PROPER(VLOOKUP(A11,#REF!,2,FALSE)),"") | D11: =IF(A11<>"",VLOOKUP(A11,'Full Price List'!$B$2:$O$2076,11,FALSE),"") | E11: =IF(AND($J$1<>"",A11<>""), CEILING( VLOOKUP(A11,#REF!,11,FALSE) * (1 - $J$1/IF($J$1>=1,100,1)), 5 ), "" ) | F11: =IF(A11<>"", IF(E11<>"", B11*E11, IF(D11<>"",B11*D11,"") ), "" )
C12: =IFERROR(PROPER(VLOOKUP(A12,#REF!,2,FALSE)),"") | D12: =IF(A12<>"",VLOOKUP(A12,'Full Price List'!$B$2:$O$2076,11,FALSE),"") | E12: =IF(AND($J$1<>"",A12<>""), CEILING( VLOOKUP(A12,#REF!,11,FALSE) * (1 - $J$1/IF($J$1>=1,100,1)), 5 ), "" ) | F12: =IF(A12<>"", IF(E12<>"", B12*E12, IF(D12<>"",B12*D12,"") ), "" )
C13: =IFERROR(PROPER(VLOOKUP(A13,#REF!,2,FALSE)),"") | D13: =IF(A13<>"",VLOOKUP(A13,'Full Price List'!$B$2:$O$2076,11,FALSE),"") | E13: =IF(AND($J$1<>"",A13<>""), CEILING( VLOOKUP(A13,#REF!,11,FALSE) * (1 - $J$1/IF($J$1>=1,100,1)), 5 ), "" ) | F13: =IF(A13<>"", IF(E13<>"", B13*E13, IF(D13<>"",B13*D13,"") ), "" )
... C30: =IFERROR(PROPER(VLOOKUP(A30,#REF!,2,FALSE)),"") | D30: =IF(A30<>"",VLOOKUP(A30,'Full Price List'!$B$2:$O$2076,11,FALSE),"") | E30: =IF(AND($J$1<>"",A30<>""), CEILING( VLOOKUP(A30,#REF!,11,FALSE) * (1 - $J$1/IF($J$1>=1,100,1)), 5 ), "" ) | F30: =IF(A30<>"", IF(E30<>"", B30*E30, IF(D30<>"",B30*D30,"") ), "" )
A31: Total | B31: =IF(SUBTOTAL(109,Table42325[Quantity])=0,"",SUBTOTAL(109,Table42325[Quantity])) | F31: =IF(SUBTOTAL(109,Table42325[Total])=0,"",SUBTOTAL(109,Table42325[Total]))
C32: =IF(ISNUMBER(E32),"Discount","") | F32: =IF(ISNUMBER(E32),MROUND(F31*E32,5),"") | G32: Discount
C33: Balance | F33: =IF(AND(ISNUMBER(F31),ISNUMBER(F32)),F31-F32,IF(F31<>"",F31,""))

Sheet Net Cash challan
A1: Art no. | B1: Quantity | C1: Item | D1: Price | E1: =IF(AND(ISNUMBER(E2),E2>0),"Net Price","Tax") -> Tax | F1: Total | H1: Net Cash | I1: Discount
C2: =IFERROR(PROPER(VLOOKUP(A2,#REF!,2,FALSE)),"") | D2: =IF(A2<>"",VLOOKUP(A2,'Full Price List'!$B$2:$O$2076,13,FALSE),"") | E2: =IF(AND($J$1<>"",A2<>""), CEILING( VLOOKUP(A2,#REF!,13,FALSE) * (1 - $J$1/IF($J$1>=1,100,1)), 5 ), "" ) | F2: =IF(A2<>"", IF(E2<>"", B2*E2, IF(D2<>"",B2*D2,"") ), "" )
C3: =IFERROR(PROPER(VLOOKUP(A3,#REF!,2,FALSE)),"") | D3: =IF(A3<>"",VLOOKUP(A3,'Full Price List'!$B$2:$O$2076,13,FALSE),"") | E3: =IF(AND($J$1<>"",A3<>""), CEILING( VLOOKUP(A3,#REF!,13,FALSE) * (1 - $J$1/IF($J$1>=1,100,1)), 5 ), "" ) | F3: =IF(A3<>"", IF(E3<>"", B3*E3, IF(D3<>"",B3*D3,"") ), "" )
C4: =IFERROR(PROPER(VLOOKUP(A4,#REF!,2,FALSE)),"") | D4: =IF(A4<>"",VLOOKUP(A4,'Full Price List'!$B$2:$O$2076,13,FALSE),"") | E4: =IF(AND($J$1<>"",A4<>""), CEILING( VLOOKUP(A4,#REF!,13,FALSE) * (1 - $J$1/IF($J$1>=1,100,1)), 5 ), "" ) | F4: =IF(A4<>"", IF(E4<>"", B4*E4, IF(D4<>"",B4*D4,"") ), "" )
C5: =IFERROR(PROPER(VLOOKUP(A5,#REF!,2,FALSE)),"") | D5: =IF(A5<>"",VLOOKUP(A5,'Full Price List'!$B$2:$O$2076,13,FALSE),"") | E5: =IF(AND($J$1<>"",A5<>""), CEILING( VLOOKUP(A5,#REF!,13,FALSE) * (1 - $J$1/IF($J$1>=1,100,1)), 5 ), "" ) | F5: =IF(A5<>"", IF(E5<>"", B5*E5, IF(D5<>"",B5*D5,"") ), "" )
C6: =IFERROR(PROPER(VLOOKUP(A6,#REF!,2,FALSE)),"") | D6: =IF(A6<>"",VLOOKUP(A6,'Full Price List'!$B$2:$O$2076,13,FALSE),"") | E6: =IF(AND($J$1<>"",A6<>""), CEILING( VLOOKUP(A6,#REF!,13,FALSE) * (1 - $J$1/IF($J$1>=1,100,1)), 5 ), "" ) | F6: =IF(A6<>"", IF(E6<>"", B6*E6, IF(D6<>"",B6*D6,"") ), "" )
C7: =IFERROR(PROPER(VLOOKUP(A7,#REF!,2,FALSE)),"") | D7: =IF(A7<>"",VLOOKUP(A7,'Full Price List'!$B$2:$O$2076,13,FALSE),"") | E7: =IF(AND($J$1<>"",A7<>""), CEILING( VLOOKUP(A7,#REF!,13,FALSE) * (1 - $J$1/IF($J$1>=1,100,1)), 5 ), "" ) | F7: =IF(A7<>"", IF(E7<>"", B7*E7, IF(D7<>"",B7*D7,"") ), "" )
C8: =IFERROR(PROPER(VLOOKUP(A8,#REF!,2,FALSE)),"") | D8: =IF(A8<>"",VLOOKUP(A8,'Full Price List'!$B$2:$O$2076,13,FALSE),"") | E8: =IF(AND($J$1<>"",A8<>""), CEILING( VLOOKUP(A8,#REF!,13,FALSE) * (1 - $J$1/IF($J$1>=1,100,1)), 5 ), "" ) | F8: =IF(A8<>"", IF(E8<>"", B8*E8, IF(D8<>"",B8*D8,"") ), "" )
C9: =IFERROR(PROPER(VLOOKUP(A9,#REF!,2,FALSE)),"") | D9: =IF(A9<>"",VLOOKUP(A9,'Full Price List'!$B$2:$O$2076,13,FALSE),"") | E9: =IF(AND($J$1<>"",A9<>""), CEILING( VLOOKUP(A9,#REF!,13,FALSE) * (1 - $J$1/IF($J$1>=1,100,1)), 5 ), "" ) | F9: =IF(A9<>"", IF(E9<>"", B9*E9, IF(D9<>"",B9*D9,"") ), "" )
C10: =IFERROR(PROPER(VLOOKUP(A10,#REF!,2,FALSE)),"") | D10: =IF(A10<>"",VLOOKUP(A10,'Full Price List'!$B$2:$O$2076,13,FALSE),"") | E10: =IF(AND($J$1<>"",A10<>""), CEILING( VLOOKUP(A10,#REF!,13,FALSE) * (1 - $J$1/IF($J$1>=1,100,1)), 5 ), "" ) | F10: =IF(A10<>"", IF(E10<>"", B10*E10, IF(D10<>"",B10*D10,"") ), "" )
C11: =IFERROR(PROPER(VLOOKUP(A11,#REF!,2,FALSE)),"") | D11: =IF(A11<>"",VLOOKUP(A11,'Full Price List'!$B$2:$O$2076,13,FALSE),"") | E11: =IF(AND($J$1<>"",A11<>""), CEILING( VLOOKUP(A11,#REF!,13,FALSE) * (1 - $J$1/IF($J$1>=1,100,1)), 5 ), "" ) | F11: =IF(A11<>"", IF(E11<>"", B11*E11, IF(D11<>"",B11*D11,"") ), "" )
C12: =IFERROR(PROPER(VLOOKUP(A12,#REF!,2,FALSE)),"") | D12: =IF(A12<>"",VLOOKUP(A12,'Full Price List'!$B$2:$O$2076,13,FALSE),"") | E12: =IF(AND($J$1<>"",A12<>""), CEILING( VLOOKUP(A12,#REF!,13,FALSE) * (1 - $J$1/IF($J$1>=1,100,1)), 5 ), "" ) | F12: =IF(A12<>"", IF(E12<>"", B12*E12, IF(D12<>"",B12*D12,"") ), "" )
C13: =IFERROR(PROPER(VLOOKUP(A13,#REF!,2,FALSE)),"") | D13: =IF(A13<>"",VLOOKUP(A13,'Full Price List'!$B$2:$O$2076,13,FALSE),"") | E13: =IF(AND($J$1<>"",A13<>""), CEILING( VLOOKUP(A13,#REF!,13,FALSE) * (1 - $J$1/IF($J$1>=1,100,1)), 5 ), "" ) | F13: =IF(A13<>"", IF(E13<>"", B13*E13, IF(D13<>"",B13*D13,"") ), "" )
... C30: =IFERROR(PROPER(VLOOKUP(A30,#REF!,2,FALSE)),"") | D30: =IF(A30<>"",VLOOKUP(A30,'Full Price List'!$B$2:$O$2076,13,FALSE),"") | E30: =IF(AND($J$1<>"",A30<>""), CEILING( VLOOKUP(A30,#REF!,13,FALSE) * (1 - $J$1/IF($J$1>=1,100,1)), 5 ), "" ) | F30: =IF(A30<>"", IF(E30<>"", B30*E30, IF(D30<>"",B30*D30,"") ), "" )
A31: Total | B31: =IF(SUBTOTAL(109,Table4232526[Quantity])=0,"",SUBTOTAL(109,Table4232526[Quantity])) | F31: =IF(SUBTOTAL(109,Table4232526[Total])=0,"",SUBTOTAL(109,Table4232526[Total]))
C32: =IF(ISNUMBER(E32),"Discount","") | F32: =IF(ISNUMBER(E32),MROUND(F31*E32,5),"") | G32: Discount
C33: Balance | F33: =IF(AND(ISNUMBER(F31),ISNUMBER(F32)),F31-F32,IF(F31<>"",F31,""))

Sheet Wsp Shawls
A1: Art no. | B1: Item | C1: Quality | D1: Wsp
A2: 101 | B2: shawl | C2: Wool | D2: 540
A3: 102 | B3: shawl | C3: wool | D3: 535
A4: 105 | B4: shawl | C4: Fine Wool | D4: 16315
A5: 106 | B5: shawl | C5: Fine Wool | D5: 11105
A6: 107 | B6: Shawl | C6: Fine Wool | D6: 3530
A7: 108 | B7: Shawl | C7: Fine Wool | D7: 4845
A8: 109 | B8: shawl | C8: Fine Wool | D8: 11115
A9: 110 | B9: Shawl | C9: Fine Wool | D9: 4960
A10: 112 | B10: shawl | C10: Fine Wool | D10: 5905
A11: 113 | B11: Shawl | C11: Fine Wool | D11: 6910
A12: 114 | B12: Shawl | C12: Polywool | D12: 425
A13: 115 | B13: shawl | C13: Fine Wool | D13: 1805
... A423: 9076 | B423: Shawl | C423: Fine Wool | D423: 1920
A424: 1401 | B424: shawl | C424: pashmina | D424: 3815
A425: 1402 | B425: shawl | C425: pashmina | D425: 5690
A426: 333 No.Black | B426: Shawl | C426: Polywool | D426: 100
A427: Ganga | B427: Shawl | C427: Polywool | D427: 165
A428: Marino | B428: Shawl | C428: Polywool | D428: 165

Sheet Wsp Stoles
A1: Art no. | B1: Item | C1: Quality | D1: Wsp | E1: Amazon | F1: With Box
A2: 181 | B2: Stole | C2: polywool | D2: 325 | E2: 990 | F2: 500
A3: 452 | B3: Stole | C3: Knitting | D3: 215 | E3: 740 | F3: 350
A4: 455 | B4: Stole | C4: Knitting | D4: 225 | E4: 770 | F4: 370
A5: 466 | B5: Stole | C5: Knitting | D5: 295 | E5: 970 | F5: 450
A6: 501 | B6: Stole | C6: Polywool | D6: 300 | E6: 780 | F6: 450
A7: 502 | B7: Stole | C7: Polywool | D7: 300 | E7: 940 | F7: 470
A8: 503 | B8: Stole | C8: Polywool | D8: 290 | E8: 960 | F8: 450
A9: 504 | B9: Stole | C9: Polywool | D9: 275 | E9: 870 | F9: 420
A10: 505 | B10: Stole | C10: Polywool | D10: 225 | E10: 650 | F10: 370
A11: 506 | B11: Stole | C11: Polywool | D11: 470 | E11: 770 | F11: 670
A12: 507 | B12: Stole | C12: Polywool | D12: 375 | E12: 690 | F12: 550
A13: 508 | B13: Stole | C13: Polywool | D13: 215 | E13: 730 | F13: 350
... A213: 8684 | B213: Stole | C213: Polywool | D213: 685 | E213: 2010 | F213: 920
A214: M1 | B214: muffler | C214: muffler | D214: 125 | E214: 480 | F214: 250
A215: ST 107 | B215: Stole | C215: China | D215: 240 | E215: 800 | F215: 370
A216: ST 124 | B216: Stole | C216: China | D216: 265 | E216: 880 | F216: 420
A217: ST 136 | B217: Stole | C217: China | D217: 215 | E217: 730 | F217: 350
A218: ST 140 | B218: Stole | C218: China | D218: 365 | E218: 1180 | F218: 550
A219: ST 141 | B219: Stole | C219: China | D219: 365 | E219: 1180 | F219: 550
A220: ST 142 | B220: Stole | C220: China | D220: 365 | E220: 1180 | F220: 550
A221: ST 143 | B221: Stole | C221: China | D221: 385 | E221: 1240 | F221: 570
A222: ST 146 | B222: Stole | C222: China | D222: 315 | E222: 1030 | F222: 470
A223: ST 150 CD | B223: Stole | C223: China | D223: 290 | E223: 960 | F223: 450
A224: ST 150 VL | B224: Stole | C224: China | D224: 290 | E224: 960 | F224: 450
A225: ST 153 | B225: Stole | C225: China | D225: 240 | E225: 800 | F225: 370
... A295: c 974 | B295: Stole | C295: China | D295: 265 | E295: 880 | F295: 420

Sheet Wsp Lohi
A1: Art no. | B1: Item | C1: Quality | D1: Wsp | E1: Amazon | F1: With Box
A2: 120 | B2: Lohi | C2: polywool | D2: 710 | E2: 2160 | F2: 970
A3: 121 | B3: Lohi | C3: Fine Wool | D3: 4375 | E3: 14340 | F3: 6070
A4: 122 | B4: Lohi | C4: Fine Wool | D4: 1515 | E4: 4460 | F4: 1920
A5: 123 | B5: Lohi | C5: Fine Wool | D5: 2010 | E5: 6610 | F5: 2520
A6: 127 | B6: Lohi | C6: Fine Wool | D6: 1450 | E6: 4280 | F6: 1850
A7: 150 | B7: Lohi | C7: Fine Wool | D7: 1800 | E7: 3790 | F7: 2170
A8: 170 | B8: Lohi | C8: Fine Wool | D8: 1635 | E8: 3820 | F8: 2000
A9: 190 | B9: Lohi | C9: polywool | D9: 650 | E9: 1820 | F9: 870
A10: 191 | B10: Lohi | C10: poywool | D10: 975 | E10: 2860 | F10: 1270
A11: 192 | B11: Lohi | C11: polywool | D11: 645 | E11: 2180 | F11: 900
A12: 193 | B12: Lohi | C12: Fine Wool | D12: 3410 | E12: 10740 | F12: 4570
A13: 194 | B13: Lohi | C13: Fine Wool | D13: 1595 | E13: 4840 | F13: 2100
... A60: 4509 | B60: Lohi | C60: Polywool | D60: 85 | E60: 330 | F60: 200
A61: 1400 white/kesari | B61: Lohi | C61: Polywool | D61: 290 | E61: 870 | F61: 450
A62: 1403 | B62: lohi | C62: pashmina | D62: 6940 | E62: 23460 | F62: 11870
A63: 1404 | B63: lohi | C63: pashmina | D63: 7565 | E63: 25580 | F63: 12970
A64: 555 white/kesari | B64: Lohi | C64: Polywool | D64: 220 | E64: 650 | F64: 370
A65: 666 white/kesari | B65: Lohi | C65: Polywool | D65: 255 | E65: 760 | F65: 400
A66: 701 Check Lohi | B66: Lohi | C66: Polywool | D66: 400 | E66: 1280 | F66: 600
A67: Arjun | B67: Lohi | C67: Polywool | D67: 245 | E67: 820 | F67: 400
A68: Crystal no.4000 | B68: Lohi | C68: Polywool | D68: 130 | E68: 480 | F68: 250
A69: Crystal no.5000 | B69: Lohi | C69: Polywool | D69: 200 | E69: 710 | F69: 350
A70: Crystal no.6000 | B70: Lohi | C70: Polywool | D70: 190 | E70: 660 | F70: 320
A71: Crystal no.7000 | B71: Lohi | C71: Polywool | D71: 220 | E71: 750 | F71: 350
A72: Crystal no.8000 | B72: Lohi | C72: Polywool | D72: 365 | E72: 1200 | F72: 550
... A76: lohi sahil | B76: Lohi | C76: Polywool | D76: 400 | E76: 1300 | F76: 600

Sheet Wsp Suits
A1: Art no. | B1: Item | C1: Wsp | D1: Amazon | E1: With Box
A2: Suit Set No.610 | B2: suit | C2: 690 | D2: 2160 | E2: 880
A3: Suit Set No.611 | B3: suit | C3: 690 | D3: 2160 | E3: 880
A4: Suit Set No.612 | B4: suit | C4: 690 | D4: 2160 | E4: 880
A5: Suit Set No.613 | B5: suit | C5: 690 | D5: 2160 | E5: 880
A6: Suit Set No.614 | B6: suit | C6: 690 | D6: 2160 | E6: 880
A7: Suit Set No.839 | B7: suit | C7: 1015 | D7: 3140 | E7: 1270
A8: Suit Set No.846 | B8: suit | C8: 1015 | D8: 3140 | E8: 1270
A9: Suit Set No.849 | B9: suit | C9: 1015 | D9: 3140 | E9: 1270
A10: Suit Set No.832 | B10: suit | C10: 1015 | D10: 3140 | E10: 1270
A11: Suit Set No.833 | B11: suit | C11: 1015 | D11: 3140 | E11: 1270
A12: Suit Set No.834 | B12: suit | C12: 1015 | D12: 3140 | E12: 1270
A13: Suit Set No.836 | B13: suit | C13: 1015 | D13: 3140 | E13: 1270
... A48: Mercury | B48: suit | C48: 1595 | D48: 4840 | E48: 2100

Sheet Wsp 2500
A1: Art no. | B1: Item | C1: Quality | D1: Wsp
A2: 120 | B2: Lohi | C2: polywool | D2: 710
A3: 122 | B3: Lohi | C3: Fine Wool | D3: 1515
A4: 123 | B4: Lohi | C4: Fine Wool | D4: 2010
A5: 127 | B5: Lohi | C5: Fine Wool | D5: 1450
A6: 150 | B6: Lohi | C6: Fine Wool | D6: 1800
A7: 170 | B7: Lohi | C7: Fine Wool | D7: 1635
A8: 190 | B8: Lohi | C8: polywool | D8: 650
A9: 191 | B9: Lohi | C9: poywool | D9: 975
A10: 192 | B10: Lohi | C10: polywool | D10: 645
A11: 194 | B11: Lohi | C11: Fine Wool | D11: 1595
A12: 275 | B12: Lohi | C12: Polywool | D12: 270
A13: 276 | B13: Lohi | C13: Polywool | D13: 175
... A55: 4509 | B55: Lohi | C55: Polywool | D55: 85
A56: 1400 white/kesari | B56: Lohi | C56: Polywool | D56: 290
A57: 555 white/kesari | B57: Lohi | C57: Polywool | D57: 220
A58: 666 white/kesari | B58: Lohi | C58: Polywool | D58: 255
A59: 701 Check Lohi | B59: Lohi | C59: Polywool | D59: 400
A60: Arjun | B60: Lohi | C60: Polywool | D60: 245
A61: Crystal no.4000 | B61: Lohi | C61: Polywool | D61: 130
A62: Crystal no.5000 | B62: Lohi | C62: Polywool | D62: 200
A63: Crystal no.6000 | B63: Lohi | C63: Polywool | D63: 190
A64: Crystal no.7000 | B64: Lohi | C64: Polywool | D64: 220
A65: Crystal no.8000 | B65: Lohi | C65: Polywool | D65: 365
A66: Crystal no.9000 | B66: Lohi | C66: Polywool | D66: 280
A67: Dhariwal no.10000 | B67: Lohi | C67: Polywool | D67: 310
... A70: M1 | B70: muffler | C70: muffler | D70: 125
A71: 847 | B71: Odni | C71: Polywool | D71: 1140
A72: N3 | B72: Ponchu | C72: muffler | D72: 315
A73: P 14 | B73: Ponchu | C73: China | D73: 510
A74: P 169 | B74: Ponchu | C74: China | D74: 370
A75: P 171 | B75: Ponchu | C75: China | D75: 415
A76: P 8 | B76: Ponchu | C76: China | D76: 425
A77: 5201 | B77: scarf | C77: Polywool | D77: 280
A78: 101 | B78: shawl | C78: Wool | D78: 540
A79: 102 | B79: shawl | C79: wool | D79: 535
A80: 114 | B80: Shawl | C80: Polywool | D80: 425
A81: 115 | B81: shawl | C81: Fine Wool | D81: 1805
A82: 119 | B82: Shawl | C82: Fine Wool | D82: 1680
A83: 132 | B83: shawl | C83: Fine Wool | D83: 2230
A84: 134 | B84: Shawl | C84: Fine Wool | D84: 1190
